Workbook

Sheet 交付概览
A2: 保险条款采集累计交付台账
A3: 更新日期 | B3: 46321 | D3: D1–B28累计259条限定工单，阶段全审97份4250页。网站v126／索引v102已回验。
A5: D1–B14内容基线（保留） | B5: 数量 | C5: 单位 | D5: 验收边界
A6: 地区基线 | B6: =COUNTA('12地区基线'!A2:A13) -> 12 | C6: 个地区 | D6: 已列出范围。未核实的地区统计保持空白。
A7: 保司与来源索引 | B7: =COUNTA(保司与来源!A2:A243) -> 242 | C7: 条来源 | D7: 原有201条来源完整保留，追加B7–B14共41条。不是保司数或独立产品数。
A8: 十四批冻结任务基数 | B8: =SUM(B29:B30,B55:B58,B77:B84) -> 108 | C8: 条任务 | D8: D1–B6历史67条；B7–B14追加41条。各批冻结基数不随缺失行缩减。
A9: D1–B14任务行数 | B9: =COUNTA(首批固定任务!A2:A109) -> 108 | C9: 条任务 | D9: 按任务 ID 计，不是独立产品数或新取得文件数。
A10: D1–B14处理记录 | B10: =COUNTA(本批执行结果!A2:A109) -> 108 | C10: 条任务 | D10: 108条是限定证据工单。B10变体线索与B13/B14重复目标探测不增加独立产品。
A11: D1–B14证据验收 | B11: =COUNTIFS(本批执行结果!M2:M109,"已验收") -> 108 | C11: 条任务 | D11: 需要复核通过、证据、有效日期及范围匹配。并非产品齐备数。
A12: D1–B14现存页全审 | B12: =SUMIFS(本批执行结果!F2:F109,本批执行结果!M2:M109,"已验收") -> 45 | C12: 份文件 | D12: 累计45份既存原件、1243物理页全审；含通用组件和非合同说明，不等于45套产品合同。
A13: 目标主文缺口关闭 | B13: =SUMIFS(本批执行结果!H2:H109,本批执行结果!M2:M109,"已验收") -> 0 | C13: 项 | D13: 各批目标主文／独立产品缺口新增关闭均0。独立产品分母未核定，不计算市场覆盖率。
A14: D1期初任务单位 | B14: 条数 | C14: 单位 | D14: 说明
A15: 产品路线核验 | B15: =COUNTIFS(首批固定任务!F2:F13,A15) -> 4 | C15: 条任务 | D15: 香港固定 4 个产品路线。可交付明确缺口，不等于已取得主文。
A16: 产品组件核验 | B16: =COUNTIFS(首批固定任务!F2:F13,A16) -> 1 | C16: 条任务 | D16: 核 Travel Protector 的现行 COVID-19 扩展／批单。
A17: 产品版本核验 | B17: =COUNTIFS(首批固定任务!F2:F13,A17) -> 1 | C17: 条任务 | D17: 核 Home Protector 360 06/20 采用关系，不代入 Basic。
A18: 文档核验 | B18: =COUNTIFS(首批固定任务!F2:F13,A18) -> 6 | C18: 条任务 | D18: 新加坡 1 份页序核验，马来西亚 5 份 Master 文档共 114 页。
A20: 历史存量（非本批新增）
A21: 指标 | B21: 历史数量 | C21: 单位 | D21: 口径
A22: 原件 | B22: =SUM('12地区基线'!D2:D13) -> 4710 | C22: 份文件 | D22: v89 历史存量，含公开原件 4,659 与隔离文件 51。
A23: 已全文审阅 | B23: =SUM('12地区基线'!E2:E13) -> 2245 | C23: 份文件 | D23: v89 历史全文审阅数量，不代表全市场覆盖。
A24: 严格通过 | B24: =SUM('12地区基线'!F2:F13) -> 411 | C24: 份文件 | D24: v89 严格主文文件数，不是 411 个完整产品。
A25: 隔离文件 | B25: =SUM('12地区基线'!G2:G13) -> 51 | C25: 份文件 | D25: v89 保留隔离文件，属于历史原件，不与原件再相加。
A27: 分批冻结与验收
A28: 批次 | B28: 冻结任务 | C28: 证据验收 | D28: 分批边界
A29: D1首批 | B29: 12 | C29: =COUNTIFS(本批执行结果!N2:N24,"D1",本批执行结果!M2:M24,"已验收") -> 12 | D29: 期初12条／验收0。现增5份全审114页及3份支持原件，均已发布。
A30: B2第二批 | B30: 11 | C30: =COUNTIFS(本批执行结果!N2:N24,"B2",本批执行结果!M2:M24,"已验收") -> 11 | D30: 期初11条／验收0。新增6份全审205页、主文角色4份已发布，合同问题仍待核。
A31: D1+B2历史累计 | B31: =SUM(B29:B30) -> 23 | C31: =SUM(C29:C30) -> 23 | D31: 只汇总证据交付。首批不重复计数，受阻与未完成范围不删除。
A33: 累计增量与未解项 | B33: 数量 | C33: 单位 | D33: 说明
A34: D1–B14全审页数 | B34: =SUMIFS(本批执行结果!P2:P109,本批执行结果!M2:M109,"已验收") -> 1243 | C34: 页 | D34: 1243页仅为现存文件全页审读。EASYCare视觉32页、Traveller英文13页及ID18页部分审读不混入。
A35: 新增支持原件 | B35: =SUMIFS(本批执行结果!E2:E109,本批执行结果!M2:M109,"已验收") -> 3 | C35: 份 | D35: 仅D1取得3份支持原件；B2–B14新增原件均0。
A36: 严格通过新增 | B36: =SUMIFS(本批执行结果!G2:G109,本批执行结果!M2:M109,"已验收") -> 3 | C36: 份 | D36: 文件级严格净增3：B8两份、B12 PA Direct一份。与当前采用、个人齐套及产品闭合分别计。
A37: 语言依赖未解 | B37: =SUMIFS(本批执行结果!R2:R109,本批执行结果!M2:M109,"已验收") -> 3 | C37: 份 | D37: EASYCare／Traveller高棉语及ID优先印尼语语义等未解决；有限任务完成不消除语言依赖。
A38: B2新增主文角色 | B38: =SUMIFS(本批执行结果!Q2:Q24,本批执行结果!M2:M24,"已验收") -> 4 | C38: 份 | D38: 4份文件角色已确认，但均仍待核验，不计产品齐套。
A40: 发布与固定索引 | B40: 数量 | C40: 单位 | D40: 状态与口径
A41: 已发布正式原件 | B41: 4713 | C41: 份 | D41: 网站v126／私有索引v102；正式4713、公开4662、隔离51不变。
A42: 其中公开原件 | B42: 4662 | C42: 份 | D42: 公开原件4,662，隔离文件51。两者合计4,713。
A43: 已发布全文审阅 | B43: 2342 | C43: 份 | D43: 当前全文2342；B28新增全文0，阶段97份4250页不变。
A44: B2已发布全文增量 | B44: =SUMIFS(本批执行结果!F2:F24,本批执行结果!N2:N24,"B2",本批执行结果!M2:M24,"已验收") -> 6 | C44: 份 | D44: 新增6份已进入线上版本115。网站已更新第二批核验状态；原件与详审证据私有留存。
A45: 第三批已验收任务 | B45: 10 | C45: 项 | D45: 10项限定任务已验收并发布：5份全文184页，2路线、2历史关系、1英文部分审读。
A46: 范围与重复报警 | B46: =MAX(COUNTIFS(本批执行结果!S2:S109,"缺范围或重复"),B8-COUNTA(首批固定任务!A2:A109),B8-COUNTA(本批执行结果!A2:A109),0) -> 0 | C46: 项 | D46: 必须为0。缺少冻结范围、重复任务或缺失执行记录均须检查。
A47: 已发布部分核验 | B47: 17 | C47: 份 | D47: 网站v126／索引v102：部分17、主角色2749、严格423。
A48: 更新任务 | D48: 在“本批执行结果”更新复核与证据。冻结表保留各批原始期初，不覆盖历史。
A49: 筛选核对 | D49: 执行表及冻结表可按批次、地区、保司、状态筛选。原始ID保持稳定。
A50: 缺项处理 | D50: 空白表示未核实而非零。独立产品分母未定，不计算全市场覆盖率。
A53: B3–B6增量与累计 | B53: 数量 | C53: 单位 | D53: 严格边界
A54: 批次 | B54: 冻结任务 | C54: 证据验收 | D54: 范围说明
A55: B3第三批 | B55: 10 | C55: =COUNTIFS(本批执行结果!N2:N68,"B3",本批执行结果!M2:M68,"已验收") -> 10 | D55: 5份现存全文184页；文件主文角色净增4。含VN附约纠偏−1，严格／产品闭合0。
A56: B4第四批 | B56: 10 | C56: =COUNTIFS(本批执行结果!N2:N68,"B4",本批执行结果!M2:M68,"已验收") -> 10 | D56: 7份全文213页：MY5份198页＋MM2组件15页；ID18页partial。身份4版本／31关系不重计。
A57: B5第五批 | B57: 12 | C57: =COUNTIFS(本批执行结果!N2:N68,"B5",本批执行结果!M2:M68,"已验收") -> 12 | D57: 12条香港有限路线，7个live 200／5个摘录HTTP未知；零原件、全文、主文、严格或闭合。
A58: B6第六批 | B58: 12 | C58: =COUNTIFS(本批执行结果!N2:N68,"B6",本批执行结果!M2:M68,"已验收") -> 12 | D58: 12条SG限定路线、11个唯一官方URL；零原件／全文／严格／闭合，294身份层并非全市场分母。
A59: D1–B6历史累计 | B59: =SUM(B29:B30,B55:B58) -> 67 | C59: =SUM(C29:C30,C55:C58) -> 67 | D59: 任务完成、取得原件、全文、文件主角色及产品闭合互不替代。
A60: 累计新增原件 | B60: =SUMIFS(本批执行结果!U2:U109,本批执行结果!M2:M109,"已验收") -> 3 | C60: 份 | D60: 3份全部为D1支持原件，不能当作主文。
A61: 文件主角色净增 | B61: =SUMIFS(本批执行结果!Q2:Q109,本批执行结果!M2:M109,"已验收") -> 26 | C61: 份 | D61: D1–B6净+13；B7 +3、B8 +5、B12 +5，共+26。仅文件主角色，不是26个产品或齐套。
A62: 当前公开合同包闭合 | B62: 0 | C62: 项 | D62: 没有新增已证当前齐备包；未核定不是已证明永不存在。
A63: 当前采用／现售 | B63: 未核定 | C63: 状态 | D63: 目录列示、历史具名合同、材料关联和最新批单均不能自动证明当前采用或现售。
A64: B4/B5/B6内容验收 | B64: 已完成 | C64: 状态 | D64: 仅计最终独立QA接受范围；与对外发布状态分开。
A65: B4/B5/B6发布 | B65: 已发布并回验 | C65: 状态 | D65: 实际网站v117／固定索引v93已据成功发布和精确回验回执确认。
A66: 来源QA纠正 | B66: 已落实 | C66: 状态 | D66: 10Life为旧版广告主供稿、非独立佐证／授权销售；HSBC含policy文件名仍属册。
A67: 访问不确定 | B67: 保留 | C67: 状态 | D67: BOCHK超时与缓存缺失不等于站方拒绝、来源HTTP状态或无主文。
A68: 权利边界 | B68: 独立保留 | C68: 说明 | D68: 原件可读或全文已审，不授予复制、打印、转载、再托管或商业复用许可。
A70: 网站入口（回执） | B70: v126 | C70: 公开网站 | D70: https://hong-kong-insurance-library.balabalaniuniu.chatgpt.site
A71: 私有索引状态 | B71: v102 | C71: 已同步回验 | D71: 三个固定索引原生v102及精确远端字节、独立终态、双私有指针均确认。
A75: B7–B14追加验收 | B75: 数量 | C75: 单位 | D75: 范围与边界
A76: 批次 | B76: 冻结任务 | C76: 证据验收 | D76: 范围说明
A77: B7 | B77: 8 | C77: =COUNTIFS(本批执行结果!N2:N109,"B7",本批执行结果!M2:M109,"已验收") -> 8 | D77: 8份125页：MY主合同3份85页，MM组件5份40页。主角色+3，严格0。
A78: B8 | B78: 5 | C78: =COUNTIFS(本批执行结果!N2:N109,"B8",本批执行结果!M2:M109,"已验收") -> 5 | D78: 5份104页全审，主角色+5，文件严格+2；其余3份结构／引用问题保留。
A79: B9 | B79: 12 | C79: =COUNTIFS(本批执行结果!N2:N109,"B9",本批执行结果!M2:M109,"已验收") -> 12 | D79: 12个既有家族的有限路线。原件、全文、主文、严格和闭合均0。
A80: B10 | B80: 1 | C80: =COUNTIFS(本批执行结果!N2:N109,"B10",本批执行结果!M2:M109,"已验收") -> 1 | D80: 1条Harvest两年缴费变体线索，不是新增独立产品；403后停止。
A81: B11 | B81: 4 | C81: =COUNTIFS(本批执行结果!N2:N109,"B11",本批执行结果!M2:M109,"已验收") -> 4 | D81: 4份103页非合同说明。新增1项历史解释支持关系，3候选未定；不升主文或采用。
A82: B12 | B82: 5 | C82: =COUNTIFS(本批执行结果!N2:N109,"B12",本批执行结果!M2:M109,"已验收") -> 5 | D82: 5份195页零售主文，主角色+5。仅PA Direct文件严格+1，其余4项保留hold。
A83: B13 | B83: 4 | C83: =COUNTIFS(本批执行结果!N2:N109,"B13",本批执行结果!M2:M109,"已验收") -> 4 | D83: 4条恢复路线。无新PDF；正文哈希缺失，浏览器证据重建限制明确。
A84: B14 | B84: 2 | C84: =COUNTIFS(本批执行结果!N2:N109,"B14",本批执行结果!M2:M109,"已验收") -> 2 | D84: 2次Trinity标签探测，未取得PDF。元数据时间为区间／上界，不是精确事件时刻。
A85: D1–B14累计 | B85: =B8 -> 108 | C85: =B11 -> 108 | D85: 108个限定工单。新原件、全审、主角色、严格及产品齐套分别统计。
A86: B7–B10发布 | B86: 已发布并回验 | C86: 状态 | D86: 实际网站v118／索引v94，已据成功回执与精确远端字节回验确认。
A87: B11–B14内容 | B87: 已验收 | C87: 状态 | D87: 此段保留B11–B14内容验收。B15–B18另列角色层，不增加本段全文或严格数量。
A88: B11–B14发布 | B88: 已发布并回验 | C88: 状态 | D88: 网站v119成功部署，固定索引v95已精确回验并通过终态QA；B15及后续批次不纳入。
A89: 当前已发布主角色 | B89: 2749 | C89: 份文件 | D89: 网站v126／索引v102主角色2749；B28主角色增量0。
A90: 当前已发布严格 | B90: 423 | C90: 份文件 | D90: B28仅恢复B24-012文件级verified，严格＋1至423；当前B24为3verified／17needs_review。
A91: 历史解释支持关系 | B91: 1 | C91: 项 | D91: B11仅1项同编号／同持有人历史关系。合同并入、准确版次配对和当前采用未证。
A92: B13响应正文身份 | B92: 不能回证 | C92: 状态 | D92: 未留正文及正文哈希。元数据文件SHA不能充作HTTP响应正文SHA。
A93: B14动作时间 | B93: 区间／上界 | C93: 状态 | D93: 下载等待先于点击设置；不能称点击后完整10秒或精确点击／超时时刻。
A94: 个人合同齐套闭合 | B94: 0 | C94: 项 | D94: 没有新增已证个人完整合同包；未核定不等于永久不存在。
A95: 当前采用确认新增 | B95: 0 | C95: 项 | D95: 不从文件级verified、目录、历史编号或支持关系推导。
A96: 后续批次边界 | B96: 新增角色层90条 | C96: 说明 | D96: 原258工单及角色历史保留；B28仅另增1条状态纠正工单，累计259。
A100: B15–B18角色层与累计 | B100: 数量 | C100: 单位 | D100: 角色验收不等于全文或产品验收
A101: 原D1–B14冻结工单 | B101: =B8 -> 108 | C101: 条 | D101: 原执行／冻结明细108条保留；不是108个产品。
A102: 新增角色限定工单 | B102: =COUNTA('B15–B18角色验收'!A2:A91) -> 90 | C102: 条 | D102: 90个SHA互异原件；只确认角色及身份锚点。
A103: D1–B18历史限定范围 | B103: =SUM(B101:B102) -> 198 | C103: 条 | D103: 原108＋角色90；不增加原件库存，不计算独立产品覆盖率。
A104: 角色证据已验收 | B104: =COUNTIF('B15–B18角色验收'!AH2:AH91,"角色已验收") -> 90 | C104: 条 | D104: 执行与独立QA锚点已核对；本段保留角色验收时90份待全文快照，后续结果另列。
A105: 合格文件主角色提议 | B105: =SUM('B15–B18角色验收'!Q2:Q91) -> 77 | C105: 份 | D105: B15 3＋B16 27＋B17 30＋B18 17＝77；只提议文件角色，不采用来源产品／持有人身份。
A106: 非合同CIS | B106: =SUM('B15–B18角色验收'!R2:R91) -> 7 | C106: 份 | D106: B15七份只属信息说明，不能替代主合同。
A107: 主角色映射保留 | B107: =SUM('B15–B18角色验收'!S2:S91) -> 6 | C107: 份 | D107: B16三份＋B18三份；6项身份／变体／语言冲突保留，不强行升格。
A108: 本轮已发布主角色新增 | B108: =SUM('B15–B18角色验收'!T2:T91) -> 77 | C108: 份 | D108: 网站v120及固定索引v96已纳入本轮77项限定文件主角色；6项映射保留，7份CIS不升主文。
A109: 网站已发布主角色合计 | B109: =B89 -> 2749 | C109: 份 | D109: 当前网站v126／索引v102主角色2749；历史角色纠正不重计。
A110: 角色库存物理页 | B110: =SUM('B15–B18角色验收'!H2:H91) -> 5186 | C110: 页 | D110: 5186页是文件总页数，不是审读量。
A111: 执行锚点文件页对 | B111: =SUM('B15–B18角色验收'!K2:K91) -> 945 | C111: 对 | D111: 945仅为各文件选页的有限锚点；不是选中页全文通读。
A112: 独立QA锚点文件页对 | B112: =SUM('B15–B18角色验收'!M2:M91) -> 627 | C112: 对 | D112: 627与执行945分别计；不能相加当作完整审读。
A113: 角色阶段待全文快照 | B113: =COUNTIF('B15–B18角色验收'!N2:N91,"待全文") -> 90 | C113: 份 | D113: 冻结角色90份待全文是历史状态，不改写。B19后为4全审、1部分、85未尝试，86仍未全审。
A114: 期初全文待核快照 | B114: 138 | C114: 条 | D114: 历史期初138不改写；不能把角色验收90写成全文完成90。
A115: 角色新增全文／严格 | B115: =SUM('B15–B18角色验收'!O2:P91) -> 0 | C115: 份 | D115: 本轮全文、严格、当前采用、齐套、独立产品与产品缺口闭合均0。
...

Sheet 本批执行结果
A1: 任务ID | B1: 地区 | C1: 处理状态 | D1: 本批结论 | E1: 新支持材料 | F1: 现存页全文核验 | G1: 严格新增 | H1: 缺口关闭 | I1: 复核状态 | J1: 复核证据 | K1: 处理完成日 | L1: 后续动作 | M1: 验收判定 | N1: 批次 | O1: 保司 | P1: 新增全文页数 | Q1: 新增主文角色 | R1: 语言依赖未解 | S1: 范围匹配 | T1: 内容状态 | U1: 新增原件 | V1: 文件角色／审读范围 | W1: 产品主文可得性 | X1: 当前公开合同包 | Y1: 当前采用／现售 | Z1: 来源证据类型 | AA1: 重要边界 | AB1: 原始文件／族ID
A2: D1-HK-001 | B2: 香港 | C2: 已复核 | D2: 官方页及产品册集中库只见宣传册；BEA专属产品页仅链接产品册。BEA册第16物理页排除合同角色，第23页列银行版本。10Life具体场景页未见文档下载链接。 | E2: 1 | F2: 0 | G2: 0 | H2: 0 | I2: 通过 | J2: 公开路线及支持件角色/SHA已复核；准确既有产品下正式新增1份银行宣传册（未全文），完整主文仍未取得，现存页全文/严格通过/缺口关闭增量0。 | K2: 46321 | L2: 取得用户提供的匿名官方保单样本，或经另外明确授权后向AIA索取准确版次样本；若出现独立公开同族主文URL可继续定点查验。 | M2: =IF(S2<>"匹配","缺范围任务",IF(I2="通过",IF(AND(J2<>"",ISNUMBER(K2),K2>=DATE(2026,10,26)),"已验收","缺证据或日期"),IF(I2="","缺状态","待复核"))) -> 已验收 | N2: D1 | O2: AIA 友邦香港 | P2: 0 | Q2: 0 | R2: 0 | S2: =IF(AND(A2<>"",N2<>"",COUNTIFS(首批固定任务!$A$2:$A$109,A2,首批固定任务!$N$2:$N$109,N2)=1,COUNTIFS($A$2:$A$109,A2)=1),"匹配","缺范围或重复") -> 匹配 | T2: 保留首批内容结论，不代表产品齐备 | U2: =E2 -> 1 | V2: 沿用D1/B2已验收结论 | W2: 沿用D1/B2结论，不新增推断 | X2: 未认定齐备 | Y2: 未由本次更新确认 | Z2: D1/B2冻结验收历史 | AA2: 新增列仅分层说明；原有任务结论与来源不覆盖。 | AB2: aia-simply-love-encore-5
A3: D1-HK-002 | B3: 香港 | C3: 已复核 | D3: 官网只提供产品册和Policy Services册；表格库未见本族主文。服务册的具体服务条款不能当整份主合同，SHA与基线相同。10Life命中Elite场景标签，不将其当独立合同版次或泛化覆盖。另查新发现的DBS独立产品页，普通访问返回403后停止；不表示所有公开来源已穷尽。 | E3: 0 | F3: 0 | G3: 0 | H3: 0 | I3: 通过 | J3: 公开路线处理证据及支持件角色/SHA已复核；完整主文未取得，未补齐产品，正式原件／现存页全审／严格通过增量均0。 | K3: 46321 | L3: 保持该受限入口停止。仅在获得新的公开主文入口或明确授权索取准确官方样本后继续。 | M3: =IF(S3<>"匹配","缺范围任务",IF(I3="通过",IF(AND(J3<>"",ISNUMBER(K3),K3>=DATE(2026,10,26)),"已验收","缺证据或日期"),IF(I3="","缺状态","待复核"))) -> 已验收 | N3: D1 | O3: Manulife 宏利香港 | P3: 0 | Q3: 0 | R3: 0 | S3: =IF(AND(A3<>"",N3<>"",COUNTIFS(首批固定任务!$A$2:$A$109,A3,首批固定任务!$N$2:$N$109,N3)=1,COUNTIFS($A$2:$A$109,A3)=1),"匹配","缺范围或重复") -> 匹配 | T3: 保留首批内容结论，不代表产品齐备 | U3: =E3 -> 0 | V3: 沿用D1/B2已验收结论 | W3: 沿用D1/B2结论，不新增推断 | X3: 未认定齐备 | Y3: 未由本次更新确认 | Z3: D1/B2冻结验收历史 | AA3: 新增列仅分层说明；原有任务结论与来源不覆盖。 | AB3: manulife-goldenstart
A4: D1-HK-003 | B4: 香港 | C4: 已复核 | D4: 中英官网确认产品名、承保主体及样本须另索取；下载库仅服务/理赔表，未见本族主文。复用昨日SC目录定点定位本族册链接，今日取得48物理页银行册；鷹宇公开介绍未见主文附件。 | E4: 1 | F4: 0 | G4: 0 | H4: 0 | I4: 通过 | J4: 公开路线及支持件角色/SHA已复核；准确既有产品下正式新增1份银行宣传册（未全文），完整主文仍未取得，现存页全文/严格通过/缺口关闭增量0。 | K4: 46321 | L4: 取得准确PHOR版次的官方匿名保单样本，或另外明确授权向Prudential索取；保留香港与澳门版本隔离。 | M4: =IF(S4<>"匹配","缺范围任务",IF(I4="通过",IF(AND(J4<>"",ISNUMBER(K4),K4>=DATE(2026,10,26)),"已验收","缺证据或日期"),IF(I4="","缺状态","待复核"))) -> 已验收 | N4: D1 | O4: Prudential 保诚香港 | P4: 0 | Q4: 0 | R4: 0 | S4: =IF(AND(A4<>"",N4<>"",COUNTIFS(首批固定任务!$A$2:$A$109,A4,首批固定任务!$N$2:$N$109,N4)=1,COUNTIFS($A$2:$A$109,A4)=1),"匹配","缺范围或重复") -> 匹配 | T4: 保留首批内容结论，不代表产品齐备 | U4: =E4 -> 1 | V4: 沿用D1/B2已验收结论 | W4: 沿用D1/B2结论，不新增推断 | X4: 未认定齐备 | Y4: 未由本次更新确认 | Z4: D1/B2冻结验收历史 | AA4: 新增列仅分层说明；原有任务结论与来源不覆盖。 | AB4: prudential-prime-horizon-insurance-plan
A5: D1-HK-004 | B5: 香港 | C5: 已复核 | D5: 官网及Find a form未见本族主文；大新专页只提供产品册；本地公开介绍链接亦为产品册。大新册第23页说明非保险合同且样本应要求提供。 | E5: 1 | F5: 0 | G5: 0 | H5: 0 | I5: 通过 | J5: 公开路线及支持件角色/SHA已复核；准确既有产品下正式新增1份银行宣传册（未全文），完整主文仍未取得，现存页全文/严格通过/缺口关闭增量0。 | K5: 46321 | L5: 取得Sun Life发出的匿名保单文件样本，或另外明确授权索取；当前公开册不能代替准确合同版本。 | M5: =IF(S5<>"匹配","缺范围任务",IF(I5="通过",IF(AND(J5<>"",ISNUMBER(K5),K5>=DATE(2026,10,26)),"已验收","缺证据或日期"),IF(I5="","缺状态","待复核"))) -> 已验收 | N5: D1 | O5: Sun Life 永明香港 | P5: 0 | Q5: 0 | R5: 0 | S5: =IF(AND(A5<>"",N5<>"",COUNTIFS(首批固定任务!$A$2:$A$109,A5,首批固定任务!$N$2:$N$109,N5)=1,COUNTIFS($A$2:$A$109,A5)=1),"匹配","缺范围或重复") -> 匹配 | T5: 保留首批内容结论，不代表产品齐备 | U5: =E5 -> 1 | V5: 沿用D1/B2已验收结论 | W5: 沿用D1/B2结论，不新增推断 | X5: 未认定齐备 | Y5: 未由本次更新确认 | Z5: D1/B2冻结验收历史 | AA5: 新增列仅分层说明；原有任务结论与来源不覆盖。 | AB5: sunlife-royalfortune
A6: D1-SG-001 | B6: 新加坡 | C6: 已复核 | D6: 现行官方目录、SingSaver与Marsh公开销售页均核过。SingSaver当前链接所得26页主文与既有2024基准原件同SHA；Marsh也链接同一官方主文。新增两条采用/渠道关系，不新增原件或全文；1026册40–48项COVID扩展仍未取得，合同包未齐。 | E6: 0 | F6: 0 | G6: 0 | H6: 0 | I6: 通过 | J6: 同SHA26页基准主文复用；新增2条渠道链接关系，COVID批单仍缺；正式原件／现存页全审／严格通过增量0。 | K6: 46321 | L6: 待用户提供或另行授权取得现行明确采用的COVID扩展/批单；不得用旧候选、宣传册或基础主文推定补齐。 | M6: =IF(S6<>"匹配","缺范围任务",IF(I6="通过",IF(AND(J6<>"",ISNUMBER(K6),K6>=DATE(2026,10,26)),"已验收","缺证据或日期"),IF(I6="","缺状态","待复核"))) -> 已验收 | N6: D1 | O6: Allied World Assurance Company, Ltd (Singapore Branch) | P6: 0 | Q6: 0 | R6: 0 | S6: =IF(AND(A6<>"",N6<>"",COUNTIFS(首批固定任务!$A$2:$A$109,A6,首批固定任务!$N$2:$N$109,N6)=1,COUNTIFS($A$2:$A$109,A6)=1),"匹配","缺范围或重复") -> 匹配 | T6: 保留首批内容结论，不代表产品齐备 | U6: =E6 -> 0 | V6: 沿用D1/B2已验收结论 | W6: 沿用D1/B2结论，不新增推断 | X6: 未认定齐备 | Y6: 未由本次更新确认 | Z6: D1/B2冻结验收历史 | AA6: 新增列仅分层说明；原有任务结论与来源不覆盖。 | AB6: SG-F-c279cfe77714176e
A7: D1-SG-002 | B7: 新加坡 | C7: 已复核 | D7: 当前官方页仍分别链接0326的360和Basic宣传册。既有360册四页无06/20准确主文链接或采用声明；名称、表列利益相似及官网资产可检索不等于版次采用。未找到替代主文或准确采用证据；360与Basic保持隔离。 | E7: 0 | F7: 0 | G7: 0 | H7: 0 | I7: 通过 | J7: 21页06/20既有主文复用；现行采用未证，Basic隔离；正式原件／现存页全审／严格通过增量0。 | K7: 46321 | L7: 待精确采用声明、现行主文包或独立Basic正文证据；现有360全文记录保留但不升级现行家族覆盖。 | M7: =IF(S7<>"匹配","缺范围任务",IF(I7="通过",IF(AND(J7<>"",ISNUMBER(K7),K7>=DATE(2026,10,26)),"已验收","缺证据或日期"),IF(I7="","缺状态","待复核"))) -> 已验收 | N7: D1 | O7: Allied World Assurance Company, Ltd (Singapore Branch) | P7: 0 | Q7: 0 | R7: 0 | S7: =IF(AND(A7<>"",N7<>"",COUNTIFS(首批固定任务!$A$2:$A$109,A7,首批固定任务!$N$2:$N$109,N7)=1,COUNTIFS($A$2:$A$109,A7)=1),"匹配","缺范围或重复") -> 匹配 | T7: 保留首批内容结论，不代表产品齐备 | U7: =E7 -> 0 | V7: 沿用D1/B2已验收结论 | W7: 沿用D1/B2结论，不新增推断 | X7: 未认定齐备 | Y7: 未由本次更新确认 | Z7: D1/B2冻结验收历史 | AA7: 新增列仅分层说明；原有任务结论与来源不覆盖。 | AB7: SG-F-14656bec56df8d86
A8: D1-SG-003 | B8: 新加坡 | C8: 已复核 | D8: 本地原件SHA复验一致，21物理页逐页页码与版式复核；正文2–20连续，34项目录定位均吻合，3.16投诉在20页正常收尾后为封底。内部未见跳号不等于已证完整：页脚总数24仍未获出版者解释，维持候选/完整性未核，不推定缺3页。官方当前文库普通GET返回403后停止。 | E8: 0 | F8: 0 | G8: 0 | H8: 0 | I8: 通过 | J8: 21物理页及34目录项定位通过；页脚总数24疑点未解；既有全文审阅完成、家族主文不计入、仍待核验不变，现存页全审增量0。 | K8: 46321 | L8: 仅在获得公开出版者同版勘误、明确新原件或用户提供权威说明后再解除页序疑点；未授权外联/登录前保持受阻。 | M8: =IF(S8<>"匹配","缺范围任务",IF(I8="通过",IF(AND(J8<>"",ISNUMBER(K8),K8>=DATE(2026,10,26)),"已验收","缺证据或日期"),IF(I8="","缺状态","待复核"))) -> 已验收 | N8: D1 | O8: Utmost Worldwide Limited (Singapore Branch) | P8: 0 | Q8: 0 | R8: 0 | S8: =IF(AND(A8<>"",N8<>"",COUNTIFS(首批固定任务!$A$2:$A$109,A8,首批固定任务!$N$2:$N$109,N8)=1,COUNTIFS($A$2:$A$109,A8)=1),"匹配","缺范围或重复") -> 匹配 | T8: 保留首批内容结论，不代表产品齐备 | U8: =E8 -> 0 | V8: 沿用D1/B2已验收结论 | W8: 沿用D1/B2结论，不新增推断 | X8: 未认定齐备 | Y8: 未由本次更新确认 | Z8: D1/B2冻结验收历史 | AA8: 新增列仅分层说明；原有任务结论与来源不覆盖。 | AB8: SG-4330cfac28a50f2e
A9: D1-MY-001 | B9: 马来西亚 | C9: 已复核 | D9: 已逐页审读24页。保费表印页2未见；其标准或个别化性质未定。主体及主保单身份已辨识，当前采用未证，不升严格通过。 | E9: 0 | F9: 1 | G9: 0 | H9: 0 | I9: 通过 | J9: 原件SHA、物理页与逐页文字/视觉证据核对通过；现存页全文核验+1（合计5份114页），合同完整性仍待核、合同完整未确认、严格通过增量0；不要求真实个人专属附表。 | K9: 46321 | L9: 核实精确公开采用证据及附表性质，不索取真实客户私人资料。 | M9: =IF(S9<>"匹配","缺范围任务",IF(I9="通过",IF(AND(J9<>"",ISNUMBER(K9),K9>=DATE(2026,10,26)),"已验收","缺证据或日期"),IF(I9="","缺状态","待复核"))) -> 已验收 | N9: D1 | O9: Sun Life Malaysia Assurance Berhad | P9: 24 | Q9: 0 | R9: 0 | S9: =IF(AND(A9<>"",N9<>"",COUNTIFS(首批固定任务!$A$2:$A$109,A9,首批固定任务!$N$2:$N$109,N9)=1,COUNTIFS($A$2:$A$109,A9)=1),"匹配","缺范围或重复") -> 匹配 | T9: 保留首批内容结论，不代表产品齐备 | U9: =E9 -> 0 | V9: 沿用D1/B2已验收结论 | W9: 沿用D1/B2结论，不新增推断 | X9: 未认定齐备 | Y9: 未由本次更新确认 | Z9: D1/B2冻结验收历史 | AA9: 新增列仅分层说明；原有任务结论与来源不覆盖。 | AB9: MY-SUN-005
A10: D1-MY-002 | B10: 马来西亚 | C10: 已复核 | D10: 已逐页审读37页双语内容。BIZS001主保单表未见，角色仍待区分；不能据页码跳跃断言通用保障条文缺失。当前渠道采用未证。 | E10: 0 | F10: 1 | G10: 0 | H10: 0 | I10: 通过 | J10: 原件SHA、物理页与逐页文字/视觉证据核对通过；现存页全文核验+1（合计5份114页），合同完整性仍待核、合同完整未确认、严格通过增量0；不要求真实个人专属附表。 | K10: 46321 | L10: 核实精确公开采用证据及附表性质，不索取真实客户私人资料。 | M10: =IF(S10<>"匹配","缺范围任务",IF(I10="通过",IF(AND(J10<>"",ISNUMBER(K10),K10>=DATE(2026,10,26)),"已验收","缺证据或日期"),IF(I10="","缺状态","待复核"))) -> 已验收 | N10: D1 | O10: Sun Life Malaysia Assurance Berhad | P10: 37 | Q10: 0 | R10: 0 | S10: =IF(AND(A10<>"",N10<>"",COUNTIFS(首批固定任务!$A$2:$A$109,A10,首批固定任务!$N$2:$N$109,N10)=1,COUNTIFS($A$2:$A$109,A10)=1),"匹配","缺范围或重复") -> 匹配 | T10: 保留首批内容结论，不代表产品齐备 | U10: =E10 -> 0 | V10: 沿用D1/B2已验收结论 | W10: 沿用D1/B2结论，不新增推断 | X10: 未认定齐备 | Y10: 未由本次更新确认 | Z10: D1/B2冻结验收历史 | AA10: 新增列仅分层说明；原有任务结论与来源不覆盖。 | AB10: MY-SUN-002
A11: D1-MY-003 | B11: 马来西亚 | C11: 已复核 | D11: 已逐页审读14页。GTTAD001/003/004/005在件；GTTAD002未见，性质未定。活动标签并不证明正文采用或当前销售。 | E11: 0 | F11: 1 | G11: 0 | H11: 0 | I11: 通过 | J11: 原件SHA、物理页与逐页文字/视觉证据核对通过；现存页全文核验+1（合计5份114页），合同完整性仍待核、合同完整未确认、严格通过增量0；不要求真实个人专属附表。 | K11: 46321 | L11: 核实精确公开采用证据及附表性质，不索取真实客户私人资料。 | M11: =IF(S11<>"匹配","缺范围任务",IF(I11="通过",IF(AND(J11<>"",ISNUMBER(K11),K11>=DATE(2026,10,26)),"已验收","缺证据或日期"),IF(I11="","缺状态","待复核"))) -> 已验收 | N11: D1 | O11: Sun Life Malaysia Takaful Berhad | P11: 14 | Q11: 0 | R11: 0 | S11: =IF(AND(A11<>"",N11<>"",COUNTIFS(首批固定任务!$A$2:$A$109,A11,首批固定任务!$N$2:$N$109,N11)=1,COUNTIFS($A$2:$A$109,A11)=1),"匹配","缺范围或重复") -> 匹配 | T11: 保留首批内容结论，不代表产品齐备 | U11: =E11 -> 0 | V11: 沿用D1/B2已验收结论 | W11: 沿用D1/B2结论，不新增推断 | X11: 未认定齐备 | Y11: 未由本次更新确认 | Z11: D1/B2冻结验收历史 | AA11: 新增列仅分层说明；原有任务结论与来源不覆盖。 | AB11: MY-SUN-029
A12: D1-MY-004 | B12: 马来西亚 | C12: 已复核 | D12: 已逐页审读13页，印页1–12连续；GTT002是已包含的保障表，公开标准正文完整。具体活动采用与当前可用性仍未证。 | E12: 0 | F12: 1 | G12: 0 | H12: 0 | I12: 通过 | J12: 原件SHA、物理页与逐页文字/视觉证据核对通过；现存页全文核验+1（合计5份114页），合同完整性仍待核、合同完整未确认、严格通过增量0；不要求真实个人专属附表。 | K12: 46321 | L12: 核实精确公开采用证据及附表性质，不索取真实客户私人资料。 | M12: =IF(S12<>"匹配","缺范围任务",IF(I12="通过",IF(AND(J12<>"",ISNUMBER(K12),K12>=DATE(2026,10,26)),"已验收","缺证据或日期"),IF(I12="","缺状态","待复核"))) -> 已验收 | N12: D1 | O12: Sun Life Malaysia Takaful Berhad | P12: 13 | Q12: 0 | R12: 0 | S12: =IF(AND(A12<>"",N12<>"",COUNTIFS(首批固定任务!$A$2:$A$109,A12,首批固定任务!$N$2:$N$109,N12)=1,COUNTIFS($A$2:$A$109,A12)=1),"匹配","缺范围或重复") -> 匹配 | T12: 保留首批内容结论，不代表产品齐备 | U12: =E12 -> 0 | V12: 沿用D1/B2已验收结论 | W12: 沿用D1/B2结论，不新增推断 | X12: 未认定齐备 | Y12: 未由本次更新确认 | Z12: D1/B2冻结验收历史 | AA12: 新增列仅分层说明；原有任务结论与来源不覆盖。 | AB12: MY-SUN-031
A13: D1-MY-005 | B13: 马来西亚 | C13: 已复核 | D13: 已逐页审读26页马来文。确认MRTTFB20及2020-07-01批单；主要给付及费用条文在件。MRTT002未见、性质待核；当前采用未证。 | E13: 0 | F13: 1 | G13: 0 | H13: 0 | I13: 通过 | J13: 原件SHA、物理页与逐页文字/视觉证据核对通过；现存页全文核验+1（合计5份114页），合同完整性仍待核、合同完整未确认、严格通过增量0；不要求真实个人专属附表。 | K13: 46321 | L13: 核实精确公开采用证据及附表性质，不索取真实客户私人资料。 | M13: =IF(S13<>"匹配","缺范围任务",IF(I13="通过",IF(AND(J13<>"",ISNUMBER(K13),K13>=DATE(2026,10,26)),"已验收","缺证据或日期"),IF(I13="","缺状态","待复核"))) -> 已验收 | N13: D1 | O13: Sun Life Malaysia Takaful Berhad | P13: 26 | Q13: 0 | R13: 0 | S13: =IF(AND(A13<>"",N13<>"",COUNTIFS(首批固定任务!$A$2:$A$109,A13,首批固定任务!$N$2:$N$109,N13)=1,COUNTIFS($A$2:$A$109,A13)=1),"匹配","缺范围或重复") -> 匹配 | T13: 保留首批内容结论，不代表产品齐备 | U13: =E13 -> 0 | V13: 沿用D1/B2已验收结论 | W13: 沿用D1/B2结论，不新增推断 | X13: 未认定齐备 | Y13: 未由本次更新确认 | Z13: D1/B2冻结验收历史 | AA13: 新增列仅分层说明；原有任务结论与来源不覆盖。 | AB13: MY-SUN-077
... A24: B2-KH-002 | B24: 柬埔寨 | C24: 证据已复核 | D24: 18页现存全文通过；p6暂停恢复与p10终止、p4-5 >2小时与p12 >=2小时、p8购单条件与当前FAQ、p18诉期措辞冲突未解决。仍待核验/严格新增0；理赔表是服务包缺件非主文核心缺件。 | E24: 0 | F24: 1 | G24: 0 | H24: 0 | I24: 通过 | J24: 现存18页逐页文本与视觉证据已独立验收。 18页现存全文通过；p6暂停恢复与p10终止、p4-5 >2小时与p12 >=2小时、p8购单条件与当前FAQ、p18诉期措辞冲突未解决。仍待核验/严格新增0；理赔表是服务包缺件非主文核心缺件。 | K24: 46321 | L24: 依准确引用页核实附表性质、采用关系及条文差异。未解决前保持待核验，不计产品齐备。 | M24: =IF(S24<>"匹配","缺范围任务",IF(I24="通过",IF(AND(J24<>"",ISNUMBER(K24),K24>=DATE(2026,10,26)),"已验收","缺证据或日期"),IF(I24="","缺状态","待复核"))) -> 已验收 | N24: B2 | O24: Forte Insurance (Cambodia) PLC. | P24: 18 | Q24: 1 | R24: 0 | S24: =IF(AND(A24<>"",N24<>"",COUNTIFS(首批固定任务!$A$2:$A$109,A24,首批固定任务!$N$2:$N$109,N24)=1,COUNTIFS($A$2:$A$109,A24)=1),"匹配","缺范围或重复") -> 匹配 | T24: 现存页全文已审，合同问题仍待核验 | U24: =E24 -> 0 | V24: 沿用D1/B2已验收结论 | W24: 沿用D1/B2结论，不新增推断 | X24: 未认定齐备 | Y24: 未由本次更新确认 | Z24: D1/B2冻结验收历史 | AA24: 新增列仅分层说明；原有任务结论与来源不覆盖。 | AB24: KH-tuneprotect-current
A25: B3-MY-001 | B25: 马来西亚 | C25: 证据已复核 | D25: 现存34页全文审读已验收；具名主条款角色已核，附表／版本／语言或关联材料问题仍待核。 | E25: 0 | F25: 1 | G25: 0 | H25: 0 | I25: 通过 | J25: B3独立QA · B3-MY-001；34物理页现存文件全文证据。 | K25: 46321 | L25: 仅按已记录引用页和问题定点核证；未解除前不计严格或当前合同包齐备，不索取真实客户资料。 | M25: =IF(S25<>"匹配","缺范围任务",IF(I25="通过",IF(AND(J25<>"",ISNUMBER(K25),K25>=DATE(2026,10,26)),"已验收","缺证据或日期"),IF(I25="","缺状态","待复核"))) -> 已验收 | N25: B3 | O25: Sun Life Malaysia Assurance Berhad | P25: 34 | Q25: 1 | R25: 0 | S25: =IF(AND(A25<>"",N25<>"",COUNTIFS(首批固定任务!$A$2:$A$109,A25,首批固定任务!$N$2:$N$109,N25)=1,COUNTIFS($A$2:$A$109,A25)=1),"匹配","缺范围或重复") -> 匹配 | T25: 现存页全文已审，合同／适用仍待核 | U25: 0 | V25: 具名主合同材料；仍待核验 | W25: 既存具名主文材料，当前适用未核 | X25: 未确认齐备 | Y25: 未核定（不等于否定） | Z25: 既存原件／既有验收事实；非本批重新下载 | AA25: 全文仅指该SHA现存全部页面；不代表当前标准合同包齐全。 | AB25: MY-SUN-006
A26: B3-MY-002 | B26: 马来西亚 | C26: 证据已复核 | D26: 现存48页全文审读已验收；具名主条款角色已核，附表／版本／语言或关联材料问题仍待核。 | E26: 0 | F26: 1 | G26: 0 | H26: 0 | I26: 通过 | J26: B3独立QA · B3-MY-002；48物理页现存文件全文证据。 | K26: 46321 | L26: 仅按已记录引用页和问题定点核证；未解除前不计严格或当前合同包齐备，不索取真实客户资料。 | M26: =IF(S26<>"匹配","缺范围任务",IF(I26="通过",IF(AND(J26<>"",ISNUMBER(K26),K26>=DATE(2026,10,26)),"已验收","缺证据或日期"),IF(I26="","缺状态","待复核"))) -> 已验收 | N26: B3 | O26: Sun Life Malaysia Assurance Berhad | P26: 48 | Q26: 1 | R26: 0 | S26: =IF(AND(A26<>"",N26<>"",COUNTIFS(首批固定任务!$A$2:$A$109,A26,首批固定任务!$N$2:$N$109,N26)=1,COUNTIFS($A$2:$A$109,A26)=1),"匹配","缺范围或重复") -> 匹配 | T26: 现存页全文已审，合同／适用仍待核 | U26: 0 | V26: 具名主合同材料；仍待核验 | W26: 既存具名主文材料，当前适用未核 | X26: 未确认齐备 | Y26: 未核定（不等于否定） | Z26: 既存原件／既有验收事实；非本批重新下载 | AA26: 全文仅指该SHA现存全部页面；不代表当前标准合同包齐全。 | AB26: MY-SUN-019
A27: B3-MY-003 | B27: 马来西亚 | C27: 证据已复核 | D27: 现存23页全文审读已验收；具名主条款角色已核，附表／版本／语言或关联材料问题仍待核。 | E27: 0 | F27: 1 | G27: 0 | H27: 0 | I27: 通过 | J27: B3独立QA · B3-MY-003；23物理页现存文件全文证据。 | K27: 46321 | L27: 仅按已记录引用页和问题定点核证；未解除前不计严格或当前合同包齐备，不索取真实客户资料。 | M27: =IF(S27<>"匹配","缺范围任务",IF(I27="通过",IF(AND(J27<>"",ISNUMBER(K27),K27>=DATE(2026,10,26)),"已验收","缺证据或日期"),IF(I27="","缺状态","待复核"))) -> 已验收 | N27: B3 | O27: Sun Life Malaysia Takaful Berhad | P27: 23 | Q27: 1 | R27: 0 | S27: =IF(AND(A27<>"",N27<>"",COUNTIFS(首批固定任务!$A$2:$A$109,A27,首批固定任务!$N$2:$N$109,N27)=1,COUNTIFS($A$2:$A$109,A27)=1),"匹配","缺范围或重复") -> 匹配 | T27: 现存页全文已审，合同／适用仍待核 | U27: 0 | V27: 具名主合同材料；仍待核验 | W27: 既存具名主文材料，当前适用未核 | X27: 未确认齐备 | Y27: 未核定（不等于否定） | Z27: 既存原件／既有验收事实；非本批重新下载 | AA27: 全文仅指该SHA现存全部页面；不代表当前标准合同包齐全。 | AB27: MY-SUN-043
A28: B3-MY-004 | B28: 马来西亚 | C28: 证据已复核 | D28: 现存41页全文审读已验收；具名主条款角色已核，附表／版本／语言或关联材料问题仍待核。 | E28: 0 | F28: 1 | G28: 0 | H28: 0 | I28: 通过 | J28: B3独立QA · B3-MY-004；41物理页现存文件全文证据。 | K28: 46321 | L28: 仅按已记录引用页和问题定点核证；未解除前不计严格或当前合同包齐备，不索取真实客户资料。 | M28: =IF(S28<>"匹配","缺范围任务",IF(I28="通过",IF(AND(J28<>"",ISNUMBER(K28),K28>=DATE(2026,10,26)),"已验收","缺证据或日期"),IF(I28="","缺状态","待复核"))) -> 已验收 | N28: B3 | O28: Sun Life Malaysia Takaful Berhad | P28: 41 | Q28: 1 | R28: 0 | S28: =IF(AND(A28<>"",N28<>"",COUNTIFS(首批固定任务!$A$2:$A$109,A28,首批固定任务!$N$2:$N$109,N28)=1,COUNTIFS($A$2:$A$109,A28)=1),"匹配","缺范围或重复") -> 匹配 | T28: 现存页全文已审，合同／适用仍待核 | U28: 0 | V28: 具名主合同材料；仍待核验 | W28: 既存具名主文材料，当前适用未核 | X28: 未确认齐备 | Y28: 未核定（不等于否定） | Z28: 既存原件／既有验收事实；非本批重新下载 | AA28: 全文仅指该SHA现存全部页面；不代表当前标准合同包齐全。 | AB28: MY-SUN-080
A29: B3-MY-005 | B29: 马来西亚 | C29: 证据已复核 | D29: 现存38页全文审读已验收；具名主条款角色已核，附表／版本／语言或关联材料问题仍待核。 | E29: 0 | F29: 1 | G29: 0 | H29: 0 | I29: 通过 | J29: B3独立QA · B3-MY-005；38物理页现存文件全文证据。 | K29: 46321 | L29: 仅按已记录引用页和问题定点核证；未解除前不计严格或当前合同包齐备，不索取真实客户资料。 | M29: =IF(S29<>"匹配","缺范围任务",IF(I29="通过",IF(AND(J29<>"",ISNUMBER(K29),K29>=DATE(2026,10,26)),"已验收","缺证据或日期"),IF(I29="","缺状态","待复核"))) -> 已验收 | N29: B3 | O29: Sun Life Malaysia Takaful Berhad | P29: 38 | Q29: 1 | R29: 0 | S29: =IF(AND(A29<>"",N29<>"",COUNTIFS(首批固定任务!$A$2:$A$109,A29,首批固定任务!$N$2:$N$109,N29)=1,COUNTIFS($A$2:$A$109,A29)=1),"匹配","缺范围或重复") -> 匹配 | T29: 现存页全文已审，合同／适用仍待核 | U29: 0 | V29: 具名主合同材料；仍待核验 | W29: 既存具名主文材料，当前适用未核 | X29: 未确认齐备 | Y29: 未核定（不等于否定） | Z29: 既存原件／既有验收事实；非本批重新下载 | AA29: 全文仅指该SHA现存全部页面；不代表当前标准合同包齐全。 | AB29: MY-SUN-097
A30: B3-HK-001 | B30: 香港 | C30: 证据已复核 | D30: 限定已记录公开路线证据已验收；未取得确切目标主文，缺口保留。 | E30: 0 | F30: 0 | G30: 0 | H30: 0 | I30: 通过 | J30: B3独立QA · B3-HK-001；限定公开路线证据。 | K30: 46321 | L30: 有新的准确公开主文入口或明确索取授权时再继续；不重复负面路线、不猜隐藏链接。 | M30: =IF(S30<>"匹配","缺范围任务",IF(I30="通过",IF(AND(J30<>"",ISNUMBER(K30),K30>=DATE(2026,10,26)),"已验收","缺证据或日期"),IF(I30="","缺状态","待复核"))) -> 已验收 | N30: B3 | O30: HSBC Life | P30: 0 | Q30: 0 | R30: 0 | S30: =IF(AND(A30<>"",N30<>"",COUNTIFS(首批固定任务!$A$2:$A$109,A30,首批固定任务!$N$2:$N$109,N30)=1,COUNTIFS($A$2:$A$109,A30)=1),"匹配","缺范围或重复") -> 匹配 | T30: 限定路线完成，主文仍缺 | U30: 0 | V30: 产品页／支持资料，不是主文 | W30: 未取得目标主文 | X30: 未确认齐备 | Y30: 未核定（不等于否定） | Z30: 保存的官方公开响应：HTTP 200 | AA30: 只覆盖保存的响应或摘录；不是全网无主文、穷尽路线或当前在售证明。 | AB30: hsbc-goal-access-universal-education
A31: B3-HK-002 | B31: 香港 | C31: 证据已复核 | D31: 限定已记录公开路线证据已验收；未取得确切目标主文，缺口保留。 | E31: 0 | F31: 0 | G31: 0 | H31: 0 | I31: 通过 | J31: B3独立QA · B3-HK-002；限定公开路线证据。 | K31: 46321 | L31: 有新的准确公开主文入口或明确索取授权时再继续；不重复负面路线、不猜隐藏链接。 | M31: =IF(S31<>"匹配","缺范围任务",IF(I31="通过",IF(AND(J31<>"",ISNUMBER(K31),K31>=DATE(2026,10,26)),"已验收","缺证据或日期"),IF(I31="","缺状态","待复核"))) -> 已验收 | N31: B3 | O31: Hang Seng Insurance | P31: 0 | Q31: 0 | R31: 0 | S31: =IF(AND(A31<>"",N31<>"",COUNTIFS(首批固定任务!$A$2:$A$109,A31,首批固定任务!$N$2:$N$109,N31)=1,COUNTIFS($A$2:$A$109,A31)=1),"匹配","缺范围或重复") -> 匹配 | T31: 限定路线完成，主文仍缺 | U31: 0 | V31: 产品页／支持资料，不是主文 | W31: 未取得目标主文 | X31: 未确认齐备 | Y31: 未核定（不等于否定） | Z31: 保存的官方公开响应：HTTP 200 | AA31: 只覆盖保存的响应或摘录；不是全网无主文、穷尽路线或当前在售证明。 | AB31: hangseng-legend-power-supreme
A32: B3-VN-001 | B32: 越南 | C32: 证据已复核 | D32: 历史精确材料关联2项已验收；当前版本采用仍待核。不新增全文或主文。 | E32: 0 | F32: 0 | G32: 0 | H32: 0 | I32: 通过 | J32: B3独立QA · B3-VN-001；精确历史材料关系证据。 | K32: 46321 | L32: 仅按已记录引用页和问题定点核证；未解除前不计严格或当前合同包齐备，不索取真实客户资料。 | M32: =IF(S32<>"匹配","缺范围任务",IF(I32="通过",IF(AND(J32<>"",ISNUMBER(K32),K32>=DATE(2026,10,26)),"已验收","缺证据或日期"),IF(I32="","缺状态","待复核"))) -> 已验收 | N32: B3 | O32: Công ty TNHH Manulife (Việt Nam) | P32: 0 | Q32: 0 | R32: 0 | S32: =IF(AND(A32<>"",N32<>"",COUNTIFS(首批固定任务!$A$2:$A$109,A32,首批固定任务!$N$2:$N$109,N32)=1,COUNTIFS($A$2:$A$109,A32)=1),"匹配","缺范围或重复") -> 匹配 | T32: 身份／关系／角色已核，不是产品闭合 | U32: 0 | V32: 仅历史材料关系核验 | W32: 当前目标版本采用未核 | X32: 未确认齐备 | Y32: 未核定（不等于否定） | Z32: 既存原件／既有验收事实；非本批重新下载 | AA32: 关系证据不等于全文；不合并资料组或产品。 | AB32: VN-539a4a42cb94
A33: B3-VN-002 | B33: 越南 | C33: 证据已复核 | D33: 历史精确材料关联2项已验收；当前版本采用仍待核。纠正附约被当主合同的角色，主文净减1。 | E33: 0 | F33: 0 | G33: 0 | H33: 0 | I33: 通过 | J33: B3独立QA · B3-VN-002；精确历史材料关系证据。 | K33: 46321 | L33: 仅按已记录引用页和问题定点核证；未解除前不计严格或当前合同包齐备，不索取真实客户资料。 | M33: =IF(S33<>"匹配","缺范围任务",IF(I33="通过",IF(AND(J33<>"",ISNUMBER(K33),K33>=DATE(2026,10,26)),"已验收","缺证据或日期"),IF(I33="","缺状态","待复核"))) -> 已验收 | N33: B3 | O33: Công ty TNHH Manulife (Việt Nam) | P33: 0 | Q33: -1 | R33: 0 | S33: =IF(AND(A33<>"",N33<>"",COUNTIFS(首批固定任务!$A$2:$A$109,A33,首批固定任务!$N$2:$N$109,N33)=1,COUNTIFS($A$2:$A$109,A33)=1),"匹配","缺范围或重复") -> 匹配 | T33: 身份／关系／角色已核，不是产品闭合 | U33: 0 | V33: 附约／补充条款，不是独立主合同 | W33: 当前目标版本采用未核 | X33: 未确认齐备 | Y33: 未核定（不等于否定） | Z33: 既存原件／既有验收事实；非本批重新下载 | AA33: 关系证据不等于全文；不合并资料组或产品。 | AB33: VN-32f604533d33
A34: B3-KH-001 | B34: 柬埔寨 | C34: 证据已复核 | D34: 仅第13–25页英文部分共13物理页已审，12页高棉语法律语义待核；整份保持部分核验。 | E34: 0 | F34: 0 | G34: 0 | H34: 0 | I34: 通过 | J34: B3独立QA · B3-KH-001；13页英文证据；高棉语未审。 | K34: 46321 | L34: 需要可靠高棉语审读并核双语一致及版本；未解除前保持部分核验。 | M34: =IF(S34<>"匹配","缺范围任务",IF(I34="通过",IF(AND(J34<>"",ISNUMBER(K34),K34>=DATE(2026,10,26)),"已验收","缺证据或日期"),IF(I34="","缺状态","待复核"))) -> 已验收 | N34: B3 | O34: Forte Insurance (Cambodia) Plc. | P34: 0 | Q34: 0 | R34: 1 | S34: =IF(AND(A34<>"",N34<>"",COUNTIFS(首批固定任务!$A$2:$A$109,A34,首批固定任务!$N$2:$N$109,N34)=1,COUNTIFS($A$2:$A$109,A34)=1),"匹配","缺范围或重复") -> 匹配 | T34: 部分审读，语言依赖未解 | U34: 0 | V34: 主文候选，当前采用未核 | W34: 有既存候选，产品主文仍未严格确立 | X34: 未确认齐备 | Y34: 未核定（不等于否定） | Z34: 既存原件／既有验收事实；非本批重新下载 | AA34: 仅英文部分，不称整份全文；语言优先关系未定。 | AB34: KH-forte-travel-search
A35: B4-MY-001 | B35: 马来西亚 | C35: 证据已复核 | D35: 25页现存英文主合同全文已审；具名GTTPW合同及附表已核，目录活动名不证明当前采用，条文关系仍待核。 | E35: 0 | F35: 1 | G35: 0 | H35: 0 | I35: 通过 | J35: B4独立QA · B4-MY-001；25物理页现存文件全文证据。 | K35: 46321 | L35: 仅按已记录引用页和问题定点核证；未解除前不计严格或当前合同包齐备，不索取真实客户资料。 | M35: =IF(S35<>"匹配","缺范围任务",IF(I35="通过",IF(AND(J35<>"",ISNUMBER(K35),K35>=DATE(2026,10,26)),"已验收","缺证据或日期"),IF(I35="","缺状态","待复核"))) -> 已验收 | N35: B4 | O35: Sun Life Malaysia Takaful Berhad | P35: 25 | Q35: 1 | R35: 0 | S35: =IF(AND(A35<>"",N35<>"",COUNTIFS(首批固定任务!$A$2:$A$109,A35,首批固定任务!$N$2:$N$109,N35)=1,COUNTIFS($A$2:$A$109,A35)=1),"匹配","缺范围或重复") -> 匹配 | T35: 现存页全文已审，合同／适用仍待核 | U35: 0 | V35: 文件主合同角色已核，仍待核验 | W35: 有既存条款材料，当前产品采用未核 | X35: 未确认齐备 | Y35: 未核定（不等于否定） | Z35: 既存原件／既有验收事实；非本批重新下载 | AA35: 仅现存页面与文件角色；目录活动名与正文具名采用分别判断。 | AB35: MY-SUN-024
A36: B4-MY-002 | B36: 马来西亚 | C36: 证据已复核 | D36: 27页现存英文主合同全文已审；引用附表未附，CIMB／Salary Account目录标签不替代正文具名身份；仍待核。 | E36: 0 | F36: 1 | G36: 0 | H36: 0 | I36: 通过 | J36: B4独立QA · B4-MY-002；27物理页现存文件全文证据。 | K36: 46321 | L36: 仅按已记录引用页和问题定点核证；未解除前不计严格或当前合同包齐备，不索取真实客户资料。 | M36: =IF(S36<>"匹配","缺范围任务",IF(I36="通过",IF(AND(J36<>"",ISNUMBER(K36),K36>=DATE(2026,10,26)),"已验收","缺证据或日期"),IF(I36="","缺状态","待复核"))) -> 已验收 | N36: B4 | O36: Sun Life Malaysia Takaful Berhad | P36: 27 | Q36: 1 | R36: 0 | S36: =IF(AND(A36<>"",N36<>"",COUNTIFS(首批固定任务!$A$2:$A$109,A36,首批固定任务!$N$2:$N$109,N36)=1,COUNTIFS($A$2:$A$109,A36)=1),"匹配","缺范围或重复") -> 匹配 | T36: 现存页全文已审，合同／适用仍待核 | U36: 0 | V36: 文件主合同角色已核，仍待核验 | W36: 有既存条款材料，当前产品采用未核 | X36: 未确认齐备 | Y36: 未核定（不等于否定） | Z36: 既存原件／既有验收事实；非本批重新下载 | AA36: 仅现存页面与文件角色；目录活动名与正文具名采用分别判断。 | AB36: MY-SUN-032
... A109: B14-HK-002 | B109: 香港 | C109: 证据已复核 | D109: Trinity TripCover条款标签单次只读点击，下载等待超时；无文档URL／PDF。未重试旧404路线。 | E109: 0 | F109: 0 | G109: 0 | H109: 0 | I109: 通过 | J109: B14独立QA · B14-HK-002；限定路线证据，原件／全文增量0。 | K109: 46321 | L109: 保留当前停止点；仅新确切公开证据或明确授权可重开，不重复负面探测或猜测路径。 | M109: =IF(S109<>"匹配","缺范围任务",IF(I109="通过",IF(AND(J109<>"",ISNUMBER(K109),K109>=DATE(2026,10,26)),"已验收","缺证据或日期"),IF(I109="","缺状态","待复核"))) -> 已验收 | N109: B14 | O109: Trinity General Insurance Company Limited | P109: 0 | Q109: 0 | R109: 0 | S109: =IF(AND(A109<>"",N109<>"",COUNTIFS(首批固定任务!$A$2:$A$109,A109,首批固定任务!$N$2:$N$109,N109)=1,COUNTIFS($A$2:$A$109,A109)=1),"匹配","缺范围或重复") -> 匹配 | T109: 限定路线完成；目标主文未取得 | U109: 0 | V109: 公开路线／线索，无已取得主文 | W109: 未确立目标产品主文可得 | X109: 未确认齐备 | Y109: 未核定（不等于否定） | Z109: 普通浏览器只读点击的保存元数据摘录；HTTP未知 | AA109: 保存的是工具元数据摘录，不是完整原始轨迹。时间为动作前后／等待完成上界；截图未保存供独立视觉复核。 | AB109: LABEL:9464feb717becffdb641ebbb

Sheet 首批固定任务
A1: 任务ID | B1: 地区 | C1: 保司 | D1: 产品／组件 | E1: 原始产品ID | F1: 任务单位 | G1: 交付要求 | H1: 期初状态 | I1: 期初下一步 | J1: 来源ID | K1: 期初验收证据 | L1: 期初完成日 | M1: 期初验收判定 | N1: 批次
A2: D1-HK-001 | B2: 香港 | C2: AIA 友邦香港 | D2: 「簡愛‧延續」儲蓄保險計劃5 | E2: aia-simply-love-encore-5 | F2: 产品路线核验 | G2: 保留准确产品身份、页面/附件URL、访问时间与结果；主文取得与路线处理完成分开；无正文仍可交付明确缺口，不算产品齐备 | H2: 已冻结 | I2: 按该产品官方页及可见附件逐项检查；有明确同产品销售来源才进入第二层；取得匹配主文即转核验，否则记录缺件与停止原因 | J2: SRC-D1-HK-001 | M2: =IF(H2="已验收",IF(AND(K2<>"",ISNUMBER(L2)),"已验收","缺证据或日期"),IF(H2="","缺状态","未验收")) -> 未验收 | N2: D1
A3: D1-HK-002 | B3: 香港 | C3: Manulife 宏利香港 | D3: 宏瑞終身即期年金保險計劃 | E3: manulife-goldenstart | F3: 产品路线核验 | G3: 保留准确产品身份、页面/附件URL、访问时间与结果；主文取得与路线处理完成分开；无正文仍可交付明确缺口，不算产品齐备 | H3: 已冻结 | I3: 按该产品官方页及可见附件逐项检查；有明确同产品销售来源才进入第二层；取得匹配主文即转核验，否则记录缺件与停止原因 | J3: SRC-D1-HK-002 | M3: =IF(H3="已验收",IF(AND(K3<>"",ISNUMBER(L3)),"已验收","缺证据或日期"),IF(H3="","缺状态","未验收")) -> 未验收 | N3: D1
A4: D1-HK-003 | B4: 香港 | C4: Prudential 保诚香港 | D4: Prime Horizon Insurance Plan | E4: prudential-prime-horizon-insurance-plan | F4: 产品路线核验 | G4: 保留准确产品身份、页面/附件URL、访问时间与结果；主文取得与路线处理完成分开；无正文仍可交付明确缺口，不算产品齐备 | H4: 已冻结 | I4: 按该产品官方页及可见附件逐项检查；有明确同产品销售来源才进入第二层；取得匹配主文即转核验，否则记录缺件与停止原因 | J4: SRC-D1-HK-003 | M4: =IF(H4="已验收",IF(AND(K4<>"",ISNUMBER(L4)),"已验收","缺证据或日期"),IF(H4="","缺状态","未验收")) -> 未验收 | N4: D1
A5: D1-HK-004 | B5: 香港 | C5: Sun Life 永明香港 | D5: 永譽傳承儲蓄計劃 | E5: sunlife-royalfortune | F5: 产品路线核验 | G5: 保留准确产品身份、页面/附件URL、访问时间与结果；主文取得与路线处理完成分开；无正文仍可交付明确缺口，不算产品齐备 | H5: 已冻结 | I5: 按该产品官方页及可见附件逐项检查；有明确同产品销售来源才进入第二层；取得匹配主文即转核验，否则记录缺件与停止原因 | J5: SRC-D1-HK-004 | M5: =IF(H5="已验收",IF(AND(K5<>"",ISNUMBER(L5)),"已验收","缺证据或日期"),IF(H5="","缺状态","未验收")) -> 未验收 | N5: D1
A6: D1-SG-001 | B6: 新加坡 | C6: Allied World Assurance Company, Ltd (Singapore Branch) | D6: Travel Protector 2024基准主文的现行COVID-19扩展/批单 | E6: SG-F-c279cfe77714176e | F6: 产品组件核验 | G6: 取得准确组件且有采用依据，或交付确定缺件与已查路线；保留已核26页主文，不升级整套齐备 | H6: 已冻结 | I6: 仅围绕当前官方1026宣传册40–48项COVID保障寻找明确采用的扩展或批单；比对2024主文第14页COVID除外及计划差异 | J6: SRC-D1-SG-001 | M6: =IF(H6="已验收",IF(AND(K6<>"",ISNUMBER(L6)),"已验收","缺证据或日期"),IF(H6="","缺状态","未验收")) -> 未验收 | N6: D1
A7: D1-SG-002 | B7: 新加坡 | C7: Allied World Assurance Company, Ltd (Singapore Branch) | D7: Home Protector 360 06/20版的现行采用与Basic隔离 | E7: SG-F-14656bec56df8d86 | F7: 产品版本核验 | G7: 提供准确版次采用证据或保持未证；360与Basic分开；不把宣传册目录2018/09当版本 | H7: 已冻结 | I7: 核0326官方宣传册/产品页是否明确采用06/20主文或有替代版；Basic单列缺口，不把360套给Basic | J7: SRC-D1-SG-002 | M7: =IF(H7="已验收",IF(AND(K7<>"",ISNUMBER(L7)),"已验收","缺证据或日期"),IF(H7="","缺状态","未验收")) -> 未验收 | N7: D1
A8: D1-SG-003 | B8: 新加坡 | C8: Utmost Worldwide Limited (Singapore Branch) | D8: FOCUS UWWS PR00030 09/25页序与完整性 | E8: SG-4330cfac28a50f2e | F8: 文档核验 | G8: 逐页页码/内容连续性记录及缺页判定依据；未能消除疑点则保留未完整，不升级主文缺口或新增文件 | H8: 已冻结 | I8: 仅核现有21物理页与正文页脚24页标注的关系；对照目录/段落/末页和官方同版说明，不因物理页差直接断言缺3页 | J8: SRC-D1-SG-003 | M8: =IF(H8="已验收",IF(AND(K8<>"",ISNUMBER(L8)),"已验收","缺证据或日期"),IF(H8="","缺状态","未验收")) -> 未验收 | N8: D1
A9: D1-MY-001 | B9: 马来西亚 | C9: Sun Life Malaysia Assurance Berhad | D9: Cancer Plan Master Policy | E9: MY-SUN-005 | F9: 文档核验 | G9: 逐页完成清单+角色与主体/渠道结论+版次或未知标记+缺件矩阵；扫描/多语言无法可靠判断时维持待审，不因文本提取或Master文件名升级 | H9: 已冻结 | I9: 校对全部页码及正文可读性；确定法律主体、团体/个人与渠道、正文版次及角色；列引用证书/附约依赖和疑点页码；按文档记录实测时间 | J9: SRC-D1-MY-001 | M9: =IF(H9="已验收",IF(AND(K9<>"",ISNUMBER(L9)),"已验收","缺证据或日期"),IF(H9="","缺状态","未验收")) -> 未验收 | N9: D1
A10: D1-MY-002 | B10: 马来西亚 | C10: Sun Life Malaysia Assurance Berhad | D10: Biz Shield Master Policy | E10: MY-SUN-002 | F10: 文档核验 | G10: 逐页完成清单+角色与主体/渠道结论+版次或未知标记+缺件矩阵；扫描/多语言无法可靠判断时维持待审，不因文本提取或Master文件名升级 | H10: 已冻结 | I10: 校对全部页码及正文可读性；确定法律主体、团体/个人与渠道、正文版次及角色；列引用证书/附约依赖和疑点页码；按文档记录实测时间 | J10: SRC-D1-MY-002 | M10: =IF(H10="已验收",IF(AND(K10<>"",ISNUMBER(L10)),"已验收","缺证据或日期"),IF(H10="","缺状态","未验收")) -> 未验收 | N10: D1
A11: D1-MY-003 | B11: 马来西亚 | C11: Sun Life Malaysia Takaful Berhad | D11: Group Term Takaful (GTT ADB) Master Contract - ILP Protection Campaign | E11: MY-SUN-029 | F11: 文档核验 | G11: 逐页完成清单+角色与主体/渠道结论+版次或未知标记+缺件矩阵；扫描/多语言无法可靠判断时维持待审，不因文本提取或Master文件名升级 | H11: 已冻结 | I11: 校对全部页码及正文可读性；确定法律主体、团体/个人与渠道、正文版次及角色；列引用证书/附约依赖和疑点页码；按文档记录实测时间 | J11: SRC-D1-MY-003 | M11: =IF(H11="已验收",IF(AND(K11<>"",ISNUMBER(L11)),"已验收","缺证据或日期"),IF(H11="","缺状态","未验收")) -> 未验收 | N11: D1
A12: D1-MY-004 | B12: 马来西亚 | C12: Sun Life Malaysia Takaful Berhad | D12: Group Term Takaful (GTT) Master Contract - Protection with Purpose roadshow Campaign | E12: MY-SUN-031 | F12: 文档核验 | G12: 逐页完成清单+角色与主体/渠道结论+版次或未知标记+缺件矩阵；扫描/多语言无法可靠判断时维持待审，不因文本提取或Master文件名升级 | H12: 已冻结 | I12: 校对全部页码及正文可读性；确定法律主体、团体/个人与渠道、正文版次及角色；列引用证书/附约依赖和疑点页码；按文档记录实测时间 | J12: SRC-D1-MY-004 | M12: =IF(H12="已验收",IF(AND(K12<>"",ISNUMBER(L12)),"已验收","缺证据或日期"),IF(H12="","缺状态","未验收")) -> 未验收 | N12: D1
A13: D1-MY-005 | B13: 马来西亚 | C13: Sun Life Malaysia Takaful Berhad | D13: Mortgage Reducing Term Takaful with Funeral Benefit 2020 Master Contract | E13: MY-SUN-077 | F13: 文档核验 | G13: 逐页完成清单+角色与主体/渠道结论+版次或未知标记+缺件矩阵；扫描/多语言无法可靠判断时维持待审，不因文本提取或Master文件名升级 | H13: 已冻结 | I13: 校对全部页码及正文可读性；确定法律主体、团体/个人与渠道、正文版次及角色；列引用证书/附约依赖和疑点页码；按文档记录实测时间 | J13: SRC-D1-MY-005 | M13: =IF(H13="已验收",IF(AND(K13<>"",ISNUMBER(L13)),"已验收","缺证据或日期"),IF(H13="","缺状态","未验收")) -> 未验收 | N13: D1
... A109: B14-HK-002 | B109: 香港 | C109: Trinity General Insurance Company Limited | D109: Trinity TripCover policy wording control | E109: LABEL:9464feb717becffdb641ebbb | F109: 限定只读标签探测 | G109: 仅按冻结范围与独立QA验收，不自动升级原件、主文、严格或产品闭合。 | H109: 已冻结 | I109: 限定已记录公开路线；记录停止原因，不猜路径或绕过限制。 | J109: SRC-B14-HK-002 | M109: =IF(H109="已验收",IF(AND(K109<>"",ISNUMBER(L109)),"已验收","缺证据或日期"),IF(H109="","缺状态","未验收")) -> 未验收 | N109: B14

Sheet 12地区基线
A1: 地区码 | B1: 地区 | C1: 基线状态 | D1: 正式文件 | E1: 已全文审阅 | F1: 严格通过 | G1: 隔离文件 | H1: 范围家族数 | I1: 已识别主合同 | J1: 待补主合同 | K1: 本批重点 | L1: 最近检查 | M1: 来源索引 | N1: 统计说明
A2: HK | B2: 香港 | C2: 已有文件，继续核验 | D2: 2326 | E2: 1132 | F2: 146 | G2: 26 | H2: 203 | I2: 36 | J2: 167 | K2: 先核未逐项检查缺口；分开未检查、未取得、受限和待授权。 | L2: 46320 | M2: 香港：52 条来源 | N2: 仅限定储蓄203族；不是全市场在售或独立产品分母。。储蓄限定203族中167缺主文；上一轮55族仅逐查16族，另112族仅逐查15族及7家公司代表路线，未逐项全查。
A3: SG | B3: 新加坡 | C3: 已有文件，继续核验 | D3: 496 | E3: 420 | F3: 94 | G3: 2 | H3: 144 | I3: 115 | J3: 29 | K3: 先核确切版本和组件依赖；144窄口径与294族投影分开。 | L3: 46320 | M3: 新加坡：25 条来源 | N3: 仅历史窄范围144族；不得与294族归一化投影或全市场分母混用。。窄口径144族中29缺主文；Travel Protector仍缺适用组件，Home360为2020版，现行适用未证，不得套用于Basic。
A4: MY | B4: 马来西亚 | C4: 已有文件，继续核验 | D4: 597 | E4: 241 | F4: 43 | G4: 0 | K4: 暂停泛扩下载，先验收已取得Master候选。 | L4: 46320 | M4: 马来西亚：7 条来源 | N4: 全市场独立产品分母未知；文件数不能作产品数或覆盖率。。Sun Life本轮124份候选含103份Master及21份certificate，均待全文；法律主体、团体/个人和银行渠道不能混。
A5: VN | B5: 越南 | C5: 已有文件，继续核验 | D5: 572 | E5: 171 | F5: 29 | G5: 1 | K5: 校正身份和关系，BHV Appendix 01等具体缺件单列。 | L5: 46320 | M5: 越南：24 条来源 | N5: 全市场独立产品分母未知；文件数不能作产品数或覆盖率。。24条关系修复涉及23个来源组；21项多变体关系待审，部分所谓缺主文项实为附约。
A6: ID | B6: 印度尼西亚 | C6: 已有文件，继续核验 | D6: 89 | E6: 20 | F6: 3 | G6: 1 | K6: 核验PSATSI并找具名产品采用证据；受限件不破解。 | L6: 46320 | M6: 印度尼西亚：1 条来源 | N6: 全市场独立产品分母未知；文件数不能作产品数或覆盖率。。MAG PSAPBI已全文但为标准支持件，不能当具名产品主文；PSATSI待核，另有密码受限文件。
A7: TH | B7: 泰国 | C7: 已有文件，继续核验 | D7: 219 | E7: 115 | F7: 59 | G7: 0 | K7: 清理角色、双语及版本关系；不将重复文件计新增。 | L7: 46320 | M7: 泰国：3 条来源 | N7: 全市场独立产品分母未知；文件数不能作产品数或覆盖率。。Roojai新入口多为既有文件；主文、摘要、附加条款及服务协议混杂，部分PDF 403。
A8: PH | B8: 菲律宾 | C8: 已有文件，继续核验 | D8: 53 | E8: 52 | F8: 12 | G8: 1 | K8: 交付疑点页码与必要缺件；历史及不完整页不升strict。 | L8: 46320 | M8: 菲律宾：3 条来源 | N8: 全市场独立产品分母未知；文件数不能作产品数或覆盖率。。FWD KanGuard与KanMend两份现官网样本文已全文，但给付对象或定义有疑点，资料包未齐。
A9: KH | B9: 柬埔寨 | C9: 已有文件，继续核验 | D9: 199 | E9: 42 | F9: 7 | G9: 13 | K9: 先审3份现公开候选及高棉文内容，分别保留历史/采用待核。 | L9: 46320 | M9: 柬埔寨：13 条来源 | N9: 全市场独立产品分母未知；文件数不能作产品数或覆盖率。。本轮6份正文候选待核；3份有现公开直链、1份历史、2份官方托管但现行采用未证。
A10: BN | B10: 文莱 | C10: 已有文件，继续核验 | D10: 33 | E10: 33 | F10: 16 | G10: 0 | K10: 核对身份与关联，区分复用与新增文件。 | L10: 46320 | M10: 文莱：4 条来源 | N10: 全市场独立产品分母未知；文件数不能作产品数或覆盖率。。TAIB同页4条关系修复复用既有原件；National EPP仅见投保书及产品说明。
A11: LA | B11: 老挝 | C11: 已有文件，继续核验 | D11: 40 | E11: 7 | F11: 2 | G11: 7 | K11: 建立共享条款适用矩阵和附录依赖，不用共用文件合并产品。 | L11: 46320 | M11: 老挝：2 条来源 | N11: 全市场独立产品分母未知；文件数不能作产品数或覆盖率。。AGL库主文及附录多为既有文件；多产品共用空白附录，部分入口验证码。
A12: MM | B12: 缅甸 | C12: 已有文件，继续核验 | D12: 86 | E12: 12 | F12: 0 | G12: 0 | K12: 审组件依赖及法律版本；遇验证挑战停止该入口。 | L12: 46320 | M12: 缅甸：9 条来源 | N12: 全市场独立产品分母未知；文件数不能作产品数或覆盖率。。FNI本轮7份仅支持/附加组件且待核；名称含TC亦可能只是brief或summary。
A13: TL | B13: 东帝汶 | C13: 正式库尚无文件 | D13: 0 | E13: 0 | F13: 0 | G13: 0 | K13: 建立本地主体及目录，保留缺口；不以印尼或跨境产品冒充本地覆盖。 | L13: 46320 | M13: 东帝汶：3 条来源 | N13: 正式库尚无东帝汶本地原件；0文件不等于当地无产品，市场产品分母仍未知。。本地正式原件0；可见一般险主体及目录线索，但寿险当前牌照与本地入口未证。

Sheet 保司与来源
A1: 来源ID | B1: 地区 | C1: 保司／机构 | D1: 来源类型 | E1: 来源名称 | F1: 版本／范围 | G1: 最近检查 | H1: 核验状态 | I1: 来源入口 | J1: 文件链接 | K1: 证据边界 | L1: 批次
A2: SRC-HK-6c2c38706b | B2: 香港 | D2: 本地银行销售渠道 | E2: www.dahsing.com | F2: dahsing-sunjoy | G2: 46320 | H2: 页面可访问；所查可见链接未取得匹配主文 | I2: =HYPERLINK("https://www.dahsing.com/en/html/insurance/life_insurance/sunjoy_global_insurance_ii.html","https://www.dahsing.com/en/html/insurance/life_insurance/sunjoy_global_insurance_ii.html") -> https://www.dahsing.com/en/html/insurance/life_insurance/sunjoy_global_insurance_ii.html | K2: 历史本轮记录日期；非今日重访。仅沿冻结的产品/版本处理明确缺件；不重跑已结案路线。 | L2: D1及历史
A3: SRC-HK-4750d4b12c | B3: 香港 | D3: 本地银行销售渠道 | E3: www.dbs.com.hk | F3: dbs-savings | G3: 46320 | H3: 访问失败：HTTP Error 403: Forbidden | I3: =HYPERLINK("https://www.dbs.com.hk/private-banking/insurance/saving-retirement-income/default.page?rd=err","https://www.dbs.com.hk/private-banking/insurance/saving-retirement-income/default.page?rd=err") -> https://www.dbs.com.hk/private-banking/insurance/saving-retirement-income/default.page?rd=err | K3: 历史本轮记录日期；非今日重访。停止该受限入口；仅新授权/新官方入口或版本变化后复查。 | L3: D1及历史
A4: SRC-HK-e87ae103e8 | B4: 香港 | D4: 本地银行销售渠道 | E4: www.sc.com | F4: sc-insurance | G4: 46320 | H4: 页面可访问；所查可见链接未取得匹配主文 | I4: =HYPERLINK("https://www.sc.com/hk/insurance/","https://www.sc.com/hk/insurance/") -> https://www.sc.com/hk/insurance/ | K4: 历史本轮记录日期；非今日重访。仅沿冻结的产品/版本处理明确缺件；不重跑已结案路线。 | L4: D1及历史
A5: SRC-HK-5e1c5fa6df | B5: 香港 | D5: 本地银行销售渠道 | E5: www.sc.com | F5: sc-savings | G5: 46320 | H5: 页面可访问；所查可见链接未取得匹配主文 | I5: =HYPERLINK("https://www.sc.com/hk/insurance/life-insurance/savings-legacy-planning/","https://www.sc.com/hk/insurance/life-insurance/savings-legacy-planning/") -> https://www.sc.com/hk/insurance/life-insurance/savings-legacy-planning/ | K5: 历史本轮记录日期；非今日重访。仅沿冻结的产品/版本处理明确缺件；不重跑已结案路线。 | L5: D1及历史
A6: SRC-HK-af614e1616 | B6: 香港 | C6: AIA（东亚银行销售渠道） | D6: 本地银行销售渠道 | E6: www.hkbea.com | F6: bank-aia-deferred-annuity-plan-2 | G6: 46320 | H6: 页面可访问；所查可见链接未取得匹配主文；页面提示可按需索取 | I6: =HYPERLINK("https://www.hkbea.com/html/en/aia-deferred-annuity-plan-2.html","https://www.hkbea.com/html/en/aia-deferred-annuity-plan-2.html") -> https://www.hkbea.com/html/en/aia-deferred-annuity-plan-2.html | K6: 历史本轮记录日期；非今日重访。仅沿冻结的产品/版本处理明确缺件；不重跑已结案路线。 | L6: D1及历史
A7: SRC-HK-0f749b75df | B7: 香港 | C7: AIA（东亚银行销售渠道） | D7: 本地银行销售渠道 | E7: www.hkbea.com | F7: bea-aia | G7: 46320 | H7: 页面可访问；所查可见链接未取得匹配主文 | I7: =HYPERLINK("https://www.hkbea.com/html/en/bea-aia-partnership.html","https://www.hkbea.com/html/en/bea-aia-partnership.html") -> https://www.hkbea.com/html/en/bea-aia-partnership.html | K7: 历史本轮记录日期；非今日重访。仅沿冻结的产品/版本处理明确缺件；不重跑已结案路线。 | L7: D1及历史
A8: SRC-HK-4658d34b2c | B8: 香港 | C8: AIA（东亚银行销售渠道） | D8: 本地银行销售渠道 | E8: www.hkbea.com | F8: bank-global-power-multi-currency-plan-3 | G8: 46320 | H8: 页面可访问；所查可见链接未取得匹配主文；页面提示可按需索取 | I8: =HYPERLINK("https://www.hkbea.com/html/en/global-power-multi-currency-plan-3.html","https://www.hkbea.com/html/en/global-power-multi-currency-plan-3.html") -> https://www.hkbea.com/html/en/global-power-multi-currency-plan-3.html | K8: 历史本轮记录日期；非今日重访。仅沿冻结的产品/版本处理明确缺件；不重跑已结案路线。 | L8: D1及历史
A9: SRC-HK-cec52af9e6 | B9: 香港 | C9: AIA（东亚银行销售渠道） | D9: 本地银行销售渠道 | E9: www.hkbea.com | F9: bank-globalflexi-savings | G9: 46320 | H9: 页面可访问；所查可见链接未取得匹配主文；页面提示可按需索取 | I9: =HYPERLINK("https://www.hkbea.com/html/en/globalflexi-savings.html","https://www.hkbea.com/html/en/globalflexi-savings.html") -> https://www.hkbea.com/html/en/globalflexi-savings.html | K9: 历史本轮记录日期；非今日重访。仅沿冻结的产品/版本处理明确缺件；不重跑已结案路线。 | L9: D1及历史
A10: SRC-HK-e073e2aece | B10: 香港 | C10: AIA（东亚银行销售渠道） | D10: 本地银行销售渠道 | E10: www.hkbea.com | F10: bank-prosper-life-insurance-plan | G10: 46320 | H10: 页面可访问；所查可见链接未取得匹配主文；页面提示可按需索取 | I10: =HYPERLINK("https://www.hkbea.com/html/en/prosper-life-insurance-plan.html","https://www.hkbea.com/html/en/prosper-life-insurance-plan.html") -> https://www.hkbea.com/html/en/prosper-life-insurance-plan.html | K10: 历史本轮记录日期；非今日重访。仅沿冻结的产品/版本处理明确缺件；不重跑已结案路线。 | L10: D1及历史
A11: SRC-HK-f2ead39462 | B11: 香港 | C11: AIA（东亚银行销售渠道） | D11: 本地银行销售渠道 | E11: www.hkbea.com | F11: bank-wealth-flexi-savings | G11: 46320 | H11: 页面可访问；所查可见链接未取得匹配主文；页面提示可按需索取 | I11: =HYPERLINK("https://www.hkbea.com/html/en/wealth-flexi-savings.html","https://www.hkbea.com/html/en/wealth-flexi-savings.html") -> https://www.hkbea.com/html/en/wealth-flexi-savings.html | K11: 历史本轮记录日期；非今日重访。仅沿冻结的产品/版本处理明确缺件；不重跑已结案路线。 | L11: D1及历史
A12: SRC-HK-a4099bf446 | B12: 香港 | C12: AXA | D12: 保险公司官方 | E12: www.axa.com.hk | F12: 「賞精彩」延期年金計劃 | G12: 46320 | H12: 可见公开页面未取得新增匹配主文；宣传册/优惠/支持件不等于主合同 | I12: =HYPERLINK("https://www.axa.com.hk/zh/downloads/life-and-savings","https://www.axa.com.hk/zh/downloads/life-and-savings") -> https://www.axa.com.hk/zh/downloads/life-and-savings | K12: 历史逐请求检查时间。仅沿冻结的产品/版本处理明确缺件；不重跑已结案路线。 | L12: D1及历史
A13: SRC-HK-35bf5afc81 | B13: 香港 | C13: BOC Life | D13: 保险公司官方 | E13: www.boclife.com.hk | F13: 中銀人壽延期年金計劃（終身） | G13: 46320 | H13: 可见公开页面未取得新增匹配主文；宣传册/优惠/支持件不等于主合同 | I13: =HYPERLINK("https://www.boclife.com.hk/tc/product/boc-life-deferred-annuity-lifetime.html","https://www.boclife.com.hk/tc/product/boc-life-deferred-annuity-lifetime.html") -> https://www.boclife.com.hk/tc/product/boc-life-deferred-annuity-lifetime.html | K13: 历史逐请求检查时间。仅沿冻结的产品/版本处理明确缺件；不重跑已结案路线。 | L13: D1及历史
A14: SRC-HK-13a41ae0a6 | B14: 香港 | C14: BOC Life | D14: 保险公司官方 | E14: www.boclife.com.hk | F14: 鑄富世代環球終身保險計劃 | G14: 46320 | H14: 可见公开页面未取得新增匹配主文；宣传册/优惠/支持件不等于主合同 | I14: =HYPERLINK("https://www.boclife.com.hk/tc/product/eternal-fortune-global-whole-life-insurance-plan.html","https://www.boclife.com.hk/tc/product/eternal-fortune-global-whole-life-insurance-plan.html") -> https://www.boclife.com.hk/tc/product/eternal-fortune-global-whole-life-insurance-plan.html | K14: 历史逐请求检查时间。仅沿冻结的产品/版本处理明确缺件；不重跑已结案路线。 | L14: D1及历史
A15: SRC-HK-5bad78e05e | B15: 香港 | C15: BOC Life | D15: 保险公司官方 | E15: www.boclife.com.hk | F15: 薪火傳承環球終身保險計劃 | G15: 46320 | H15: 可见公开页面未取得新增匹配主文；宣传册/优惠/支持件不等于主合同 | I15: =HYPERLINK("https://www.boclife.com.hk/tc/product/glamorous-glow-global-whole-life-insurance-plan.html","https://www.boclife.com.hk/tc/product/glamorous-glow-global-whole-life-insurance-plan.html") -> https://www.boclife.com.hk/tc/product/glamorous-glow-global-whole-life-insurance-plan.html | K15: 历史逐请求检查时间。仅沿冻结的产品/版本处理明确缺件；不重跑已结案路线。 | L15: D1及历史
A16: SRC-HK-c7c3c03592 | B16: 香港 | C16: BOC Life | D16: 保险公司官方 | E16: www.boclife.com.hk | F16: 月悅出息終身享保險計劃 | G16: 46320 | H16: 可见公开页面未取得新增匹配主文；宣传册/优惠/支持件不等于主合同 | I16: =HYPERLINK("https://www.boclife.com.hk/tc/product/incomejoy-lifelong-insurance-plan.html","https://www.boclife.com.hk/tc/product/incomejoy-lifelong-insurance-plan.html") -> https://www.boclife.com.hk/tc/product/incomejoy-lifelong-insurance-plan.html | K16: 历史逐请求检查时间。仅沿冻结的产品/版本处理明确缺件；不重跑已结案路线。 | L16: D1及历史
A17: SRC-HK-99bdea2859 | B17: 香港 | C17: BOC Life | D17: 保险公司官方 | E17: www.boclife.com.hk | F17: 目標三年保險計劃 | G17: 46320 | H17: 可见公开页面未取得新增匹配主文；宣传册/优惠/支持件不等于主合同 | I17: =HYPERLINK("https://www.boclife.com.hk/tc/product/target3-years-insurance-plan.html","https://www.boclife.com.hk/tc/product/target3-years-insurance-plan.html") -> https://www.boclife.com.hk/tc/product/target3-years-insurance-plan.html | K17: 历史逐请求检查时间。仅沿冻结的产品/版本处理明确缺件；不重跑已结案路线。 | L17: D1及历史
A18: SRC-HK-4910d0077b | B18: 香港 | C18: BOC Life | D18: 保险公司官方 | E18: www.boclife.com.hk | F18: 精選目標五年保險計劃 | G18: 46320 | H18: 可见公开页面未取得新增匹配主文；宣传册/优惠/支持件不等于主合同 | I18: =HYPERLINK("https://www.boclife.com.hk/tc/product/target5-years-plus-insurance-plan.html","https://www.boclife.com.hk/tc/product/target5-years-plus-insurance-plan.html") -> https://www.boclife.com.hk/tc/product/target5-years-plus-insurance-plan.html | K18: 历史逐请求检查时间。仅沿冻结的产品/版本处理明确缺件；不重跑已结案路线。 | L18: D1及历史
A19: SRC-HK-605320de19 | B19: 香港 | C19: CTF Life | D19: 保险公司官方 | E19: www.ctflife.com.hk | F19: 「盛悅」萬用保險保障計劃 | G19: 46320 | H19: 返回验证挑战，未取得真正产品页面；已停止该入口 | I19: =HYPERLINK("https://www.ctflife.com.hk/tc/product/wealth/gorgeous-universal-life-protection-plan","https://www.ctflife.com.hk/tc/product/wealth/gorgeous-universal-life-protection-plan") -> https://www.ctflife.com.hk/tc/product/wealth/gorgeous-universal-life-protection-plan | K19: 历史逐请求检查时间。停止该受限入口；仅新授权/新官方入口或版本变化后复查。 | L19: D1及历史
A20: SRC-HK-ba187b4d0d | B20: 香港 | C20: CTF Life | D20: 保险公司官方 | E20: www.ctflife.com.hk | F20: 「匠心 • 傳承」儲蓄保險計劃 2 (優越版) | G20: 46320 | H20: 返回验证挑战，未取得真正产品页面；已停止该入口 | I20: =HYPERLINK("https://www.ctflife.com.hk/tc/product/wealth/mywealth-savings-insurance-plan-2-prestige","https://www.ctflife.com.hk/tc/product/wealth/mywealth-savings-insurance-plan-2-prestige") -> https://www.ctflife.com.hk/tc/product/wealth/mywealth-savings-insurance-plan-2-prestige | K20: 历史逐请求检查时间。停止该受限入口；仅新授权/新官方入口或版本变化后复查。 | L20: D1及历史
A21: SRC-HK-a29b5bed4b | B21: 香港 | C21: CTF Life | D21: 保险公司官方 | E21: www.ctflife.com.hk | F21: 「飛揚．88」儲蓄保險計劃 | G21: 46320 | H21: 返回验证挑战，未取得真正产品页面；已停止该入口 | I21: =HYPERLINK("https://www.ctflife.com.hk/tc/product/wealth/sky-leap-88-savings-insurance-plan","https://www.ctflife.com.hk/tc/product/wealth/sky-leap-88-savings-insurance-plan") -> https://www.ctflife.com.hk/tc/product/wealth/sky-leap-88-savings-insurance-plan | K21: 历史逐请求检查时间。停止该受限入口；仅新授权/新官方入口或版本变化后复查。 | L21: D1及历史
A22: SRC-HK-266e3e3809 | B22: 香港 | C22: China Life (Overseas) | D22: 保险公司官方 | E22: chinalife.com.hk | F22: Grand Horizon Savings Insurance Plan (Exclusive to Broker Channel) | G22: 46320 | H22: 可见公开页面未取得新增匹配主文；宣传册/优惠/支持件不等于主合同 | I22: =HYPERLINK("https://chinalife.com.hk/products/insurance/grand-horizon-savings-insurance-plan-exclusive-to-broker-channel","https://chinalife.com.hk/products/insurance/grand-horizon-savings-insurance-plan-exclusive-to-broker-channel") -> https://chinalife.com.hk/products/insurance/grand-horizon-savings-insurance-plan-exclusive-to-broker-channel | K22: 历史逐请求检查时间。仅沿冻结的产品/版本处理明确缺件；不重跑已结案路线。 | L22: D1及历史
A23: SRC-HK-68cd7e8e87 | B23: 香港 | C23: China Pacific Life Insurance (H.K.) Company Limited | D23: 保险公司官方 | E23: www.cpiclifehk.com.hk | F23: 世代悅享儲蓄保險計劃3 | G23: 46320 | H23: 可见公开页面未取得新增匹配主文；宣传册/优惠/支持件不等于主合同 | I23: =HYPERLINK("https://www.cpiclifehk.com.hk/ProductIntroduce/ProductDetail?productCode=Everlasting-Joy-3","https://www.cpiclifehk.com.hk/ProductIntroduce/ProductDetail?productCode=Everlasting-Joy-3") -> https://www.cpiclifehk.com.hk/ProductIntroduce/ProductDetail?productCode=Everlasting-Joy-3 | K23: 历史逐请求检查时间。仅沿冻结的产品/版本处理明确缺件；不重跑已结案路线。 | L23: D1及历史
A24: SRC-HK-094918c851 | B24: 香港 | C24: Chubb Life | D24: 保险公司官方 | E24: www.chubb.com | F24: Chubb Future Achiever Savings Plan II | G24: 46320 | H24: 可见公开页面未取得新增匹配主文；宣传册/优惠/支持件不等于主合同 | I24: =HYPERLINK("https://www.chubb.com/hk-en/personal/chubb-future-achiever-savings-plan-2.html","https://www.chubb.com/hk-en/personal/chubb-future-achiever-savings-plan-2.html") -> https://www.chubb.com/hk-en/personal/chubb-future-achiever-savings-plan-2.html | K24: 历史逐请求检查时间。仅沿冻结的产品/版本处理明确缺件；不重跑已结案路线。 | L24: D1及历史
A25: SRC-HK-ca03c232c3 | B25: 香港 | C25: Fubon Life Insurance (Hong Kong) Company Limited | D25: 保险公司官方 | E25: www.fubonlife.com.hk | F25: 盈玥保險計劃 | G25: 46320 | H25: 可见公开页面未取得新增匹配主文；宣传册/优惠/支持件不等于主合同 | I25: =HYPERLINK("https://www.fubonlife.com.hk/life_hk/html/tc/products/treasure-prestige.html","https://www.fubonlife.com.hk/life_hk/html/tc/products/treasure-prestige.html") -> https://www.fubonlife.com.hk/life_hk/html/tc/products/treasure-prestige.html | K25: 历史逐请求检查时间。仅沿冻结的产品/版本处理明确缺件；不重跑已结案路线。 | L25: D1及历史
A26: SRC-HK-155493430c | B26: 香港 | C26: HSBC Life | D26: 保险公司官方 | E26: www.hsbc.com.hk | F26: HSBC EarlyIncome Deferred Annuity Plan | G26: 46320 | H26: 可见公开页面未取得新增匹配主文；宣传册/优惠/支持件不等于主合同 | I26: =HYPERLINK("https://www.hsbc.com.hk/insurance/products/savings-and-retirement/early-income-deferred-annuity/","https://www.hsbc.com.hk/insurance/products/savings-and-retirement/early-income-deferred-annuity/") -> https://www.hsbc.com.hk/insurance/products/savings-and-retirement/early-income-deferred-annuity/ | K26: 历史逐请求检查时间。仅沿冻结的产品/版本处理明确缺件；不重跑已结案路线。 | L26: D1及历史
A27: SRC-HK-e31a49cdc7 | B27: 香港 | C27: HSBC Life | D27: 保险公司官方 | E27: www.hsbc.com.hk | F27: HSBC Flourish Income Annuity Plan | G27: 46320 | H27: 可见公开页面未取得新增匹配主文；宣传册/优惠/支持件不等于主合同 | I27: =HYPERLINK("https://www.hsbc.com.hk/insurance/products/savings-and-retirement/flourish-income-annuity/","https://www.hsbc.com.hk/insurance/products/savings-and-retirement/flourish-income-annuity/") -> https://www.hsbc.com.hk/insurance/products/savings-and-retirement/flourish-income-annuity/ | K27: 历史逐请求检查时间。仅沿冻结的产品/版本处理明确缺件；不重跑已结案路线。 | L27: D1及历史
A28: SRC-HK-1f15ddfad2 | B28: 香港 | C28: HSBC Life | D28: 保险公司官方 | E28: www.hsbc.com.hk | F28: HSBC Income Goal Deferred Annuity Plan | G28: 46320 | H28: 可见公开页面未取得新增匹配主文；宣传册/优惠/支持件不等于主合同 | I28: =HYPERLINK("https://www.hsbc.com.hk/insurance/products/savings-and-retirement/income-goal-deferred-annuity/","https://www.hsbc.com.hk/insurance/products/savings-and-retirement/income-goal-deferred-annuity/") -> https://www.hsbc.com.hk/insurance/products/savings-and-retirement/income-goal-deferred-annuity/ | K28: 历史逐请求检查时间。仅沿冻结的产品/版本处理明确缺件；不重跑已结案路线。 | L28: D1及历史
A29: SRC-HK-12fb188f79 | B29: 香港 | C29: Hang Seng Insurance | D29: 保险公司官方 | E29: www.hangseng.com | F29: 「晉盛」延期年金人壽保險計劃 - 恒生銀行 | G29: 46320 | H29: 可见公开页面未取得新增匹配主文；宣传册/优惠/支持件不等于主合同 | I29: =HYPERLINK("https://www.hangseng.com/zh-hk/personal/insurance-mpf/retirement-wealth-education/fortunelife-deferred-annuity/","https://www.hangseng.com/zh-hk/personal/insurance-mpf/retirement-wealth-education/fortunelife-deferred-annuity/") -> https://www.hangseng.com/zh-hk/personal/insurance-mpf/retirement-wealth-education/fortunelife-deferred-annuity/ | K29: 历史逐请求检查时间。仅沿冻结的产品/版本处理明确缺件；不重跑已结案路线。 | L29: D1及历史
A30: SRC-HK-eef3efa20f | B30: 香港 | C30: Hang Seng Insurance | D30: 保险公司官方 | E30: www.hangseng.com | F30: 「聚息通」人壽保險計劃 | G30: 46320 | H30: 可见公开页面未取得新增匹配主文；宣传册/优惠/支持件不等于主合同 | I30: =HYPERLINK("https://www.hangseng.com/zh-hk/personal/insurance-mpf/retirement-wealth-education/income-power/","https://www.hangseng.com/zh-hk/personal/insurance-mpf/retirement-wealth-education/income-power/") -> https://www.hangseng.com/zh-hk/personal/insurance-mpf/retirement-wealth-education/income-power/ | K30: 历史逐请求检查时间。仅沿冻结的产品/版本处理明确缺件；不重跑已结案路线。 | L30: D1及历史
A31: SRC-HK-128249f83d | B31: 香港 | C31: Hong Kong Life Insurance Limited | D31: 保险公司官方 | E31: www.hklife.com.hk | F31: Wealth Global Multi-Currency Insurance Plan | G31: 46320 | H31: 可见公开页面未取得新增匹配主文；宣传册/优惠/支持件不等于主合同 | I31: =HYPERLINK("https://www.hklife.com.hk/en/products/personal-insurance/savings-plan/wealth-global-multi-currency-insurance-plan/index.html","https://www.hklife.com.hk/en/products/personal-insurance/savings-plan/wealth-global-multi-currency-insurance-plan/index.html") -> https://www.hklife.com.hk/en/products/personal-insurance/savings-plan/wealth-global-multi-currency-insurance-plan/index.html | K31: 历史逐请求检查时间。仅沿冻结的产品/版本处理明确缺件；不重跑已结案路线。 | L31: D1及历史
A32: SRC-HK-204b85559d | B32: 香港 | C32: YF Life | D32: 保险公司官方 | E32: www.yflife.com | F32: 萬通多元教育儲蓄計劃 | G32: 46320 | H32: 可见公开页面未取得新增匹配主文；宣传册/优惠/支持件不等于主合同 | I32: =HYPERLINK("https://www.yflife.com/tc/product/savings/my-flexi-generations-saver/","https://www.yflife.com/tc/product/savings/my-flexi-generations-saver/") -> https://www.yflife.com/tc/product/savings/my-flexi-generations-saver/ | K32: 历史逐请求检查时间。仅沿冻结的产品/版本处理明确缺件；不重跑已结案路线。 | L32: D1及历史
A33: SRC-HK-d9f168be97 | B33: 香港 | C33: Zurich Life Insurance (Hong Kong) Limited | D33: 保险公司官方 | E33: life.zurich.com.hk | F33: Swiss Prime Savings Insurance Plan | G33: 46320 | H33: 可见公开页面未取得新增匹配主文；宣传册/优惠/支持件不等于主合同 | I33: =HYPERLINK("https://life.zurich.com.hk/en/products/swiss-prime-savings-insurance-plan/","https://life.zurich.com.hk/en/products/swiss-prime-savings-insurance-plan/") -> https://life.zurich.com.hk/en/products/swiss-prime-savings-insurance-plan/ | K33: 历史逐请求检查时间。仅沿冻结的产品/版本处理明确缺件；不重跑已结案路线。 | L33: D1及历史
A34: SRC-HK-90272692ff | B34: 香港 | C34: AIA 友邦香港 | D34: 保险公司官方 | E34: www.aia.com.hk | F34: AIA延期年金計劃2 | G34: 46320 | H34: 页面可访问；所查可见链接未取得匹配主文；页面提示可按需索取 | I34: =HYPERLINK("https://www.aia.com.hk/en/products/save/aia-deferred-annuity-plan-2.html","https://www.aia.com.hk/en/products/save/aia-deferred-annuity-plan-2.html") -> https://www.aia.com.hk/en/products/save/aia-deferred-annuity-plan-2.html | K34: 历史本轮记录日期；非今日重访。仅沿冻结的产品/版本处理明确缺件；不重跑已结案路线。 | L34: D1及历史
A35: SRC-HK-4d6dc4e758 | B35: 香港 | C35: AIA 友邦香港 | D35: 保险公司官方 | E35: www.aia.com.hk | F35: GlobalFlexi Savings Insurance Plan | G35: 46320 | H35: 页面可访问；所查可见链接未取得匹配主文；页面提示可按需索取 | I35: =HYPERLINK("https://www.aia.com.hk/en/products/save/global-flexi.html","https://www.aia.com.hk/en/products/save/global-flexi.html") -> https://www.aia.com.hk/en/products/save/global-flexi.html | K35: 历史本轮记录日期；非今日重访。仅沿冻结的产品/版本处理明确缺件；不重跑已结案路线。 | L35: D1及历史
A36: SRC-HK-fc65524559 | B36: 香港 | C36: AIA 友邦香港 | D36: 保险公司官方 | E36: www.aia.com.hk | F36: Global Power Multi-Currency Savings Insurance Plan 3 | G36: 46320 | H36: 页面可访问；所查可见链接未取得匹配主文；页面提示可按需索取 | I36: =HYPERLINK("https://www.aia.com.hk/en/products/save/global-power-3.html","https://www.aia.com.hk/en/products/save/global-power-3.html") -> https://www.aia.com.hk/en/products/save/global-power-3.html | K36: 历史本轮记录日期；非今日重访。仅沿冻结的产品/版本处理明确缺件；不重跑已结案路线。 | L36: D1及历史
A37: SRC-HK-5184343d26 | B37: 香港 | C37: AIA 友邦香港 | D37: 保险公司官方 | E37: www.aia.com.hk | F37: 「活然人生」保險計劃 | G37: 46320 | H37: 页面可访问；所查可见链接未取得匹配主文；页面提示可按需索取 | I37: =HYPERLINK("https://www.aia.com.hk/en/products/save/prosperlife.html","https://www.aia.com.hk/en/products/save/prosperlife.html") -> https://www.aia.com.hk/en/products/save/prosperlife.html | K37: 历史本轮记录日期；非今日重访。仅沿冻结的产品/版本处理明确缺件；不重跑已结案路线。 | L37: D1及历史
A38: SRC-HK-6da6f21312 | B38: 香港 | C38: AIA 友邦香港 | D38: 保险公司官方 | E38: www.aia.com.hk | F38: Wealth Flexi Savings Insurance Plan | G38: 46320 | H38: 页面可访问；所查可见链接未取得匹配主文；页面提示可按需索取 | I38: =HYPERLINK("https://www.aia.com.hk/en/products/save/wealth-flexi","https://www.aia.com.hk/en/products/save/wealth-flexi") -> https://www.aia.com.hk/en/products/save/wealth-flexi | K38: 历史本轮记录日期；非今日重访。仅沿冻结的产品/版本处理明确缺件；不重跑已结案路线。 | L38: D1及历史
A39: SRC-HK-550167b5ea | B39: 香港 | C39: Manulife 宏利香港 | D39: 保险公司官方 | E39: www.manulife.com.hk | F39: 宏浚傳承保障計劃 | G39: 46320 | H39: 页面可访问；所查可见链接未取得匹配主文 | I39: =HYPERLINK("https://www.manulife.com.hk/en/individual/products/save/savings/future-assure.html","https://www.manulife.com.hk/en/individual/products/save/savings/future-assure.html") -> https://www.manulife.com.hk/en/individual/products/save/savings/future-assure.html | K39: 历史本轮记录日期；非今日重访。仅沿冻结的产品/版本处理明确缺件；不重跑已结案路线。 | L39: D1及历史
A40: SRC-HK-5eb777bde3 | B40: 香港 | C40: Manulife 宏利香港 | D40: 保险公司官方 | E40: www.manulife.com.hk | F40: 宏摯家傳承保險計劃 | G40: 46320 | H40: 页面可访问；所查可见链接未取得匹配主文；页面提示可按需索取 | I40: =HYPERLINK("https://www.manulife.com.hk/en/individual/products/save/savings/genesis-centurion.html","https://www.manulife.com.hk/en/individual/products/save/savings/genesis-centurion.html") -> https://www.manulife.com.hk/en/individual/products/save/savings/genesis-centurion.html | K40: 历史本轮记录日期；非今日重访。仅沿冻结的产品/版本处理明确缺件；不重跑已结案路线。 | L40: D1及历史
A41: SRC-HK-83c3ff9cdb | B41: 香港 | C41: Manulife 宏利香港 | D41: 保险公司官方 | E41: www.manulife.com.hk | F41: 宏摯傳承保障計劃 | G41: 46320 | H41: 页面可访问；所查可见链接未取得匹配主文；页面提示可按需索取 | I41: =HYPERLINK("https://www.manulife.com.hk/en/individual/products/save/savings/genesis.html","https://www.manulife.com.hk/en/individual/products/save/savings/genesis.html") -> https://www.manulife.com.hk/en/individual/products/save/savings/genesis.html | K41: 历史本轮记录日期；非今日重访。仅沿冻结的产品/版本处理明确缺件；不重跑已结案路线。 | L41: D1及历史
A42: SRC-HK-4842f454f5 | B42: 香港 | C42: Manulife 宏利香港 | D42: 保险公司官方 | E42: www.manulife.com.hk | F42: 赤霞珠終身壽險計劃2 | G42: 46320 | H42: 页面可访问；所查可见链接未取得匹配主文 | I42: =HYPERLINK("https://www.manulife.com.hk/en/individual/products/save/savings/la-vie-2.html","https://www.manulife.com.hk/en/individual/products/save/savings/la-vie-2.html") -> https://www.manulife.com.hk/en/individual/products/save/savings/la-vie-2.html | K42: 历史本轮记录日期；非今日重访。仅沿冻结的产品/版本处理明确缺件；不重跑已结案路线。 | L42: D1及历史
A43: SRC-HK-d8344edb4f | B43: 香港 | C43: Manulife 宏利香港 | D43: 保险公司官方 | E43: www.manulife.com.hk | F43: 宏利環球貨幣保障計劃 | G43: 46320 | H43: 页面可访问；所查可见链接未取得匹配主文 | I43: =HYPERLINK("https://www.manulife.com.hk/en/individual/products/save/savings/manuglobal-saver.html","https://www.manulife.com.hk/en/individual/products/save/savings/manuglobal-saver.html") -> https://www.manulife.com.hk/en/individual/products/save/savings/manuglobal-saver.html | K43: 历史本轮记录日期；非今日重访。仅沿冻结的产品/版本处理明确缺件；不重跑已结案路线。 | L43: D1及历史
A44: SRC-HK-9f5a4b5ba5 | B44: 香港 | C44: Prudential 保诚香港 | D44: 保险公司官方 | E44: www.prudential.com.hk | F44: Prudential Enlight Savings Insurance Series | G44: 46320 | H44: 页面可访问；所查可见链接未取得匹配主文 | I44: =HYPERLINK("https://www.prudential.com.hk/en/products/save/savings/prudential-enlight-savings-insurance-series/","https://www.prudential.com.hk/en/products/save/savings/prudential-enlight-savings-insurance-series/") -> https://www.prudential.com.hk/en/products/save/savings/prudential-enlight-savings-insurance-series/ | K44: 历史本轮记录日期；非今日重访。仅沿冻结的产品/版本处理明确缺件；不重跑已结案路线。 | L44: D1及历史
A45: SRC-HK-0bf75c5362 | B45: 香港 | C45: Prudential 保诚香港 | D45: 保险公司官方 | E45: www.prudential.com.hk | F45: Prudential Entrust Multi-Currency Insurance Plan | G45: 46320 | H45: 页面可访问；所查可见链接未取得匹配主文 | I45: =HYPERLINK("https://www.prudential.com.hk/en/products/save/savings/prudential-entrust-multi-currency-plan/","https://www.prudential.com.hk/en/products/save/savings/prudential-entrust-multi-currency-plan/") -> https://www.prudential.com.hk/en/products/save/savings/prudential-entrust-multi-currency-plan/ | K45: 历史本轮记录日期；非今日重访。仅沿冻结的产品/版本处理明确缺件；不重跑已结案路线。 | L45: D1及历史
A46: SRC-HK-cc05afdfef | B46: 香港 | C46: Sun Life 永明香港 | D46: 保险公司官方 | E46: www.sunlife.com.hk | F46: 享悅即享年金保險 | G46: 46320 | H46: 页面可访问；所查可见链接未取得匹配主文 | I46: =HYPERLINK("https://www.sunlife.com.hk/en/insurance/wealth-management/retirement/retirefree-immediate-annuity/","https://www.sunlife.com.hk/en/insurance/wealth-management/retirement/retirefree-immediate-annuity/") -> https://www.sunlife.com.hk/en/insurance/wealth-management/retirement/retirefree-immediate-annuity/ | K46: 历史本轮记录日期；非今日重访。仅沿冻结的产品/版本处理明确缺件；不重跑已结案路线。 | L46: D1及历史
A47: SRC-HK-1e181737cc | B47: 香港 | C47: Sun Life 永明香港 | D47: 保险公司官方 | E47: www.sunlife.com.hk | F47: 永越多元貨幣保險計劃 II | G47: 46320 | H47: 页面可访问；所查可见链接未取得匹配主文 | I47: =HYPERLINK("https://www.sunlife.com.hk/en/insurance/wealth-management/savings/stellar-multi-currency-ii/","https://www.sunlife.com.hk/en/insurance/wealth-management/savings/stellar-multi-currency-ii/") -> https://www.sunlife.com.hk/en/insurance/wealth-management/savings/stellar-multi-currency-ii/ | K47: 历史本轮记录日期；非今日重访。仅沿冻结的产品/版本处理明确缺件；不重跑已结案路线。 | L47: D1及历史
A48: SRC-HK-6d54b75caf | B48: 香港 | C48: Sun Life 永明香港 | D48: 保险公司官方 | E48: www.sunlife.com.hk | F48: 萬年青•星河傳承保險計劃 II | G48: 46320 | H48: 页面可访问；所查可见链接未取得匹配主文 | I48: =HYPERLINK("https://www.sunlife.com.hk/en/insurance/wealth-management/savings/sungift-global-ii/","https://www.sunlife.com.hk/en/insurance/wealth-management/savings/sungift-global-ii/") -> https://www.sunlife.com.hk/en/insurance/wealth-management/savings/sungift-global-ii/ | K48: 历史本轮记录日期；非今日重访。仅沿冻结的产品/版本处理明确缺件；不重跑已结案路线。 | L48: D1及历史
A49: SRC-HK-dc73a6570f | B49: 香港 | C49: Sun Life 永明香港 | D49: 保险公司官方 | E49: www.sunlife.com.hk | F49: 萬年青•星河尊享保險計劃 II | G49: 46320 | H49: 页面可访问；所查可见链接未取得匹配主文 | I49: =HYPERLINK("https://www.sunlife.com.hk/en/insurance/wealth-management/savings/sunjoy-global-ii/","https://www.sunlife.com.hk/en/insurance/wealth-management/savings/sunjoy-global-ii/") -> https://www.sunlife.com.hk/en/insurance/wealth-management/savings/sunjoy-global-ii/ | K49: 历史本轮记录日期；非今日重访。仅沿冻结的产品/版本处理明确缺件；不重跑已结案路线。 | L49: D1及历史
A50: SRC-SG-f6db3e1371 | B50: 新加坡 | D50: 公开中介页面（身份待核） | E50: shentonbrokers.com | F50: Great Travel Insurance | G50: 46320 | H50: 未取得可核匹配主文；官方页面403，路线已停止 | I50: =HYPERLINK("https://shentonbrokers.com/compare/travel/fwd-vs-great-american","https://shentonbrokers.com/compare/travel/fwd-vs-great-american") -> https://shentonbrokers.com/compare/travel/fwd-vs-great-american | K50: 历史本轮记录日期；非今日重访。停止该受限入口；仅新授权/新官方入口或版本变化后复查。 | L50: D1及历史
A51: SRC-SG-5a57c8312b | B51: 新加坡 | D51: 公开中介页面（身份待核） | E51: shentonbrokers.com | F51: 有限主文补缺路线 | G51: 46320 | H51: 访问失败：HTTP 403 Forbidden | I51: =HYPERLINK("https://shentonbrokers.com/compare/travel/fwd-vs-great-american","https://shentonbrokers.com/compare/travel/fwd-vs-great-american") -> https://shentonbrokers.com/compare/travel/fwd-vs-great-american | K51: 历史本轮记录日期；非今日重访。停止该受限入口；仅新授权/新官方入口或版本变化后复查。 | L51: D1及历史
A52: SRC-SG-c3fb773669 | B52: 新加坡 | D52: 保险公司官方 | E52: www.greatamericaninsurancegroup.com | F52: 有限主文补缺路线 | G52: 46320 | H52: 访问失败：HTTP 403 Forbidden | I52: =HYPERLINK("https://www.greatamericaninsurancegroup.com/about-us/business-operations/product/singapore-branch/portfolio-of-products-and-proposal-forms","https://www.greatamericaninsurancegroup.com/about-us/business-operations/product/singapore-branch/portfolio-of-products-and-proposal-forms") -> https://www.greatamericaninsurancegroup.com/about-us/business-operations/product/singapore-branch/portfolio-of-products-and-proposal-forms | K52: 历史本轮记录日期；非今日重访。停止该受限入口；仅新授权/新官方入口或版本变化后复查。 | L52: D1及历史
A53: SRC-SG-4d613c3c8a | B53: 新加坡 | C53: Allied World Assurance Company Ltd, Singapore Branch | D53: 保险公司官方 | E53: alliedworldinsurance.com | F53: Personal Accident Protector | G53: 46320 | H53: 所查官网及公开路线未找到可核同产品主文 | I53: =HYPERLINK("https://alliedworldinsurance.com/products/accident-health-singapore/","https://alliedworldinsurance.com/products/accident-health-singapore/") -> https://alliedworldinsurance.com/products/accident-health-singapore/ | K53: 历史本轮记录日期；非今日重访。仅沿冻结的产品/版本处理明确缺件；不重跑已结案路线。 | L53: D1及历史
A54: SRC-SG-85f318924b | B54: 新加坡 | C54: Allied World Assurance Company Ltd, Singapore Branch | D54: 保险公司官方 | E54: alliedworldinsurance.com | F54: Home Protector | G54: 46320 | H54: Home360完整2020版已取得；现行版采用待证，Basic未取得 | I54: =HYPERLINK("https://alliedworldinsurance.com/products/personal-lines-singapore/","https://alliedworldinsurance.com/products/personal-lines-singapore/") -> https://alliedworldinsurance.com/products/personal-lines-singapore/ | K54: 历史本轮记录日期；非今日重访。仅沿冻结的产品/版本处理明确缺件；不重跑已结案路线。 | L54: D1及历史
A55: SRC-SG-67f6f8fab2 | B55: 新加坡 | C55: Allied World Assurance Company Ltd, Singapore Branch | D55: 保险公司官方 | E55: alliedworldinsurance.com | F55: Personal Accident Protector | G55: 46320 | H55: 所查官网及公开路线未找到可核同产品主文 | I55: =HYPERLINK("https://alliedworldinsurance.com/products/personal-lines-singapore/","https://alliedworldinsurance.com/products/personal-lines-singapore/") -> https://alliedworldinsurance.com/products/personal-lines-singapore/ | K55: 历史本轮记录日期；非今日重访。仅沿冻结的产品/版本处理明确缺件；不重跑已结案路线。 | L55: D1及历史
A56: SRC-SG-b6fe20dfa2 | B56: 新加坡 | C56: Allied World Assurance Company Ltd, Singapore Branch | D56: 保险公司官方 | E56: alliedworldinsurance.com | F56: Travel Protector | G56: 46320 | H56: 主文已取得且有现页关联；COVID批单仍缺，资料包未齐 | I56: =HYPERLINK("https://alliedworldinsurance.com/products/personal-lines-singapore/","https://alliedworldinsurance.com/products/personal-lines-singapore/") -> https://alliedworldinsurance.com/products/personal-lines-singapore/ | K56: 历史本轮记录日期；非今日重访。仅沿冻结的产品/版本处理明确缺件；不重跑已结案路线。 | L56: D1及历史
A57: SRC-SG-65d2ccc730 | B57: 新加坡 | C57: Friends Provident International Limited | D57: 保险公司官方 | E57: advisers.fpinternational.sg | F57: Global Portfolio | G57: 46320 | H57: 公开文件库仅发现支持资料，未取得匹配主文 | I57: =HYPERLINK("https://advisers.fpinternational.sg/knowledge/document-library/","https://advisers.fpinternational.sg/knowledge/document-library/") -> https://advisers.fpinternational.sg/knowledge/document-library/ | K57: 历史本轮记录日期；非今日重访。仅沿冻结的产品/版本处理明确缺件；不重跑已结案路线。 | L57: D1及历史
A58: SRC-SG-b73e371867 | B58: 新加坡 | C58: Friends Provident International Limited | D58: 保险公司官方 | E58: advisers.fpinternational.sg | F58: Global Wealth Advance | G58: 46320 | H58: 公开文件库仅发现支持资料，未取得匹配主文 | I58: =HYPERLINK("https://advisers.fpinternational.sg/knowledge/document-library/","https://advisers.fpinternational.sg/knowledge/document-library/") -> https://advisers.fpinternational.sg/knowledge/document-library/ | K58: 历史本轮记录日期；非今日重访。仅沿冻结的产品/版本处理明确缺件；不重跑已结案路线。 | L58: D1及历史
A59: SRC-SG-f9b1031956 | B59: 新加坡 | C59: Friends Provident International Limited | D59: 保险公司官方 | E59: advisers.fpinternational.sg | F59: Global Wealth Manager | G59: 46320 | H59: 公开文件库仅发现支持资料，未取得匹配主文 | I59: =HYPERLINK("https://advisers.fpinternational.sg/knowledge/document-library/","https://advisers.fpinternational.sg/knowledge/document-library/") -> https://advisers.fpinternational.sg/knowledge/document-library/ | K59: 历史本轮记录日期；非今日重访。仅沿冻结的产品/版本处理明确缺件；不重跑已结案路线。 | L59: D1及历史
A60: SRC-SG-a48ca92a82 | B60: 新加坡 | C60: Friends Provident International Limited | D60: 保险公司官方 | E60: www.fpinternational.sg | F60: Global Portfolio | G60: 46320 | H60: 公开文件库仅发现支持资料，未取得匹配主文 | I60: =HYPERLINK("https://www.fpinternational.sg/knowledge/document-library/","https://www.fpinternational.sg/knowledge/document-library/") -> https://www.fpinternational.sg/knowledge/document-library/ | K60: 历史本轮记录日期；非今日重访。仅沿冻结的产品/版本处理明确缺件；不重跑已结案路线。 | L60: D1及历史
A61: SRC-SG-7ef6fec27d | B61: 新加坡 | C61: Friends Provident International Limited | D61: 保险公司官方 | E61: www.fpinternational.sg | F61: Global Wealth Advance | G61: 46320 | H61: 公开文件库仅发现支持资料，未取得匹配主文 | I61: =HYPERLINK("https://www.fpinternational.sg/knowledge/document-library/","https://www.fpinternational.sg/knowledge/document-library/") -> https://www.fpinternational.sg/knowledge/document-library/ | K61: 历史本轮记录日期；非今日重访。仅沿冻结的产品/版本处理明确缺件；不重跑已结案路线。 | L61: D1及历史
A62: SRC-SG-2a30025b4e | B62: 新加坡 | C62: Friends Provident International Limited | D62: 保险公司官方 | E62: www.fpinternational.sg | F62: Global Wealth Manager | G62: 46320 | H62: 公开文件库仅发现支持资料，未取得匹配主文 | I62: =HYPERLINK("https://www.fpinternational.sg/knowledge/document-library/","https://www.fpinternational.sg/knowledge/document-library/") -> https://www.fpinternational.sg/knowledge/document-library/ | K62: 历史本轮记录日期；非今日重访。仅沿冻结的产品/版本处理明确缺件；不重跑已结案路线。 | L62: D1及历史
A63: SRC-SG-fd0a2b802c | B63: 新加坡 | C63: Great American Insurance Company, Singapore Branch | D63: 保险公司官方 | E63: www.greatamericaninsurancegroup.com | F63: GREAT Renovation Protect | G63: 46320 | H63: 未取得可核匹配主文；官方页面403，路线已停止 | I63: =HYPERLINK("https://www.greatamericaninsurancegroup.com/about-us/business-operations/product/singapore-branch/portfolio-of-products-and-proposal-forms","https://www.greatamericaninsurancegroup.com/about-us/business-operations/product/singapore-branch/portfolio-of-products-and-proposal-forms") -> https://www.greatamericaninsurancegroup.com/about-us/business-operations/product/singapore-branch/portfolio-of-products-and-proposal-forms | K63: 历史本轮记录日期；非今日重访。停止该受限入口；仅新授权/新官方入口或版本变化后复查。 | L63: D1及历史
A64: SRC-SG-f0899a46f7 | B64: 新加坡 | C64: Great American Insurance Company, Singapore Branch | D64: 保险公司官方 | E64: www.greatamericaninsurancegroup.com | F64: Great Home Insurance | G64: 46320 | H64: 未取得可核匹配主文；官方页面403，路线已停止 | I64: =HYPERLINK("https://www.greatamericaninsurancegroup.com/about-us/business-operations/product/singapore-branch/portfolio-of-products-and-proposal-forms","https://www.greatamericaninsurancegroup.com/about-us/business-operations/product/singapore-branch/portfolio-of-products-and-proposal-forms") -> https://www.greatamericaninsurancegroup.com/about-us/business-operations/product/singapore-branch/portfolio-of-products-and-proposal-forms | K64: 历史本轮记录日期；非今日重访。停止该受限入口；仅新授权/新官方入口或版本变化后复查。 | L64: D1及历史
A65: SRC-SG-3abd6fcbc8 | B65: 新加坡 | C65: Great American Insurance Company, Singapore Branch | D65: 保险公司官方 | E65: www.greatamericaninsurancegroup.com | F65: Great Personal Accident Insurance | G65: 46320 | H65: 未取得可核匹配主文；官方页面403，路线已停止 | I65: =HYPERLINK("https://www.greatamericaninsurancegroup.com/about-us/business-operations/product/singapore-branch/portfolio-of-products-and-proposal-forms","https://www.greatamericaninsurancegroup.com/about-us/business-operations/product/singapore-branch/portfolio-of-products-and-proposal-forms") -> https://www.greatamericaninsurancegroup.com/about-us/business-operations/product/singapore-branch/portfolio-of-products-and-proposal-forms | K65: 历史本轮记录日期；非今日重访。停止该受限入口；仅新授权/新官方入口或版本变化后复查。 | L65: D1及历史
A66: SRC-SG-597c7c37be | B66: 新加坡 | C66: Great American Insurance Company, Singapore Branch | D66: 保险公司官方 | E66: www.greatamericaninsurancegroup.com | F66: Great Pleasure Craft Insurance | G66: 46320 | H66: 未取得可核匹配主文；官方页面403，路线已停止 | I66: =HYPERLINK("https://www.greatamericaninsurancegroup.com/about-us/business-operations/product/singapore-branch/portfolio-of-products-and-proposal-forms","https://www.greatamericaninsurancegroup.com/about-us/business-operations/product/singapore-branch/portfolio-of-products-and-proposal-forms") -> https://www.greatamericaninsurancegroup.com/about-us/business-operations/product/singapore-branch/portfolio-of-products-and-proposal-forms | K66: 历史本轮记录日期；非今日重访。停止该受限入口；仅新授权/新官方入口或版本变化后复查。 | L66: D1及历史
A67: SRC-SG-0bb000b8d2 | B67: 新加坡 | C67: Great American Insurance Company, Singapore Branch | D67: 保险公司官方 | E67: www.greatamericaninsurancegroup.com | F67: Great Travel Insurance | G67: 46320 | H67: 未取得可核匹配主文；官方页面403，路线已停止 | I67: =HYPERLINK("https://www.greatamericaninsurancegroup.com/about-us/business-operations/product/singapore-branch/portfolio-of-products-and-proposal-forms","https://www.greatamericaninsurancegroup.com/about-us/business-operations/product/singapore-branch/portfolio-of-products-and-proposal-forms") -> https://www.greatamericaninsurancegroup.com/about-us/business-operations/product/singapore-branch/portfolio-of-products-and-proposal-forms | K67: 历史本轮记录日期；非今日重访。停止该受限入口；仅新授权/新官方入口或版本变化后复查。 | L67: D1及历史
A68: SRC-SG-edd4368a9b | B68: 新加坡 | C68: Great American Insurance Company, Singapore Branch | D68: 保险公司官方 | E68: www.greatamericaninsurancegroup.com | F68: Motor Private Car Insurance | G68: 46320 | H68: 未取得可核匹配主文；官方页面403，路线已停止 | I68: =HYPERLINK("https://www.greatamericaninsurancegroup.com/about-us/business-operations/product/singapore-branch/portfolio-of-products-and-proposal-forms","https://www.greatamericaninsurancegroup.com/about-us/business-operations/product/singapore-branch/portfolio-of-products-and-proposal-forms") -> https://www.greatamericaninsurancegroup.com/about-us/business-operations/product/singapore-branch/portfolio-of-products-and-proposal-forms | K68: 历史本轮记录日期；非今日重访。停止该受限入口；仅新授权/新官方入口或版本变化后复查。 | L68: D1及历史
A69: SRC-SG-6a2d568c59 | B69: 新加坡 | C69: Income Insurance Limited | D69: 保险公司官方 | E69: www.income.com.sg | F69: OCBC Protect Classic | G69: 46320 | H69: 仅关键特性说明，不是主合同 | I69: =HYPERLINK("https://www.income.com.sg/life-insurance/ocbc-protect","https://www.income.com.sg/life-insurance/ocbc-protect") -> https://www.income.com.sg/life-insurance/ocbc-protect | K69: 历史本轮记录日期；非今日重访。仅沿冻结的产品/版本处理明确缺件；不重跑已结案路线。 | L69: D1及历史
A70: SRC-SG-104e4df064 | B70: 新加坡 | C70: Income Insurance Limited | D70: 保险公司官方 | E70: www.income.com.sg | F70: OCBC Protect Prime | G70: 46320 | H70: 仅关键特性说明，不是主合同 | I70: =HYPERLINK("https://www.income.com.sg/life-insurance/ocbc-protect","https://www.income.com.sg/life-insurance/ocbc-protect") -> https://www.income.com.sg/life-insurance/ocbc-protect | K70: 历史本轮记录日期；非今日重访。仅沿冻结的产品/版本处理明确缺件；不重跑已结案路线。 | L70: D1及历史
A71: SRC-SG-f3b52cb43e | B71: 新加坡 | C71: Utmost Worldwide Limited, Singapore Branch | D71: 保险公司官方 | E71: www.utmostgroup.com | F71: FOCUS | G71: 46320 | H71: 重复既有原件，无新增；页码完整性待核 | I71: =HYPERLINK("https://www.utmostgroup.com/document-library/future/business-section/surrender-or-claim/business-topic/policy-conditions","https://www.utmostgroup.com/document-library/future/business-section/surrender-or-claim/business-topic/policy-conditions") -> https://www.utmostgroup.com/document-library/future/business-section/surrender-or-claim/business-topic/policy-conditions | K71: 历史本轮记录日期；非今日重访。仅沿冻结的产品/版本处理明确缺件；不重跑已结案路线。 | L71: D1及历史
A72: SRC-MY-7faf501921 | B72: 马来西亚 | C72: Sun Life Malaysia Assurance Berhad | D72: 保险公司官方 | E72: www.sunlifemalaysia.com | F72: Access Shield Contract (CIMB Bank Berhad)；Biz Shield Master Policy；Biz Shield Plus (Level) Master Policy 等（同来源库） | G72: 46320 | H72: 本轮取得25份正式新增文件，其中0份已全文、25份待全文；文件取得不等于现行主文或资料包齐备 | I72: =HYPERLINK("https://www.sunlifemalaysia.com/client-care/downloads/","https://www.sunlifemalaysia.com/client-care/downloads/") -> https://www.sunlifemalaysia.com/client-care/downloads/ | K72: 历史本轮记录日期；非今日重访。仅沿冻结的产品/版本处理明确缺件；不重跑已结案路线。 | L72: D1及历史
A73: SRC-MY-47c18661b3 | B73: 马来西亚 | C73: Sun Life Malaysia Takaful Berhad | D73: 保险公司官方 | E73: www.sunlifemalaysia.com | F73: Credit Protector Plus-i Master Contract；Group Term Takaful with CI Benefit Master Contract - Private Wealth Privilege Campaign；Group Term Takaful with CI Benefit Master Contract - Guaranteed CI Cover Campaign 等（同来源库） | G73: 46320 | H73: 本轮取得99份正式新增文件，其中0份已全文、99份待全文；文件取得不等于现行主文或资料包齐备 | I73: =HYPERLINK("https://www.sunlifemalaysia.com/client-care/downloads/","https://www.sunlifemalaysia.com/client-care/downloads/") -> https://www.sunlifemalaysia.com/client-care/downloads/ | K73: 历史本轮记录日期；非今日重访。仅沿冻结的产品/版本处理明确缺件；不重跑已结案路线。 | L73: D1及历史
A74: SRC-VN-1428350c8d | B74: 越南 | D74: 保险公司官方 | E74: plgic-production.s3.ap-southeast-1.amazonaws.com | F74: 官方产品目录 | G74: 46320 | H74: 访问失败：403 Forbidden | I74: =HYPERLINK("https://plgic-production.s3.ap-southeast-1.amazonaws.com/2023%2BCorporate%2BWebsite%2BAsset%2BUpdate/OFW%2BPage/Paramount%2BOFW%2BPolicy.pdf.pdf","https://plgic-production.s3.ap-southeast-1.amazonaws.com/2023%2BCorporate%2BWebsite%2BAsset%2BUpdate/OFW%2BPage/Paramount%2BOFW%2BPolicy.pdf.pdf") -> https://plgic-production.s3.ap-southeast-1.amazonaws.com/2023%2BCorporate%2BWebsite%2BAsset%2BUpdate/OFW%2BPage/Paramount%2BOFW%2BPolicy.pdf.pdf | K74: 历史本轮记录日期；非今日重访。停止该受限入口；仅新授权/新官方入口或版本变化后复查。 | L74: D1及历史
A75: SRC-VN-404ccf157c | B75: 越南 | C75: AAA Insurance | D75: 保险公司官方 | E75: www.aaa.com.vn | F75: Apartment Benefits Summary | G75: 46320 | H75: 官方页关联既有材料；仅关系修复，身份/变体及在售未证 | I75: =HYPERLINK("https://www.aaa.com.vn/bao-hiem-can-ho-va-chung-cu","https://www.aaa.com.vn/bao-hiem-can-ho-va-chung-cu") -> https://www.aaa.com.vn/bao-hiem-can-ho-va-chung-cu | J75: =HYPERLINK("https://www.aaa.com.vn/storage/download/[Web]_Quy tac Bao hiem can ho chung cu.pdf","https://www.aaa.com.vn/storage/download/[Web]_Quy tac Bao hiem can ho chung cu.pdf") -> https://www.aaa.com.vn/storage/download/[Web]_Quy tac Bao hiem can ho chung cu.pdf | K75: 历史本轮采集时间。仅沿冻结的产品/版本处理明确缺件；不重跑已结案路线。 | L75: D1及历史
A76: SRC-VN-2f96beb45a | B76: 越南 | C76: AAA Insurance | D76: 保险公司官方 | E76: www.aaa.com.vn | F76: Healthcare Benefits Summary | G76: 46320 | H76: 官方页关联既有材料；仅关系修复，身份/变体及在售未证 | I76: =HYPERLINK("https://www.aaa.com.vn/bao-hiem-cham-soc-suc-khoe","https://www.aaa.com.vn/bao-hiem-cham-soc-suc-khoe") -> https://www.aaa.com.vn/bao-hiem-cham-soc-suc-khoe | J76: =HYPERLINK("https://www.aaa.com.vn/storage/download/quy%20tac%20bao%20hiem%20cham%20soc%20suc%20khoe_compressed.pdf","https://www.aaa.com.vn/storage/download/quy%20tac%20bao%20hiem%20cham%20soc%20suc%20khoe_compressed.pdf") -> https://www.aaa.com.vn/storage/download/quy%20tac%20bao%20hiem%20cham%20soc%20suc%20khoe_compressed.pdf | K76: 历史本轮采集时间。仅沿冻结的产品/版本处理明确缺件；不重跑已结案路线。 | L76: D1及历史
A77: SRC-VN-bd14f78fce | B77: 越南 | C77: Bao Long Insurance Corporation | D77: 保险公司官方 | E77: baolonginsurance.com.vn | F77: International travel benefit schedule | G77: 46320 | H77: 官方页关联既有材料；仅关系修复，身份/变体及在售未证 | I77: =HYPERLINK("https://baolonginsurance.com.vn/san-pham/san-pham-ca-nhan/bao-hiem-du-lich/quyen-loi-bao-hiem-du-lich","https://baolonginsurance.com.vn/san-pham/san-pham-ca-nhan/bao-hiem-du-lich/quyen-loi-bao-hiem-du-lich") -> https://baolonginsurance.com.vn/san-pham/san-pham-ca-nhan/bao-hiem-du-lich/quyen-loi-bao-hiem-du-lich | J77: =HYPERLINK("https://baolonginsurance.com.vn/Data/Sites/1/media/bao hiem ca nhan/bh-du-lich/quy-tac-bao-hiem-du-lich-quoc-te.pdf","https://baolonginsurance.com.vn/Data/Sites/1/media/bao hiem ca nhan/bh-du-lich/quy-tac-bao-hiem-du-lich-quoc-te.pdf") -> https://baolonginsurance.com.vn/Data/Sites/1/media/bao hiem ca nhan/bh-du-lich/quy-tac-bao-hiem-du-lich-quoc-te.pdf | K77: 历史本轮采集时间。仅沿冻结的产品/版本处理明确缺件；不重跑已结案路线。 | L77: D1及历史
A78: SRC-VN-93f49efe38 | B78: 越南 | C78: Công ty TNHH Bảo hiểm nhân thọ Prudential Việt Nam | D78: 保险公司官方 | E78: www.prudential.com.vn | F78: Biểu phí bảo hiểm cơ sở – Bảo hiểm hỗn hợp với quyền lợi học vấn tăng dần | G78: 46320 | H78: 官方页关联既有材料；仅关系修复，身份/变体及在售未证 | I78: =HYPERLINK("https://www.prudential.com.vn/vi/cham-soc-khach-hang/tai-lieu-va-bieu-mau/","https://www.prudential.com.vn/vi/cham-soc-khach-hang/tai-lieu-va-bieu-mau/") -> https://www.prudential.com.vn/vi/cham-soc-khach-hang/tai-lieu-va-bieu-mau/ | J78: =HYPERLINK("https://www.prudential.com.vn/content/dam/prudential-aem-lbu/pva/vi_VN/pdf/san-pham-bao-hiem/pru-tuong-lai-tuoi-sang-tnc.pdf","https://www.prudential.com.vn/content/dam/prudential-aem-lbu/pva/vi_VN/pdf/san-pham-bao-hiem/pru-tuong-lai-tuoi-sang-tnc.pdf") -> https://www.prudential.com.vn/content/dam/prudential-aem-lbu/pva/vi_VN/pdf/san-pham-bao-hiem/pru-tuong-lai-tuoi-sang-tnc.pdf | K78: 历史本轮采集时间。仅沿冻结的产品/版本处理明确缺件；不重跑已结案路线。 | L78: D1及历史
A79: SRC-VN-203ddabe97 | B79: 越南 | C79: Công ty TNHH Bảo hiểm nhân thọ Prudential Việt Nam | D79: 保险公司官方 | E79: www.prudential.com.vn | F79: Biểu phí bảo hiểm cơ sở – Bảo hiểm nhân thọ tử kỳ với số tiền bảo hiểm giảm dần dành cho người đi vay | G79: 46320 | H79: 官方页关联既有材料；仅关系修复，身份/变体及在售未证 | I79: =HYPERLINK("https://www.prudential.com.vn/vi/cham-soc-khach-hang/tai-lieu-va-bieu-mau/","https://www.prudential.com.vn/vi/cham-soc-khach-hang/tai-lieu-va-bieu-mau/") -> https://www.prudential.com.vn/vi/cham-soc-khach-hang/tai-lieu-va-bieu-mau/ | J79: =HYPERLINK("https://www.prudential.com.vn/content/dam/prudential-aem-lbu/pva/vi_VN/pdf/san-pham-bao-hiem/pru-an-tam-bao-tin-ke-hoach-a-qlnc-tnc.pdf","https://www.prudential.com.vn/content/dam/prudential-aem-lbu/pva/vi_VN/pdf/san-pham-bao-hiem/pru-an-tam-bao-tin-ke-hoach-a-qlnc-tnc.pdf") -> https://www.prudential.com.vn/content/dam/prudential-aem-lbu/pva/vi_VN/pdf/san-pham-bao-hiem/pru-an-tam-bao-tin-ke-hoach-a-qlnc-tnc.pdf | K79: 历史本轮采集时间。仅沿冻结的产品/版本处理明确缺件；不重跑已结案路线。 | L79: D1及历史
A80: SRC-VN-425cb5ea4f | B80: 越南 | C80: Công ty TNHH Bảo hiểm nhân thọ Prudential Việt Nam | D80: 保险公司官方 | E80: www.prudential.com.vn | F80: Bảng tỷ lệ phí bảo hiểm cơ bản và các bảng tỷ lệ phí rủi ro – PRU-ĐẦU TƯ VỮNG TIẾN | G80: 46320 | H80: 官方页关联既有材料；仅关系修复，身份/变体及在售未证 | I80: =HYPERLINK("https://www.prudential.com.vn/vi/cham-soc-khach-hang/tai-lieu-va-bieu-mau/","https://www.prudential.com.vn/vi/cham-soc-khach-hang/tai-lieu-va-bieu-mau/") -> https://www.prudential.com.vn/vi/cham-soc-khach-hang/tai-lieu-va-bieu-mau/ | J80: =HYPERLINK("https://www.prudential.com.vn/content/dam/prudential-aem-lbu/pva/vi_VN/pdf/san-pham-bao-hiem/pru-dau-tu-vung-tien-tnc.pdf","https://www.prudential.com.vn/content/dam/prudential-aem-lbu/pva/vi_VN/pdf/san-pham-bao-hiem/pru-dau-tu-vung-tien-tnc.pdf") -> https://www.prudential.com.vn/content/dam/prudential-aem-lbu/pva/vi_VN/pdf/san-pham-bao-hiem/pru-dau-tu-vung-tien-tnc.pdf | K80: 历史本轮采集时间。仅沿冻结的产品/版本处理明确缺件；不重跑已结案路线。 | L80: D1及历史
A81: SRC-VN-d5178fff94 | B81: 越南 | C81: Công ty TNHH Bảo hiểm nhân thọ Prudential Việt Nam | D81: 保险公司官方 | E81: www.prudential.com.vn | F81: Bảng tỷ lệ phí bảo hiểm cơ bản và các bảng tỷ lệ phí rủi ro – PRUBảo Vệ Tối Đa 2.0 | G81: 46320 | H81: 官方页关联既有材料；仅关系修复，身份/变体及在售未证 | I81: =HYPERLINK("https://www.prudential.com.vn/vi/cham-soc-khach-hang/tai-lieu-va-bieu-mau/","https://www.prudential.com.vn/vi/cham-soc-khach-hang/tai-lieu-va-bieu-mau/") -> https://www.prudential.com.vn/vi/cham-soc-khach-hang/tai-lieu-va-bieu-mau/ | J81: =HYPERLINK("https://www.prudential.com.vn/content/dam/prudential-aem-lbu/pva/vi_VN/pdf/san-pham-bao-hiem/pru-bao-ve-toi-da2-tnc.pdf","https://www.prudential.com.vn/content/dam/prudential-aem-lbu/pva/vi_VN/pdf/san-pham-bao-hiem/pru-bao-ve-toi-da2-tnc.pdf") -> https://www.prudential.com.vn/content/dam/prudential-aem-lbu/pva/vi_VN/pdf/san-pham-bao-hiem/pru-bao-ve-toi-da2-tnc.pdf | K81: 历史本轮采集时间。仅沿冻结的产品/版本处理明确缺件；不重跑已结案路线。 | L81: D1及历史
A82: SRC-VN-87150ac483 | B82: 越南 | C82: Công ty TNHH Bảo hiểm nhân thọ Prudential Việt Nam | D82: 保险公司官方 | E82: www.prudential.com.vn | F82: Bảng tỷ lệ phí bảo hiểm hàng năm – PHÚ-TOÀN GIA HƯNG THỊNH | G82: 46320 | H82: 官方页关联既有材料；仅关系修复，身份/变体及在售未证 | I82: =HYPERLINK("https://www.prudential.com.vn/vi/cham-soc-khach-hang/tai-lieu-va-bieu-mau/","https://www.prudential.com.vn/vi/cham-soc-khach-hang/tai-lieu-va-bieu-mau/") -> https://www.prudential.com.vn/vi/cham-soc-khach-hang/tai-lieu-va-bieu-mau/ | J82: =HYPERLINK("https://www.prudential.com.vn/content/dam/prudential-aem-lbu/pva/vi_VN/pdf/san-pham-bao-hiem/phu-toan-gia-hung-thinh-tnc.pdf","https://www.prudential.com.vn/content/dam/prudential-aem-lbu/pva/vi_VN/pdf/san-pham-bao-hiem/phu-toan-gia-hung-thinh-tnc.pdf") -> https://www.prudential.com.vn/content/dam/prudential-aem-lbu/pva/vi_VN/pdf/san-pham-bao-hiem/phu-toan-gia-hung-thinh-tnc.pdf | K82: 历史本轮采集时间。仅沿冻结的产品/版本处理明确缺件；不重跑已结案路线。 | L82: D1及历史
A83: SRC-VN-006032e472 | B83: 越南 | C83: Công ty TNHH Bảo hiểm nhân thọ Prudential Việt Nam | D83: 保险公司官方 | E83: www.prudential.com.vn | F83: Bảng tỷ lệ phí bảo hiểm hàng năm – PHÚ-TÂM AN | G83: 46320 | H83: 官方页关联既有材料；仅关系修复，身份/变体及在售未证 | I83: =HYPERLINK("https://www.prudential.com.vn/vi/cham-soc-khach-hang/tai-lieu-va-bieu-mau/","https://www.prudential.com.vn/vi/cham-soc-khach-hang/tai-lieu-va-bieu-mau/") -> https://www.prudential.com.vn/vi/cham-soc-khach-hang/tai-lieu-va-bieu-mau/ | J83: =HYPERLINK("https://www.prudential.com.vn/content/dam/prudential-aem-lbu/pva/vi_VN/pdf/tai-lieu-bieu-mau/phu-tam-an-dieu-kien-dieu-khoan.pdf","https://www.prudential.com.vn/content/dam/prudential-aem-lbu/pva/vi_VN/pdf/tai-lieu-bieu-mau/phu-tam-an-dieu-kien-dieu-khoan.pdf") -> https://www.prudential.com.vn/content/dam/prudential-aem-lbu/pva/vi_VN/pdf/tai-lieu-bieu-mau/phu-tam-an-dieu-kien-dieu-khoan.pdf | K83: 历史本轮采集时间。仅沿冻结的产品/版本处理明确缺件；不重跑已结案路线。 | L83: D1及历史
A84: SRC-VN-cb42aa884c | B84: 越南 | C84: Công ty TNHH Bảo hiểm nhân thọ Prudential Việt Nam | D84: 保险公司官方 | E84: www.prudential.com.vn | F84: Bảng tỷ lệ phí bảo hiểm – Bảo hiểm nhân thọ hỗn hợp, sản phẩm có quyền lợi học vấn đảm bảo (PHÚ-AN GIA THÀNH TÀI) | G84: 46320 | H84: 官方页关联既有材料；仅关系修复，身份/变体及在售未证 | I84: =HYPERLINK("https://www.prudential.com.vn/vi/cham-soc-khach-hang/tai-lieu-va-bieu-mau/","https://www.prudential.com.vn/vi/cham-soc-khach-hang/tai-lieu-va-bieu-mau/") -> https://www.prudential.com.vn/vi/cham-soc-khach-hang/tai-lieu-va-bieu-mau/ | J84: =HYPERLINK("https://www.prudential.com.vn/content/dam/prudential-aem-lbu/pva/vi_VN/pdf/tai-lieu-bieu-mau/phu-an-gia-thanh-tai-dieu-kien-dieu-khoan.pdf","https://www.prudential.com.vn/content/dam/prudential-aem-lbu/pva/vi_VN/pdf/tai-lieu-bieu-mau/phu-an-gia-thanh-tai-dieu-kien-dieu-khoan.pdf") -> https://www.prudential.com.vn/content/dam/prudential-aem-lbu/pva/vi_VN/pdf/tai-lieu-bieu-mau/phu-an-gia-thanh-tai-dieu-kien-dieu-khoan.pdf | K84: 历史本轮采集时间。仅沿冻结的产品/版本处理明确缺件；不重跑已结案路线。 | L84: D1及历史
A85: SRC-VN-131cdff2d1 | B85: 越南 | C85: Công ty TNHH Bảo hiểm nhân thọ Prudential Việt Nam | D85: 保险公司官方 | E85: www.prudential.com.vn | F85: Bảng tỷ lệ phí bảo hiểm – Bảo hiểm tai nạn cá nhân tăng cường (PRU-NĂNG ĐỘNG official catalog link) | G85: 46320 | H85: 官方页关联既有材料；仅关系修复，身份/变体及在售未证 | I85: =HYPERLINK("https://www.prudential.com.vn/vi/cham-soc-khach-hang/tai-lieu-va-bieu-mau/","https://www.prudential.com.vn/vi/cham-soc-khach-hang/tai-lieu-va-bieu-mau/") -> https://www.prudential.com.vn/vi/cham-soc-khach-hang/tai-lieu-va-bieu-mau/ | J85: =HYPERLINK("https://www.prudential.com.vn/content/dam/prudential-aem-lbu/pva/vi_VN/pdf/san-pham-bao-hiem/pru-nang-dong-tnc.pdf","https://www.prudential.com.vn/content/dam/prudential-aem-lbu/pva/vi_VN/pdf/san-pham-bao-hiem/pru-nang-dong-tnc.pdf") -> https://www.prudential.com.vn/content/dam/prudential-aem-lbu/pva/vi_VN/pdf/san-pham-bao-hiem/pru-nang-dong-tnc.pdf | K85: 历史本轮采集时间。仅沿冻结的产品/版本处理明确缺件；不重跑已结案路线。 | L85: D1及历史
A86: SRC-VN-3f17da0d14 | B86: 越南 | C86: Công ty TNHH Bảo hiểm nhân thọ Prudential Việt Nam | D86: 保险公司官方 | E86: www.prudential.com.vn | F86: Bảng tỷ lệ phí bảo hiểm – Sản phẩm bảo hiểm nhân thọ trọn đời (PHÚ-TRƯỜNG AN) | G86: 46320 | H86: 官方页关联既有材料；仅关系修复，身份/变体及在售未证 | I86: =HYPERLINK("https://www.prudential.com.vn/vi/cham-soc-khach-hang/tai-lieu-va-bieu-mau/","https://www.prudential.com.vn/vi/cham-soc-khach-hang/tai-lieu-va-bieu-mau/") -> https://www.prudential.com.vn/vi/cham-soc-khach-hang/tai-lieu-va-bieu-mau/ | J86: =HYPERLINK("https://www.prudential.com.vn/content/dam/prudential-aem-lbu/pva/vi_VN/pdf/tai-lieu-bieu-mau/phu-truong-an-dieu-kien-dieu-khoan.pdf","https://www.prudential.com.vn/content/dam/prudential-aem-lbu/pva/vi_VN/pdf/tai-lieu-bieu-mau/phu-truong-an-dieu-kien-dieu-khoan.pdf") -> https://www.prudential.com.vn/content/dam/prudential-aem-lbu/pva/vi_VN/pdf/tai-lieu-bieu-mau/phu-truong-an-dieu-kien-dieu-khoan.pdf | K86: 历史本轮采集时间。仅沿冻结的产品/版本处理明确缺件；不重跑已结案路线。 | L86: D1及历史
A87: SRC-VN-da09becf06 | B87: 越南 | C87: Công ty TNHH Bảo hiểm nhân thọ Prudential Việt Nam | D87: 保险公司官方 | E87: www.prudential.com.vn | F87: Bảng tỷ lệ phí bảo hiểm – Sản phẩm bảo hiểm tử kỳ PRUYên Tâm Vui Khỏe | G87: 46320 | H87: 官方页关联既有材料；仅关系修复，身份/变体及在售未证 | I87: =HYPERLINK("https://www.prudential.com.vn/vi/cham-soc-khach-hang/tai-lieu-va-bieu-mau/","https://www.prudential.com.vn/vi/cham-soc-khach-hang/tai-lieu-va-bieu-mau/") -> https://www.prudential.com.vn/vi/cham-soc-khach-hang/tai-lieu-va-bieu-mau/ | J87: =HYPERLINK("https://www.prudential.com.vn/content/dam/prudential-aem-lbu/pva/vi_VN/pdf/san-pham-bao-hiem/yen-tam-vui-khoe-tnc.pdf","https://www.prudential.com.vn/content/dam/prudential-aem-lbu/pva/vi_VN/pdf/san-pham-bao-hiem/yen-tam-vui-khoe-tnc.pdf") -> https://www.prudential.com.vn/content/dam/prudential-aem-lbu/pva/vi_VN/pdf/san-pham-bao-hiem/yen-tam-vui-khoe-tnc.pdf | K87: 历史本轮采集时间。仅沿冻结的产品/版本处理明确缺件；不重跑已结案路线。 | L87: D1及历史
A88: SRC-VN-493c0b7158 | B88: 越南 | C88: Công ty TNHH Bảo hiểm nhân thọ Prudential Việt Nam | D88: 保险公司官方 | E88: www.prudential.com.vn | F88: Bảng tỷ lệ phí bảo hiểm – Sản phẩm có quyền lợi tiền mặt trả định kỳ mỗi hai năm (PHÚ-AN GIA TÍCH LŨY ĐỊNH KỲ) | G88: 46320 | H88: 官方页关联既有材料；仅关系修复，身份/变体及在售未证 | I88: =HYPERLINK("https://www.prudential.com.vn/vi/cham-soc-khach-hang/tai-lieu-va-bieu-mau/","https://www.prudential.com.vn/vi/cham-soc-khach-hang/tai-lieu-va-bieu-mau/") -> https://www.prudential.com.vn/vi/cham-soc-khach-hang/tai-lieu-va-bieu-mau/ | J88: =HYPERLINK("https://www.prudential.com.vn/content/dam/prudential-aem-lbu/pva/vi_VN/pdf/tai-lieu-bieu-mau/phu-an-gia-tich-luy-dinh-ky-dieu-kien-dieu-khoan.pdf","https://www.prudential.com.vn/content/dam/prudential-aem-lbu/pva/vi_VN/pdf/tai-lieu-bieu-mau/phu-an-gia-tich-luy-dinh-ky-dieu-kien-dieu-khoan.pdf") -> https://www.prudential.com.vn/content/dam/prudential-aem-lbu/pva/vi_VN/pdf/tai-lieu-bieu-mau/phu-an-gia-tich-luy-dinh-ky-dieu-kien-dieu-khoan.pdf | K88: 历史本轮采集时间。仅沿冻结的产品/版本处理明确缺件；不重跑已结案路线。 | L88: D1及历史
A89: SRC-VN-def7af999e | B89: 越南 | C89: Công ty TNHH Bảo hiểm nhân thọ Prudential Việt Nam | D89: 保险公司官方 | E89: www.prudential.com.vn | F89: Danh sách gói quyền lợi bảo hiểm của sản phẩm PRU-NĂNG ĐỘNG | G89: 46320 | H89: 官方页关联既有材料；仅关系修复，身份/变体及在售未证 | I89: =HYPERLINK("https://www.prudential.com.vn/vi/cham-soc-khach-hang/tai-lieu-va-bieu-mau/","https://www.prudential.com.vn/vi/cham-soc-khach-hang/tai-lieu-va-bieu-mau/") -> https://www.prudential.com.vn/vi/cham-soc-khach-hang/tai-lieu-va-bieu-mau/ | J89: =HYPERLINK("https://www.prudential.com.vn/content/dam/prudential-aem-lbu/pva/vi_VN/pdf/san-pham-bao-hiem/pru-nang-dong-tnc.pdf","https://www.prudential.com.vn/content/dam/prudential-aem-lbu/pva/vi_VN/pdf/san-pham-bao-hiem/pru-nang-dong-tnc.pdf") -> https://www.prudential.com.vn/content/dam/prudential-aem-lbu/pva/vi_VN/pdf/san-pham-bao-hiem/pru-nang-dong-tnc.pdf | K89: 历史本轮采集时间。仅沿冻结的产品/版本处理明确缺件；不重跑已结案路线。 | L89: D1及历史
A90: SRC-VN-655db3e880 | B90: 越南 | C90: Công ty TNHH Bảo hiểm nhân thọ Prudential Việt Nam | D90: 保险公司官方 | E90: www.prudential.com.vn | F90: Danh sách nghề nghiệp không được tham gia sản phẩm PRU-BẢO VỆ 24/7 / PRU-Guard 24/7 | G90: 46320 | H90: 官方页关联既有材料；仅关系修复，身份/变体及在售未证 | I90: =HYPERLINK("https://www.prudential.com.vn/vi/cham-soc-khach-hang/tai-lieu-va-bieu-mau/","https://www.prudential.com.vn/vi/cham-soc-khach-hang/tai-lieu-va-bieu-mau/") -> https://www.prudential.com.vn/vi/cham-soc-khach-hang/tai-lieu-va-bieu-mau/ | J90: =HYPERLINK("https://www.prudential.com.vn/content/dam/prudential-aem-lbu/pva/vi_VN/pdf/san-pham-bao-hiem/pru-bao-ve-24-7-tc.pdf","https://www.prudential.com.vn/content/dam/prudential-aem-lbu/pva/vi_VN/pdf/san-pham-bao-hiem/pru-bao-ve-24-7-tc.pdf") -> https://www.prudential.com.vn/content/dam/prudential-aem-lbu/pva/vi_VN/pdf/san-pham-bao-hiem/pru-bao-ve-24-7-tc.pdf | K90: 历史本轮采集时间。仅沿冻结的产品/版本处理明确缺件；不重跑已结案路线。 | L90: D1及历史
A91: SRC-VN-a21c7bd44e | B91: 越南 | C91: Công ty TNHH Bảo hiểm nhân thọ Prudential Việt Nam | D91: 保险公司官方 | E91: www.prudential.com.vn | F91: PRU-NHIỆT ĐỚI – Tài liệu giới thiệu sản phẩm và biểu phí | G91: 46320 | H91: 官方页关联既有材料；仅关系修复，身份/变体及在售未证 | I91: =HYPERLINK("https://www.prudential.com.vn/vi/cham-soc-khach-hang/tai-lieu-va-bieu-mau/","https://www.prudential.com.vn/vi/cham-soc-khach-hang/tai-lieu-va-bieu-mau/") -> https://www.prudential.com.vn/vi/cham-soc-khach-hang/tai-lieu-va-bieu-mau/ | J91: =HYPERLINK("https://www.prudential.com.vn/content/dam/prudential-aem-lbu/pva/vi_VN/pdf/san-pham-bao-hiem/pru-nhiet-doi-tnc.pdf","https://www.prudential.com.vn/content/dam/prudential-aem-lbu/pva/vi_VN/pdf/san-pham-bao-hiem/pru-nhiet-doi-tnc.pdf") -> https://www.prudential.com.vn/content/dam/prudential-aem-lbu/pva/vi_VN/pdf/san-pham-bao-hiem/pru-nhiet-doi-tnc.pdf | K91: 历史本轮采集时间。仅沿冻结的产品/版本处理明确缺件；不重跑已结案路线。 | L91: D1及历史
A92: SRC-VN-d2d65e3eda | B92: 越南 | C92: Công ty TNHH Bảo hiểm nhân thọ Prudential Việt Nam | D92: 保险公司官方 | E92: www.prudential.com.vn | F92: PRU-VUI SỐNG – Tài liệu giới thiệu sản phẩm và biểu phí | G92: 46320 | H92: 官方页关联既有材料；仅关系修复，身份/变体及在售未证 | I92: =HYPERLINK("https://www.prudential.com.vn/vi/cham-soc-khach-hang/tai-lieu-va-bieu-mau/","https://www.prudential.com.vn/vi/cham-soc-khach-hang/tai-lieu-va-bieu-mau/") -> https://www.prudential.com.vn/vi/cham-soc-khach-hang/tai-lieu-va-bieu-mau/ | J92: =HYPERLINK("https://www.prudential.com.vn/content/dam/prudential-aem-lbu/pva/vi_VN/pdf/san-pham-bao-hiem/pru-vui-song-tc.pdf","https://www.prudential.com.vn/content/dam/prudential-aem-lbu/pva/vi_VN/pdf/san-pham-bao-hiem/pru-vui-song-tc.pdf") -> https://www.prudential.com.vn/content/dam/prudential-aem-lbu/pva/vi_VN/pdf/san-pham-bao-hiem/pru-vui-song-tc.pdf | K92: 历史本轮采集时间。仅沿冻结的产品/版本处理明确缺件；不重跑已结案路线。 | L92: D1及历史
A93: SRC-VN-8be57c8c72 | B93: 越南 | C93: Công ty TNHH Manulife (Việt Nam) | D93: 保险公司官方 | E93: www.manulife.com.vn | F93: Lưu ý khi tham gia sản phẩm Kiến Tạo Thịnh Vượng | G93: 46320 | H93: 官方页关联既有材料；仅关系修复，身份/变体及在售未证 | I93: =HYPERLINK("https://www.manulife.com.vn/vi/san-pham-bao-hiem/danh-muc-dieu-khoan-san-pham/dieu-khoan-san-pham-chinh.html","https://www.manulife.com.vn/vi/san-pham-bao-hiem/danh-muc-dieu-khoan-san-pham/dieu-khoan-san-pham-chinh.html") -> https://www.manulife.com.vn/vi/san-pham-bao-hiem/danh-muc-dieu-khoan-san-pham/dieu-khoan-san-pham-chinh.html | J93: =HYPERLINK("https://www.manulife.com.vn/content/dam/insurance/vn/documents/about-us/pd_brochure-scb/kien-tao-thinh-vuong/SCB-Kien-Tao-Thinh-Vuong-TnC.pdf","https://www.manulife.com.vn/content/dam/insurance/vn/documents/about-us/pd_brochure-scb/kien-tao-thinh-vuong/SCB-Kien-Tao-Thinh-Vuong-TnC.pdf") -> https://www.manulife.com.vn/content/dam/insurance/vn/documents/about-us/pd_brochure-scb/kien-tao-thinh-vuong/SCB-Kien-Tao-Thinh-Vuong-TnC.pdf | K93: 历史本轮采集时间。仅沿冻结的产品/版本处理明确缺件；不重跑已结案路线。 | L93: D1及历史
A94: SRC-VN-4625637f1e | B94: 越南 | C94: Công ty TNHH Manulife (Việt Nam) | D94: 保险公司官方 | E94: www.manulife.com.vn | F94: Lưu ý khi tham gia sản phẩm Tâm An 360 | G94: 46320 | H94: 官方页关联既有材料；仅关系修复，身份/变体及在售未证 | I94: =HYPERLINK("https://www.manulife.com.vn/vi/san-pham-bao-hiem/danh-muc-dieu-khoan-san-pham/dieu-khoan-san-pham-chinh.html","https://www.manulife.com.vn/vi/san-pham-bao-hiem/danh-muc-dieu-khoan-san-pham/dieu-khoan-san-pham-chinh.html") -> https://www.manulife.com.vn/vi/san-pham-bao-hiem/danh-muc-dieu-khoan-san-pham/dieu-khoan-san-pham-chinh.html | J94: =HYPERLINK("https://www.manulife.com.vn/content/dam/insurance/vn/documents/about-us/pd_brochure-scb/tam-an-360/dieu-khoan-san-pham.pdf","https://www.manulife.com.vn/content/dam/insurance/vn/documents/about-us/pd_brochure-scb/tam-an-360/dieu-khoan-san-pham.pdf") -> https://www.manulife.com.vn/content/dam/insurance/vn/documents/about-us/pd_brochure-scb/tam-an-360/dieu-khoan-san-pham.pdf | K94: 历史本轮采集时间。仅沿冻结的产品/版本处理明确缺件；不重跑已结案路线。 | L94: D1及历史
A95: SRC-VN-0e2027dbc1 | B95: 越南 | C95: Công ty TNHH Manulife (Việt Nam) | D95: 保险公司官方 | E95: www.manulife.com.vn | F95: Lưu ý khi tham gia sản phẩm bổ trợ Sống Khỏe Mỗi Ngày | G95: 46320 | H95: 官方页关联既有材料；仅关系修复，身份/变体及在售未证 | I95: =HYPERLINK("https://www.manulife.com.vn/vi/san-pham-bao-hiem/danh-muc-dieu-khoan-san-pham/dieu-khoan-san-pham-chinh.html","https://www.manulife.com.vn/vi/san-pham-bao-hiem/danh-muc-dieu-khoan-san-pham/dieu-khoan-san-pham-chinh.html") -> https://www.manulife.com.vn/vi/san-pham-bao-hiem/danh-muc-dieu-khoan-san-pham/dieu-khoan-san-pham-chinh.html | J95: =HYPERLINK("https://www.manulife.com.vn/content/dam/insurance/vn/documents/ngan-hang/brochure/scb/Quy-Tac-Va-Dieu-Khoan-Song-Khoe-Moi-Ngay.pdf","https://www.manulife.com.vn/content/dam/insurance/vn/documents/ngan-hang/brochure/scb/Quy-Tac-Va-Dieu-Khoan-Song-Khoe-Moi-Ngay.pdf") -> https://www.manulife.com.vn/content/dam/insurance/vn/documents/ngan-hang/brochure/scb/Quy-Tac-Va-Dieu-Khoan-Song-Khoe-Moi-Ngay.pdf | K95: 历史本轮采集时间。仅沿冻结的产品/版本处理明确缺件；不重跑已结案路线。 | L95: D1及历史
A96: SRC-VN-3512149658 | B96: 越南 | C96: Post - Telecommunication Joint Stock Insurance Corporation (PTI) | D96: 保险公司官方 | E96: www.pti.com.vn | F96: bao-hiem-elite-care | G96: 46320 | H96: 官方页关联既有材料；仅关系修复，身份/变体及在售未证 | I96: =HYPERLINK("https://www.pti.com.vn/pticare/bao-hiem-elite-care/","https://www.pti.com.vn/pticare/bao-hiem-elite-care/") -> https://www.pti.com.vn/pticare/bao-hiem-elite-care/ | J96: =HYPERLINK("https://www.pti.com.vn/wp-content/uploads/2026/10/QTBH-suc-khoe-Cao-cap-21_Elitecare.pdf","https://www.pti.com.vn/wp-content/uploads/2026/10/QTBH-suc-khoe-Cao-cap-21_Elitecare.pdf") -> https://www.pti.com.vn/wp-content/uploads/2026/10/QTBH-suc-khoe-Cao-cap-21_Elitecare.pdf | K96: 历史本轮采集时间。仅沿冻结的产品/版本处理明确缺件；不重跑已结案路线。 | L96: D1及历史
A97: SRC-VN-88137741f4 | B97: 越南 | C97: Post - Telecommunication Joint Stock Insurance Corporation (PTI) | D97: 保险公司官方 | E97: www.pti.com.vn | F97: bao-hiem-phuc-an-sinh | G97: 46320 | H97: 官方页关联既有材料；仅关系修复，身份/变体及在售未证 | I97: =HYPERLINK("https://www.pti.com.vn/pticare/bao-hiem-phuc-an-sinh/","https://www.pti.com.vn/pticare/bao-hiem-phuc-an-sinh/") -> https://www.pti.com.vn/pticare/bao-hiem-phuc-an-sinh/ | J97: =HYPERLINK("https://www.pti.com.vn/wp-content/uploads/2025/01/Quy-tac-BH-Phuc-An-Sinh.pdf","https://www.pti.com.vn/wp-content/uploads/2025/01/Quy-tac-BH-Phuc-An-Sinh.pdf") -> https://www.pti.com.vn/wp-content/uploads/2025/01/Quy-tac-BH-Phuc-An-Sinh.pdf | K97: 历史本轮采集时间。仅沿冻结的产品/版本处理明确缺件；不重跑已结案路线。 | L97: D1及历史
A98: SRC-ID-74cb1ae306 | B98: 印度尼西亚 | C98: PT Asuransi Multi Artha Guna Tbk | D98: 保险公司官方 | E98: www.mag.co.id | F98: Polis Standar Asuransi Pengangkutan Barang Indonesia (PSAPBI)；Polis Standar Asuransi Terorisme dan Sabotase Indonesia (PSATSI) | G98: 46320 | H98: 本轮取得2份正式新增文件，其中1份已全文、1份待全文；文件取得不等于现行主文或资料包齐备 | I98: =HYPERLINK("https://www.mag.co.id/download/","https://www.mag.co.id/download/") -> https://www.mag.co.id/download/ | K98: 历史本轮记录日期；非今日重访。仅沿冻结的产品/版本处理明确缺件；不重跑已结案路线。 | L98: D1及历史
A99: SRC-TH-7a4f799093 | B99: 泰国 | C99: Prudential Life Assurance (Thailand) Public Company Limited | D99: 公开中介页面（身份待核） | E99: insurance.add-digital.co.th | F99: PRUEasy Saver 10/4 contract-details (broker candidate) | G99: 46320 | H99: 公开中介关联PDF返回403；未取得文件，停止该入口 | I99: =HYPERLINK("https://insurance.add-digital.co.th/th/prueasy-saver-104","https://insurance.add-digital.co.th/th/prueasy-saver-104") -> https://insurance.add-digital.co.th/th/prueasy-saver-104 | J99: =HYPERLINK("https://insurance.add-digital.co.th/medias/add-cloudcms/space/Saving/PRUEasy-Saver-10-4/PRUEasy-Saver-10-4.pdf","https://insurance.add-digital.co.th/medias/add-cloudcms/space/Saving/PRUEasy-Saver-10-4/PRUEasy-Saver-10-4.pdf") -> https://insurance.add-digital.co.th/medias/add-cloudcms/space/Saving/PRUEasy-Saver-10-4/PRUEasy-Saver-10-4.pdf | K99: 历史本轮记录日期；非今日重访。停止该受限入口；仅新授权/新官方入口或版本变化后复查。 | L99: D1及历史
A100: SRC-TH-6e47b38dfc | B100: 泰国 | C100: Roojai Insurance Public Company Limited | D100: 保险公司官方 | E100: www.roojai.com | F100: 集中条款/下载库 | G100: 46320 | H100: 既有正式库包含24份该来源文件；最近补缺路径为重复已有条款，不计新增；未在本次重新访问 | I100: =HYPERLINK("https://www.roojai.com/en/policy-wordings/","https://www.roojai.com/en/policy-wordings/") -> https://www.roojai.com/en/policy-wordings/ | K100: 本轮重复取得记录日期；不是全部文件重新全文核验。仅沿冻结的产品/版本处理明确缺件；不重跑已结案路线。 | L100: D1及历史
...

Sheet 验收口径
A1: 项目 | B1: 口径／动作 | C1: 验收必备 | D1: 计数边界
A2: 冻结范围 | B2: 原258工单及历史数据保留；B28新增1条状态纠正工单，累计259。 | C2: 任务ID、原始ID及来源ID保持稳定。各批冻结期初不写成验收结果。 | D2: 259为限定工单，不是独立产品。B28无新增全文，窄核45页不计入4250全审页。
A3: 证据验收 | B3: 证据验收与内容、文件主角色、产品主文可得、当前包齐备及严格通过分别记录。 | C3: 复核通过、证据非空、有效处理日及唯一冻结范围匹配。 | D3: 只有已验收明确增量纳入。部分语言审读、通用组件和材料映射不得自动升格。
A4: 完整主文 | B4: 正文应具备可读完整内容、连续页序与准确身份，不以文件名、宣传册、文本提取成功或可下载代替。 | C4: 逐页页码及内容记录；法律主体、渠道、文档角色、版本或未知标记；依赖组件与缺件。 | D4: 严格通过按文件计，不直接等于独立产品或整套合同齐备。
A5: 版本与采用 | B5: 正文印载版本、官方当前采用与产品现售状态分别核验。URL目录年份不能替代版次。 | C5: 精确版本／组件及明确采用依据。没有证据时保持未知。 | D5: Home Protector 360 与 Basic 分开。FOCUS 21物理页／24页脚疑点未解除前不得升级完整。
A6: 马来西亚文档 | B6: D1冻结5份原件114页，B2另核5份原件187页，不重复计数。Assurance与Takaful分开，团体与个人不混用。 | C6: 按原始文档身份和哈希核全文；保留英文／马来文判断依据及疑点页码。 | D6: Master 文档核验不等于具名产品锁定、现行主文采用或整套齐备。
A7: 来源日期 | B7: 各批均于2026-10-26冻结。历史来源保持原检查日；新公开响应观测日另列，不把全文审读日当作重新取得日。 | C7: 新执行证据另记实际访问／核验时间、官方 URL 和结果。 | D7: v89 历史原件、全文、严格通过与隔离文件，不计入本批新增。
A8: 公开入口边界 | B8: 只检查固定范围的公开官方入口及明确匹配来源。遇403、登录、验证码或WAF停止该入口。 | C8: 保留已查路线、访问结果和停止原因；不猜路径、不绕过限制、不外联、不搜索真实个人保单。 | D8: 受阻或未取得保留原任务，不删除、不升级为已齐备。
A9: 未知与零 | B9: 缺少经核验的统计时留空并注明。零仅用于已确认范围内的真实零。 | C9: 列明统计对象、单位、来源和分母。家族范围不是全市场产品数。 | D9: 全市场独立产品分母尚未核定；不据此计算全市场覆盖率。
A12: 校验项 | B12: 实际值 | C12: 冻结基数 | D12: 判定
A13: 地区行数 | B13: =COUNTA('12地区基线'!A2:A13) -> 12 | C13: 12 | D13: =IF(B13=C13,"一致","需检查增删") -> 一致
A14: 任务行数 | B14: =COUNTA(首批固定任务!A2:A109) -> 108 | C14: 108 | D14: =IF(B14=C14,"一致","需检查增删") -> 一致
A15: 来源行数 | B15: =COUNTA(保司与来源!A2:A243) -> 242 | C15: 242 | D15: =IF(B15=C15,"一致","需检查增删") -> 一致
A16: 正式文件合计 | B16: =SUM('12地区基线'!D2:D13) -> 4710 | C16: 4710 | D16: =IF(B16=C16,"一致","需检查增删") -> 一致
A17: 已全文审阅合计 | B17: =SUM('12地区基线'!E2:E13) -> 2245 | C17: 2245 | D17: =IF(B17=C17,"一致","需检查增删") -> 一致
A18: 严格通过合计 | B18: =SUM('12地区基线'!F2:F13) -> 411 | C18: 411 | D18: =IF(B18=C18,"一致","需检查增删") -> 一致
A19: 隔离文件合计 | B19: =SUM('12地区基线'!G2:G13) -> 51 | C19: 51 | D19: =IF(B19=C19,"一致","需检查增删") -> 一致
A21: 冻结任务ID | B21: 冻结表出现次数 | C21: 执行表出现次数 | D21: 范围判定
A22: D1-HK-001 | B22: =COUNTIFS(首批固定任务!$A$2:$A$24,A22) -> 1 | C22: =COUNTIFS(本批执行结果!$A$2:$A$24,A22) -> 1 | D22: =IF(AND(B22=1,C22=1),"一致","缺范围或重复") -> 一致
A23: D1-HK-002 | B23: =COUNTIFS(首批固定任务!$A$2:$A$24,A23) -> 1 | C23: =COUNTIFS(本批执行结果!$A$2:$A$24,A23) -> 1 | D23: =IF(AND(B23=1,C23=1),"一致","缺范围或重复") -> 一致
A24: D1-HK-003 | B24: =COUNTIFS(首批固定任务!$A$2:$A$24,A24) -> 1 | C24: =COUNTIFS(本批执行结果!$A$2:$A$24,A24) -> 1 | D24: =IF(AND(B24=1,C24=1),"一致","缺范围或重复") -> 一致
A25: D1-HK-004 | B25: =COUNTIFS(首批固定任务!$A$2:$A$24,A25) -> 1 | C25: =COUNTIFS(本批执行结果!$A$2:$A$24,A25) -> 1 | D25: =IF(AND(B25=1,C25=1),"一致","缺范围或重复") -> 一致
A26: D1-SG-001 | B26: =COUNTIFS(首批固定任务!$A$2:$A$24,A26) -> 1 | C26: =COUNTIFS(本批执行结果!$A$2:$A$24,A26) -> 1 | D26: =IF(AND(B26=1,C26=1),"一致","缺范围或重复") -> 一致
A27: D1-SG-002 | B27: =COUNTIFS(首批固定任务!$A$2:$A$24,A27) -> 1 | C27: =COUNTIFS(本批执行结果!$A$2:$A$24,A27) -> 1 | D27: =IF(AND(B27=1,C27=1),"一致","缺范围或重复") -> 一致
A28: D1-SG-003 | B28: =COUNTIFS(首批固定任务!$A$2:$A$24,A28) -> 1 | C28: =COUNTIFS(本批执行结果!$A$2:$A$24,A28) -> 1 | D28: =IF(AND(B28=1,C28=1),"一致","缺范围或重复") -> 一致
A29: D1-MY-001 | B29: =COUNTIFS(首批固定任务!$A$2:$A$24,A29) -> 1 | C29: =COUNTIFS(本批执行结果!$A$2:$A$24,A29) -> 1 | D29: =IF(AND(B29=1,C29=1),"一致","缺范围或重复") -> 一致
A30: D1-MY-002 | B30: =COUNTIFS(首批固定任务!$A$2:$A$24,A30) -> 1 | C30: =COUNTIFS(本批执行结果!$A$2:$A$24,A30) -> 1 | D30: =IF(AND(B30=1,C30=1),"一致","缺范围或重复") -> 一致
A31: D1-MY-003 | B31: =COUNTIFS(首批固定任务!$A$2:$A$24,A31) -> 1 | C31: =COUNTIFS(本批执行结果!$A$2:$A$24,A31) -> 1 | D31: =IF(AND(B31=1,C31=1),"一致","缺范围或重复") -> 一致
A32: D1-MY-004 | B32: =COUNTIFS(首批固定任务!$A$2:$A$24,A32) -> 1 | C32: =COUNTIFS(本批执行结果!$A$2:$A$24,A32) -> 1 | D32: =IF(AND(B32=1,C32=1),"一致","缺范围或重复") -> 一致
A33: D1-MY-005 | B33: =COUNTIFS(首批固定任务!$A$2:$A$24,A33) -> 1 | C33: =COUNTIFS(本批执行结果!$A$2:$A$24,A33) -> 1 | D33: =IF(AND(B33=1,C33=1),"一致","缺范围或重复") -> 一致
... A44: B2-KH-002 | B44: =COUNTIFS(首批固定任务!$A$2:$A$24,A44) -> 1 | C44: =COUNTIFS(本批执行结果!$A$2:$A$24,A44) -> 1 | D44: =IF(AND(B44=1,C44=1),"一致","缺范围或重复") -> 一致
A46: B2内容分层 | B46: 6份现存全文205页。4份主文角色确认后仍待核验。 | C46: 32页EASYCare视觉结构证据独立保存，不计全文。 | D46: 新原件0、严格新增0、独立产品缺口关闭0。
A47: D1/B2历史发布 | B47: 两批已发布至线上版本115。网站已更新第二批核验状态。 | C47: 正式原件4713、公开4662、全文2256、部分核验14、严格411、隔离51。 | D47: B2新增6份全文已在线。原件与详审证据私有留存。
A48: 后续批次 | B48: B3/B4/B5/B6见新增验收与审计区；不把旧候选状态视为当前。 | C48: 历史23、67、108、198、203、210、218、238、258保留；B28追加后259。 | D48: 完整原始文件数、全文、角色、严格和产品闭合分层计量。
A50: 使用权限 | B50: 全文审读表示内容检查，不代表允许复制、再发布或商业复用。 | C50: 受限文件不提供可自动使用的提取文本。 | D50: 原件及审计历史保持。
A53: 追加批次审计 | B53: 冻结表次数 | C53: 执行表次数 | D53: 范围判定
A54: B3-MY-001 | B54: =COUNTIFS(首批固定任务!$A$2:$A$68,A54) -> 1 | C54: =COUNTIFS(本批执行结果!$A$2:$A$68,A54) -> 1 | D54: =IF(AND(B54=1,C54=1),"一致","缺范围或重复") -> 一致
A55: B3-MY-002 | B55: =COUNTIFS(首批固定任务!$A$2:$A$68,A55) -> 1 | C55: =COUNTIFS(本批执行结果!$A$2:$A$68,A55) -> 1 | D55: =IF(AND(B55=1,C55=1),"一致","缺范围或重复") -> 一致
A56: B3-MY-003 | B56: =COUNTIFS(首批固定任务!$A$2:$A$68,A56) -> 1 | C56: =COUNTIFS(本批执行结果!$A$2:$A$68,A56) -> 1 | D56: =IF(AND(B56=1,C56=1),"一致","缺范围或重复") -> 一致
A57: B3-MY-004 | B57: =COUNTIFS(首批固定任务!$A$2:$A$68,A57) -> 1 | C57: =COUNTIFS(本批执行结果!$A$2:$A$68,A57) -> 1 | D57: =IF(AND(B57=1,C57=1),"一致","缺范围或重复") -> 一致
A58: B3-MY-005 | B58: =COUNTIFS(首批固定任务!$A$2:$A$68,A58) -> 1 | C58: =COUNTIFS(本批执行结果!$A$2:$A$68,A58) -> 1 | D58: =IF(AND(B58=1,C58=1),"一致","缺范围或重复") -> 一致
A59: B3-HK-001 | B59: =COUNTIFS(首批固定任务!$A$2:$A$68,A59) -> 1 | C59: =COUNTIFS(本批执行结果!$A$2:$A$68,A59) -> 1 | D59: =IF(AND(B59=1,C59=1),"一致","缺范围或重复") -> 一致
A60: B3-HK-002 | B60: =COUNTIFS(首批固定任务!$A$2:$A$68,A60) -> 1 | C60: =COUNTIFS(本批执行结果!$A$2:$A$68,A60) -> 1 | D60: =IF(AND(B60=1,C60=1),"一致","缺范围或重复") -> 一致
A61: B3-VN-001 | B61: =COUNTIFS(首批固定任务!$A$2:$A$68,A61) -> 1 | C61: =COUNTIFS(本批执行结果!$A$2:$A$68,A61) -> 1 | D61: =IF(AND(B61=1,C61=1),"一致","缺范围或重复") -> 一致
A62: B3-VN-002 | B62: =COUNTIFS(首批固定任务!$A$2:$A$68,A62) -> 1 | C62: =COUNTIFS(本批执行结果!$A$2:$A$68,A62) -> 1 | D62: =IF(AND(B62=1,C62=1),"一致","缺范围或重复") -> 一致
A63: B3-KH-001 | B63: =COUNTIFS(首批固定任务!$A$2:$A$68,A63) -> 1 | C63: =COUNTIFS(本批执行结果!$A$2:$A$68,A63) -> 1 | D63: =IF(AND(B63=1,C63=1),"一致","缺范围或重复") -> 一致
A64: B4-MY-001 | B64: =COUNTIFS(首批固定任务!$A$2:$A$68,A64) -> 1 | C64: =COUNTIFS(本批执行结果!$A$2:$A$68,A64) -> 1 | D64: =IF(AND(B64=1,C64=1),"一致","缺范围或重复") -> 一致
A65: B4-MY-002 | B65: =COUNTIFS(首批固定任务!$A$2:$A$68,A65) -> 1 | C65: =COUNTIFS(本批执行结果!$A$2:$A$68,A65) -> 1 | D65: =IF(AND(B65=1,C65=1),"一致","缺范围或重复") -> 一致
... A97: B6-SG-012 | B97: =COUNTIFS(首批固定任务!$A$2:$A$68,A97) -> 1 | C97: =COUNTIFS(本批执行结果!$A$2:$A$68,A97) -> 1 | D97: =IF(AND(B97=1,C97=1),"一致","缺范围或重复") -> 一致
A99: B3验收 | B99: 10任务；5份现存全文184页；主文净+4。 | C99: VN两个任务共4项历史关联，现行采用仍待核。 | D99: KH英文13页不升整份全文；高棉语12页语义未核。
A100: B4验收 | B100: 7份全文213页；ID18页partial，主文0；MY主文+5。 | C100: 身份2工作单、4版本及31关系，均不产生新全文／主文。 | D100: MM组件全文不变成主合同；ID印尼语优先未全审；目录名不证明具名采用。
A101: B5来源 | B101: 7份产品页live HTTP 200；5份摘录HTTP未知。 | C101: HSBC含policy文件名仍是产品册或服务表格。 | D101: 10Life旧版广告主供稿，非独立佐证或恒生授权销售证据。
A102: 访问边界 | B102: BOCHK工具超时不是来源HTTP 400。 | C102: 缓存年龄不是本次来源核验日期，摘录不保证全页。 | D102: 未取得不等于不存在；不声称全部公开路线穷尽。
A103: 实际发布 | B103: 实际网站v126／固定私有索引v102。 | C103: 网站部署、三个固定索引精确远端回验、独立终态及双私有指针均确认。 | D103: Site126／index102全文2342、部分17、主角色2749、严格423。
A104: 权利说明 | B104: 全文审读与可读不授予复制、打印、转载、再托管或商用许可。 | C104: 历史权限审计单独追加；既有冻结事实不被追溯改写。 | D104: 旧提取／渲染证据仅用于审计，不因此新增复用授权。
A106: B6来源 | B106: 12项任务对应11个唯一官方URL，响应均200并校验正文哈希；未下载PDF。 | C106: 294身份层与较窄144范围均非全市场分母；版本与币种不互换。 | D106: SingSaver编辑页及页脚自述不确立目标销售授权；403拒绝和无主文分开。
A109: B7–B14追加范围审计 | B109: 冻结表次数 | C109: 执行表次数 | D109: 范围判定
A110: B7-MY-001 | B110: =COUNTIFS(首批固定任务!$A$2:$A$109,A110) -> 1 | C110: =COUNTIFS(本批执行结果!$A$2:$A$109,A110) -> 1 | D110: =IF(AND(B110=1,C110=1),"一致","需核对") -> 一致
A111: B7-MY-002 | B111: =COUNTIFS(首批固定任务!$A$2:$A$109,A111) -> 1 | C111: =COUNTIFS(本批执行结果!$A$2:$A$109,A111) -> 1 | D111: =IF(AND(B111=1,C111=1),"一致","需核对") -> 一致
A112: B7-MY-003 | B112: =COUNTIFS(首批固定任务!$A$2:$A$109,A112) -> 1 | C112: =COUNTIFS(本批执行结果!$A$2:$A$109,A112) -> 1 | D112: =IF(AND(B112=1,C112=1),"一致","需核对") -> 一致
A113: B7-MM-001 | B113: =COUNTIFS(首批固定任务!$A$2:$A$109,A113) -> 1 | C113: =COUNTIFS(本批执行结果!$A$2:$A$109,A113) -> 1 | D113: =IF(AND(B113=1,C113=1),"一致","需核对") -> 一致
A114: B7-MM-002 | B114: =COUNTIFS(首批固定任务!$A$2:$A$109,A114) -> 1 | C114: =COUNTIFS(本批执行结果!$A$2:$A$109,A114) -> 1 | D114: =IF(AND(B114=1,C114=1),"一致","需核对") -> 一致
A115: B7-MM-003 | B115: =COUNTIFS(首批固定任务!$A$2:$A$109,A115) -> 1 | C115: =COUNTIFS(本批执行结果!$A$2:$A$109,A115) -> 1 | D115: =IF(AND(B115=1,C115=1),"一致","需核对") -> 一致
A116: B7-MM-004 | B116: =COUNTIFS(首批固定任务!$A$2:$A$109,A116) -> 1 | C116: =COUNTIFS(本批执行结果!$A$2:$A$109,A116) -> 1 | D116: =IF(AND(B116=1,C116=1),"一致","需核对") -> 一致
A117: B7-MM-005 | B117: =COUNTIFS(首批固定任务!$A$2:$A$109,A117) -> 1 | C117: =COUNTIFS(本批执行结果!$A$2:$A$109,A117) -> 1 | D117: =IF(AND(B117=1,C117=1),"一致","需核对") -> 一致
A118: B8-MY-001 | B118: =COUNTIFS(首批固定任务!$A$2:$A$109,A118) -> 1 | C118: =COUNTIFS(本批执行结果!$A$2:$A$109,A118) -> 1 | D118: =IF(AND(B118=1,C118=1),"一致","需核对") -> 一致
A119: B8-MY-002 | B119: =COUNTIFS(首批固定任务!$A$2:$A$109,A119) -> 1 | C119: =COUNTIFS(本批执行结果!$A$2:$A$109,A119) -> 1 | D119: =IF(AND(B119=1,C119=1),"一致","需核对") -> 一致
A120: B8-MY-003 | B120: =COUNTIFS(首批固定任务!$A$2:$A$109,A120) -> 1 | C120: =COUNTIFS(本批执行结果!$A$2:$A$109,A120) -> 1 | D120: =IF(AND(B120=1,C120=1),"一致","需核对") -> 一致
A121: B8-MY-004 | B121: =COUNTIFS(首批固定任务!$A$2:$A$109,A121) -> 1 | C121: =COUNTIFS(本批执行结果!$A$2:$A$109,A121) -> 1 | D121: =IF(AND(B121=1,C121=1),"一致","需核对") -> 一致
... A150: B14-HK-002 | B150: =COUNTIFS(首批固定任务!$A$2:$A$109,A150) -> 1 | C150: =COUNTIFS(本批执行结果!$A$2:$A$109,A150) -> 1 | D150: =IF(AND(B150=1,C150=1),"一致","需核对") -> 一致
A153: 分层验收 | B153: 来源路线、文件角色、现存页全审、严格状态分别记录。 | C153: 当前采用、公开通用合同包、个人合同齐套分别核证。 | D153: 当前采用／齐套未证，不阻止符合定义的文件级verified；反向亦不能推导闭合。
A154: B7组件 | B154: 8份125页全审，主角色+3。 | C154: MM五份40页仅Institute组件；MY三份85页。 | D154: 不是8份独立主合同，也非当前已采用的完整海事保单。
A155: B8文件级通过 | B155: MY-SUN-068和MY-SUN-025严格+2。 | C155: 其余3份主附表／内部引用hold保留。 | D155: 普通视觉阅读不产生复制、打印、再托管或商业复用授权。
A156: B9/B10计数 | B156: B9十二既有家族＋B10一条变体线索为13工单。 | C156: 一次缴费与两年缴费版本不互换。 | D156: HTTP 403拒绝与无响应传输不确定分开；不声称全网不存在。
A157: B11关系 | B157: 4份103页均为非合同信息说明。 | C157: 1项同编号／持有人历史解释关系；另外3候选保持未定。 | D157: 不认定合同并入、补齐主附表、准确版次采用或产品合并。
A158: B12严格 | B158: 5份195页均为零售主合同文件。 | C158: 仅PA Direct文件级verified；Home／Travel／HealthPro／Prime Pro保留明确问题。 | D158: 当前采用、签发、个体齐套与文件级严格独立。
A159: B13证据限制 | B159: 响应正文和正文SHA均未保存。 | C159: 浏览器说明由执行者转录／重建，不能独立回放或声称视觉QA。 | D159: 503不是权限拒绝；SPAN无href不能排除点击处理或其他公开条款。
A160: B14证据限制 | B160: 工具元数据摘录及哈希一致，不是完整原始浏览器轨迹。 | C160: 点击前后及等待完成为时段／上界；截图未留供独立视觉复核。 | D160: 两次探测未得文档URL／PDF。无新原件、主文、全文、严格或产品闭合。
A161: 统计重计 | B161: D1–B14共108工单、45份既存全审1243页。 | C161: 新支持原件3、主角色净+26、严格+3；产品／包闭合0。 | D161: B15试点排除。不是108个或45个已完成产品。
A162: 发布与验收 | B162: 本地内容已验收不等于远端已发布。 | C162: 只用成功部署和精确固定索引回验更新当前发布字段。 | D162: B4/B5/B6的v117／v93及早期发布记录作为历史保留。
A166: 角色层独立计量 | B166: B15–B18共90；原D1–B14共108，合计198工单。 | C166: 90角色记录按原件ID＋SHA匹配，不覆盖历史审读层。 | D166: 45份全审1243页／3支持原件及期初138不变。
A167: 页数口径 | B167: 库存5186；执行有限锚点945；独立QA有限锚点627。 | C167: 执行和QA页码分别列明；二者重叠，不相加。 | D167: 锚点检查不等于选中页通读，更不等于全文。
... A249: 余项与后续采集 | B249: 固定138逐SHA实际对账，余项及下一步见“交付范围与后续采集”。 | C249: 旧17及条件11不是独立完成证据；按真实最终状态刷新。 | D249: 官方联系未获发送批准且此前readiness失败；未发送、未等回信。

Sheet MY身份与材料
A1: MY限定合同身份与材料关系
A2: 仅2个身份工作单、4个既审合同版本及31项材料关系。不是全市场产品分母；不新增原件、全文、主文、严格或产品闭合。
A4: 原始ID | B4: 法律主体 | C4: 正文计划名 | D4: 合同号 | E4: 已审版本依据 | F4: 版本登记ID | G4: 历史主文角色 | H4: 当前精确采用 | I4: 当前在售 | J4: 当前公开合同包
A5: MY-SUN-006 | B5: Sun Life Malaysia Assurance Berhad | C5: Cash Plus Assurance | D5: CPA0613 | E5: 2015-01-01 / 2020-07-01 / 2025-07-01 批单集合；非现行采用证明 | F5: MY-CV-db45e5380bd10dcf4637ad23 | G5: 已核（历史） | H5: 未核定（非否定） | I5: 未核定（非否定） | J5: 未确认齐备
A6: MY-SUN-008 | B6: Sun Life Malaysia Assurance Berhad | C6: Credit Protector Plus | D6: CPP0813 | E6: 2016-04-01 / 2020-07-01 / 2021-05-28 / 2025-07-01 批单集合；非现行采用证明 | F6: MY-CV-58044f828aef3206e86806c8 | G6: 已核（历史） | H6: 未核定（非否定） | I6: 未核定（非否定） | J6: 未确认齐备
A7: MY-SUN-002 | B7: Sun Life Malaysia Assurance Berhad | C7: Biz Shield | D7: BIZS0914 | E7: 2015-01-01 / 2020-07-01 / 2025-07-01 批单集合；非现行采用证明 | F7: MY-CV-662b30a1b4203ee9442d934b | G7: 非主文（历史） | H7: 未核定（非否定） | I7: 未核定（非否定） | J7: 未确认齐备
A8: MY-SUN-036 | B8: Sun Life Malaysia Takaful Berhad | C8: Biz Shield-i | D8: BSI0317 | E8: 2019-07-01 / 2020-07-01 / 2025-07-01 批单集合；非现行采用证明 | F8: MY-CV-b69be7a48e4192e2e2b1bb23 | G8: 已核（历史） | H8: 未核定（非否定） | I8: 未核定（非否定） | J8: 未确认齐备
A10: 材料关系 ≠ 实际采用：附表、组件、批单及目录关联分别登记；空白／未核定不能作通配合并，Assurance与Takaful分开。
A12: 原始ID | B12: 材料角色 | C12: 材料标签 | D12: 组件编号 | E12: 物理页／范围 | F12: 原件中存在 | G12: 依赖分类 | H12: 关联性质 | I12: 当前采用／现售 | J12: 证据索引
A13: MY-SUN-006 | B13: 既审具名主合同原件 | C13: Cash Plus Assurance Master Policy | D13: CPA0613 | E13: 34 | F13: 已核存在 | G13: A：含附表性质未解依赖 | H13: 已审材料组成关系 | I13: 均未核定，不因关联而升级 | J13: REL-062dc678dba03d8de6c6；EV-3161e8a4d95fd95e / EV-301f3823904fefeb / EV-787f09b2a1442c84
A14: MY-SUN-006 | B14: 现存标准附件组 | C14: CPA002 / CPA003 / CPA004 / CPA005 | D14: CPA002 / CPA003 / CPA004 / CPA005 | E14: 未单独计页 | F14: 已核存在 | G14: A：公共通用组件 | H14: 已审材料组成关系 | I14: 均未核定，不因关联而升级 | J14: REL-b0cc250fab35ceeb1e6c；EV-083bf1d337cc4a02
A15: MY-SUN-006 | B15: 具日期批单 | C15: sanctions endorsement effective2025-07-01 | D15: 未核定 | E15: 未单独计页 | F15: 已核存在 | G15: A：公共通用组件 | H15: 已审材料组成关系 | I15: 均未核定，不因关联而升级 | J15: REL-b1a78f3e3b752da0cbbf；EV-e7c6abb191a1a3bb
A16: MY-SUN-006 | B16: 具日期批单 | C16: age/change endorsement effective2020-07-01 | D16: 未核定 | E16: 未单独计页 | F16: 已核存在 | G16: A：公共通用组件 | H16: 已审材料组成关系 | I16: 均未核定，不因关联而升级 | J16: REL-edd53d5729f6f7f26dfa；EV-ec1d9d1f0f1fc93f
A17: MY-SUN-006 | B17: 具日期批单 | C17: FSA/tax/FATCA/TPD endorsement effective2015-01-01 | D17: 未核定 | E17: 未单独计页 | F17: 已核存在 | G17: A：公共通用组件 | H17: 已审材料组成关系 | I17: 均未核定，不因关联而升级 | J17: REL-8c40f15b44882d0a0e1a；EV-b1bc5883efeb965b
A18: MY-SUN-006 | B18: 法律主体更名通知 | C18: company rename effective2013-08-19, not product issue date | D18: 未核定 | E18: 未单独计页 | F18: 已核存在 | G18: A：公共通用组件 | H18: 已审材料组成关系 | I18: 均未核定，不因关联而升级 | J18: REL-0b19319c6b3f88a39778；EV-bfdb8b5c992d641a
A19: MY-SUN-006 | B19: 引用主合同附表 | C19: CPA001 master policy schedule | D19: CPA001 | E19: 未单独计页 | F19: 现存文件未见 | G19: A或B性质未定 | H19: 引用依赖，现存文件未见 | I19: 均未核定，不因关联而升级 | J19: REL-3b2507cd33593eea3bf3；EV-292fb0a6b63da04c / EV-4bee4b82e3fa19aa
A20: MY-SUN-006 | B20: 个人化保单组件 | C20: Individual certificate, proposal/medical/questionnaire and claim evidence | D20: 未核定 | E20: 未单独计页 | F20: 现存文件未见 | G20: B：个人化组件 | H20: 引用依赖，现存文件未见 | I20: 均未核定，不因关联而升级 | J20: REL-65bb19fa89122e8b7b27；EV-4bee4b82e3fa19aa
A21: MY-SUN-008 | B21: 既审具名主合同原件 | C21: Credit Protector Plus Master Policy | D21: CPP0813 | E21: 74 | F21: 已核存在 | G21: A：含附表性质未解依赖 | H21: 已审材料组成关系 | I21: 均未核定，不因关联而升级 | J21: REL-af3c6215d0ef0f69c7f0；EV-eb2b7cc0f8721b53 / EV-7feb26864febce78 / EV-55199f85d862dd04
A22: MY-SUN-008 | B22: 现存标准附件组 | C22: CPP002 / CPP003 / CPP004 / CPP005 / CPP006 | D22: CPP002 / CPP003 / CPP004 / CPP005 / CPP006 | E22: 未单独计页 | F22: 已核存在 | G22: A：公共通用组件 | H22: 已审材料组成关系 | I22: 均未核定，不因关联而升级 | J22: REL-923befd036b19dff27a9；EV-ee3decb7459cc60c
A23: MY-SUN-008 | B23: 具日期批单 | C23: sanctions endorsement | D23: 未核定 | E23: 未单独计页 | F23: 已核存在 | G23: A：公共通用组件 | H23: 已审材料组成关系 | I23: 均未核定，不因关联而升级 | J23: REL-6803f4f8e929397e6717；EV-067af96a818febed
A24: MY-SUN-008 | B24: 具日期批单 | C24: outstanding balance definition for enrollment on/after date only | D24: 未核定 | E24: 未单独计页 | F24: 已核存在 | G24: A：公共通用组件 | H24: 已审材料组成关系 | I24: 均未核定，不因关联而升级 | J24: REL-48b1380065d1f0661ae2；EV-ebfb5411be14a664
A25: MY-SUN-008 | B25: 具日期批单 | C25: age/change-policy endorsement; CPA002 reference anomaly | D25: 未核定 | E25: 未单独计页 | F25: 已核存在 | G25: A：公共通用组件 | H25: 已审材料组成关系 | I25: 均未核定，不因关联而升级 | J25: REL-ba7b87191884bf185c25；EV-a023fdde12bd9e7c
A26: MY-SUN-008 | B26: 具日期批单 | C26: full CI definition/ADL amendment | D26: 未核定 | E26: 未单独计页 | F26: 已核存在 | G26: A：公共通用组件 | H26: 已审材料组成关系 | I26: 均未核定，不因关联而升级 | J26: REL-093f78df9490ef9bf56c；EV-a3c5c0247ebd709d
A27: MY-SUN-008 | B27: 引用主合同附表 | C27: CPP001 master policy schedule | D27: CPP001 | E27: 未单独计页 | F27: 现存文件未见 | G27: A或B性质未定 | H27: 引用依赖，现存文件未见 | I27: 均未核定，不因关联而升级 | J27: REL-d62f082e183c4a045f7b；EV-dc842963e9c1f1da / EV-0d302653e50ffcef
A28: MY-SUN-008 | B28: 个人化保单组件 | C28: Individual certificate, enrollment health declaration and monthly card balance | D28: 未核定 | E28: 未单独计页 | F28: 现存文件未见 | G28: B：个人化组件 | H28: 引用依赖，现存文件未见 | I28: 均未核定，不因关联而升级 | J28: REL-08b23e9fec6407cd7e62；EV-0d302653e50ffcef
A29: MY-SUN-002 | B29: 既审具名主合同原件 | C29: Biz Shield Master Policy | D29: BIZS0914 | E29: 37 | F29: 已核存在 | G29: A：含附表性质未解依赖 | H29: 已审材料组成关系 | I29: 均未核定，不因关联而升级 | J29: REL-eb59bef007448d34c388；EV-e15b3f2e47ec37f6 / EV-948acf722d1b438c / EV-8185a90f8a5a1a12
A30: MY-SUN-002 | B30: 现存标准附件组 | C30: BIZS002 / BIZS003 / BIZS004 / BIZS005 | D30: BIZS002 / BIZS003 / BIZS004 / BIZS005 | E30: 未单独计页 | F30: 已核存在 | G30: A：公共通用组件 | H30: 已审材料组成关系 | I30: 均未核定，不因关联而升级 | J30: REL-e525fe40d73544f76968；EV-2c3bd418edc3c1fc
A31: MY-SUN-002 | B31: 具日期批单 | C31: sanctions endorsement effective/signed date | D31: 未核定 | E31: 未单独计页 | F31: 已核存在 | G31: A：公共通用组件 | H31: 已审材料组成关系 | I31: 均未核定，不因关联而升级 | J31: REL-38f44370e7e77f0d1004；EV-643aaee3e7224952
A32: MY-SUN-002 | B32: 具日期批单 | C32: age/gender/change endorsement effective date | D32: 未核定 | E32: 未单独计页 | F32: 已核存在 | G32: A：公共通用组件 | H32: 已审材料组成关系 | I32: 均未核定，不因关联而升级 | J32: REL-785e710ab0bfec1b6fa6；EV-b4577ede7cfbd71f
A33: MY-SUN-002 | B33: 具日期批单 | C33: master/tax/FATCA endorsement effective date | D33: 未核定 | E33: 未单独计页 | F33: 已核存在 | G33: A：公共通用组件 | H33: 已审材料组成关系 | I33: 均未核定，不因关联而升级 | J33: REL-32f4129a07216e611b2c；EV-ad46ab99a89049fb
A34: MY-SUN-002 | B34: 引用主合同附表 | C34: BIZS001 master policy schedule | D34: BIZS001 | E34: 未单独计页 | F34: 现存文件未见 | G34: A或B性质未定 | H34: 引用依赖，现存文件未见 | I34: 均未核定，不因关联而升级 | J34: REL-61dab040f9ca22d326fa；EV-1797113ff8d7eca9 / EV-e52d23906f8ded25
A35: MY-SUN-002 | B35: 个人化保单组件 | C35: Individual certificate/proposal and individualized commencement/sum assured | D35: 未核定 | E35: 未单独计页 | F35: 现存文件未见 | G35: B：个人化组件 | H35: 引用依赖，现存文件未见 | I35: 均未核定，不因关联而升级 | J35: REL-22a0df349d0adf632bca；EV-d9476854b3dc9980
A36: MY-SUN-036 | B36: 既审具名主合同原件 | C36: Biz Shield-i Master Contract | D36: BSI0317 | E36: 49 | F36: 已核存在 | G36: A：含附表性质未解依赖 | H36: 已审材料组成关系 | I36: 均未核定，不因关联而升级 | J36: REL-f84187e17e8972f409ce；EV-ec167fb9414ad322 / EV-ca7935e1e8ed962d / EV-22c20fc68d3e14a8
A37: MY-SUN-036 | B37: 现存标准附件组 | C37: BSI001 / BSI003 / BSI004 / BSI005 / BSI006 / BSI007 / BSI008 / BSI009 | D37: BSI001 / BSI003 / BSI004 / BSI005 / BSI006 / BSI007 / BSI008 / BSI009 | E37: 未单独计页 | F37: 已核存在 | G37: A：公共通用组件 | H37: 已审材料组成关系 | I37: 均未核定，不因关联而升级 | J37: REL-e50bc28f5f3ec535a283；EV-530b93d402883e77
A38: MY-SUN-036 | B38: 具日期批单 | C38: sanctions endorsement | D38: 未核定 | E38: 未单独计页 | F38: 已核存在 | G38: A：公共通用组件 | H38: 已审材料组成关系 | I38: 均未核定，不因关联而升级 | J38: REL-c6c38205621ae06c6a7b；EV-ba8940e5cad871e1
A39: MY-SUN-036 | B39: 具日期批单 | C39: age/legalproceeding deletion/cash/fund/Wakalah amendment | D39: 未核定 | E39: 未单独计页 | F39: 已核存在 | G39: A：公共通用组件 | H39: 已审材料组成关系 | I39: 均未核定，不因关联而升级 | J39: REL-a036e5aecb0909b1d4db；EV-e3384ad8c35502e2
A40: MY-SUN-036 | B40: 具日期批单 | C40: legal amendment;smallamount/surrender/cash/TPD/surplus changes | D40: 未核定 | E40: 未单独计页 | F40: 已核存在 | G40: A：公共通用组件 | H40: 已审材料组成关系 | I40: 均未核定，不因关联而升级 | J40: REL-eefb8f46a18386419c9d；EV-bf9f539f72f8dc9d
A41: MY-SUN-036 | B41: 引用主合同附表 | C41: Referenced master contract schedule; code-title association unverified | D41: 未核定 | E41: 未单独计页 | F41: 现存文件未见 | G41: A或B性质未定 | H41: 引用依赖，现存文件未见 | I41: 均未核定，不因关联而升级 | J41: REL-3a796f73a3262a78c25c；EV-393388ce11f5b302 / EV-7e9235d2e0627a2d
A42: MY-SUN-036 | B42: 个人化保单组件 | C42: Issued certificate sum, term, fee percentage, person and financing details | D42: 未核定 | E42: 未单独计页 | F42: 现存文件未见 | G42: B：个人化组件 | H42: 引用依赖，现存文件未见 | I42: 均未核定，不因关联而升级 | J42: REL-c3fff42a46b160fae3a1；EV-7e9235d2e0627a2d
A43: MY-SUN-036 | B43: 未见附件代码且标题映射未定 | C43: BSI002 code absent; title not established | D43: BSI002 | E43: 未单独计页 | F43: 现存文件未见 | G43: 依赖性质未定 | H43: 引用依赖，现存文件未见 | I43: 均未核定，不因关联而升级 | J43: REL-49d8a1c48e662aa50af1；EV-0e7ed973c09570c5 / EV-3d04b4be796753e5
A46: B11解释支持关系：1项历史同编号／同持有人关系，3项未定候选。均不证明合同采用。
A48: 关系ID | B48: 支持件ID | C48: 对应主文ID | D48: 关系分类 | E48: 支持件页码 | F48: 历史关系已核 | G48: 准确版次／合同并入 | H48: 当前采用 | I48: 附表／个体齐套 | J48: 证据索引
A49: B11-MY-001-R1 | B49: MY-SUP-006 | C49: MY-SUN-024 | D49: 同编号／同持有人历史解释支持 | E49: 2、3、17 | F49: 限定历史关系已核 | G49: 均未证实 | H49: 均未核定 | I49: 不补齐、不关闭 | J49: B11-MY-001-R1；源/对应SHA分别保留
A50: B11-MY-002-R1 | B50: MY-SUP-008 | C50: MY-SUN-025 | D50: 仅GTT CI家族候选 | E50: 1、2、17 | F50: 精确关系未定 | G50: 均未证实 | H50: 均未核定 | I50: 不补齐、不关闭 | J50: B11-MY-002-R1；源/对应SHA分别保留
A51: B11-MY-003-R1 | B51: MY-SUP-007 | C51: MY-SUN-032 | D51: GTT CW家族候选，主附表未定 | E51: 1、2、3、19 | F51: 精确关系未定 | G51: 均未证实 | H51: 均未核定 | I51: 不补齐、不关闭 | J51: B11-MY-003-R1；源/对应SHA分别保留
A52: B11-MY-004-R1 | B52: MY-SUP-017 | C52: MY-SUN-033 | D52: 家族候选，编号顺序不符 | E52: 2、3、12 | F52: 精确关系未定 | G52: 均未证实 | H52: 均未核定 | I52: 不补齐、不关闭 | J52: B11-MY-004-R1；源/对应SHA分别保留

Sheet B15–B18角色验收
A1: 任务ID | B1: 批次 | C1: 地区 | D1: 冻结来源保司 | E1: 冻结来源产品标签 | F1: 角色层决定 | G1: 锚点观察的文件角色 | H1: 库存页数（非审读） | I1: 实际文件总页数 | J1: 执行锚点物理页 | K1: 执行锚点页数 | L1: 独立QA锚点物理页 | M1: 独立QA锚点页数 | N1: 全文状态 | O1: 全文增量 | P1: 严格增量 | Q1: 主角色提议数 | R1: 非合同CIS数 | S1: 保留映射数 | T1: 本轮已发布主角色增量 | U1: 原件ID | V1: 原件SHA-256 | W1: 正文身份观察（不改来源） | X1: 身份／版次／附表限制 | Y1: 独立QA纠正与补充 | Z1: 映射保留原因 | AA1: 私有元数据包下载 | AB1: 原始来源入口 | AC1: 原始文档来源 | AD1: 冻结时间UTC | AE1: 执行完成UTC | AF1: 独立QA时间UTC | AG1: 角色检查点ID | AH1: 角色证据验收 | AI1: 唯一任务检查
A2: B15-MY-001 | B2: B15 | C2: MY | D2: Sun Life Malaysia Takaful Berhad | E2: Group Term Takaful (GTTCP0425) - Legacy and Protection Campaign | F2: 非合同CIS | G2: noncontract_certificate_information_summary | H2: 35 | I2: 35 | J2: 1, 2, 3, 35 | K2: 4 | L2: 1, 2, 3, 35 | M2: 4 | N2: 待全文 | O2: 0 | P2: 0 | Q2: =IF(F2="主角色提议",1,0) -> 0 | R2: =IF(F2="非合同CIS",1,0) -> 1 | S2: =IF(F2="映射保留",1,0) -> 0 | T2: 0 | U2: regional-20261025-07c5c6d5fb1fec25 | V2: 07c5c6d5fb1fec2500240c2ff34f4ed386f7c89c7543940bd9c190f1fd43cb80 | W2: issuer_in_cover_and_cis_opening: Sun Life Malaysia Takaful Berhad product_name: Group Term Takaful (GTT CP) master_reference_code: GTTCP0425 master_holder: CIMB Bank Berhad version_boundary_note: Code is a master reference observed in the file, not an inferred issuance date or current-version assertion. | X2: Legacy and Protection Campaign is a frozen/source label, not an independently verified body title in these anchors. | Y2: Physical p3 is explicitly an information-only noncontract CIS and points to a separate master contract/policy. This does not establish the missing master wording. No assertion that every uninspected page has been classified or read. | AA2: =HYPERLINK("https://chatgpt.com/api/library/files/libfile_b303d0e820e08191b7ca12b5c5e78338/download","B15私有元数据包") -> B15私有元数据包 | AB2: https://www.sunlifemalaysia.com/client-care/downloads/ | AC2: https://www.sunlifemalaysia.com/getContentAsset/18d526dd-4d62-43f4-8d94-e0aa346330dc/826411a5-9a44-43a6-8410-a7ad95da6d70/GTT-Certificate-of-Takaful_EngBM-for-client-_GTT-CP_040425_CIMB-Bank-Clean.pdf | AD2: 46321.297 | AE2: 46321.304 | AF2: 46321.319 | AG2: B15-MY-001:accepted-role-only:20261026 | AH2: =IF(AND(AI2="匹配",LEN(V2)=64,J2<>"",L2<>"",K2>0,M2>0,AD2>0,AE2>0,AF2>0,AG2<>"",N2="待全文",O2=0,P2=0,Q2+R2+S2=1),"角色已验收","需检查证据") -> 角色已验收 | AI2: =IF(COUNTIF($A$2:$A$91,A2)=1,"匹配","缺范围或重复") -> 匹配
A3: B15-MY-002 | B3: B15 | C3: MY | D3: Sun Life Malaysia Takaful Berhad | E3: Group Term Life - MRTT Complimentary GTT Campaign - Plan A (CIMB Bank Berhad) | F3: 非合同CIS | G3: noncontract_certificate_information_summary | H3: 21 | I3: 21 | J3: 1, 2, 3, 21 | K3: 4 | L3: 1, 2, 3, 21 | M3: 4 | N3: 待全文 | O3: 0 | P3: 0 | Q3: =IF(F3="主角色提议",1,0) -> 0 | R3: =IF(F3="非合同CIS",1,0) -> 1 | S3: =IF(F3="映射保留",1,0) -> 0 | T3: 0 | U3: regional-20261025-1db8d63aa433ea6d | V3: 1db8d63aa433ea6d59dbc350f44c704456313df333db2358f26cf278df16b137 | W3: issuer_in_cover_and_cis_opening: Sun Life Malaysia Takaful Berhad product_name: Group Term Takaful - Plan A master_reference_code: GTTCIMB0623 master_holder: CIMB Islamic Bank / CIMB Islamic Bank Berhad (address field) version_boundary_note: Code is a master reference observed in the file, not an inferred issuance date or current-version assertion. | X3: Frozen target incorrectly says Group Term Life and CIMB Bank Berhad; observed body identifies Group Term Takaful and CIMB Islamic Bank. No replacement master contract has been established. | Y3: Physical p3 is explicitly an information-only noncontract CIS and points to a separate master contract/policy. This does not establish the missing master wording. No assertion that every uninspected page has been classified or read. Frozen source label says Group Term Life and CIMB Bank Berhad. Actual p1/p3 say Group Term Takaful and Sun Life Malaysia Takaful Berhad; p2 says CIMB Islamic Bank (CIMB Islamic Bank Berhad in address), GTTCIMB0623. Plan A/B is a benefit-table heading at p2, not a separately proved product or master-version identity. Frozen target/source ownership retained, not silently overwritten. | AA3: =HYPERLINK("https://chatgpt.com/api/library/files/libfile_b303d0e820e08191b7ca12b5c5e78338/download","B15私有元数据包") -> B15私有元数据包 | AB3: https://www.sunlifemalaysia.com/client-care/downloads/ | AC3: https://www.sunlifemalaysia.com/getContentAsset/9009cf63-c443-4c1d-8c62-4013b194da66/826411a5-9a44-43a6-8410-a7ad95da6d70/GTT-Certificate-of-takaful-for-Client_GTTCIMB0623-_Repriced-MRTT_PlanA-Wevbsite_5.pdf | AD3: 46321.297 | AE3: 46321.304 | AF3: 46321.319 | AG3: B15-MY-002:accepted-role-only:20261026 | AH3: =IF(AND(AI3="匹配",LEN(V3)=64,J3<>"",L3<>"",K3>0,M3>0,AD3>0,AE3>0,AF3>0,AG3<>"",N3="待全文",O3=0,P3=0,Q3+R3+S3=1),"角色已验收","需检查证据") -> 角色已验收 | AI3: =IF(COUNTIF($A$2:$A$91,A3)=1,"匹配","缺范围或重复") -> 匹配
A4: B15-MY-003 | B4: B15 | C4: MY | D4: Sun Life Malaysia Takaful Berhad | E4: Takaful PA SmartPro Contract (Financial Institution) | F4: 主角色提议 | G4: historical_main_contract_with_endorsements | H4: 50 | I4: 50 | J4: 1, 2, 3, 4, 5, 9, 13, 14, 15, 16, 17, 20, 26, 50 | K4: 14 | L4: 1, 2, 3, 4, 5, 9, 13, 14, 15, 16, 17, 20, 26, 50 | M4: 14 | N4: 待全文 | O4: 0 | P4: 0 | Q4: =IF(F4="主角色提议",1,0) -> 1 | R4: =IF(F4="非合同CIS",1,0) -> 0 | S4: =IF(F4="映射保留",1,0) -> 0 | T4: 1 | U4: regional-20261025-2514a7e8222f38f0 | V4: 2514a7e8222f38f0799ca9327d3141058e226aa165c1dcdc68f3f785712e9cf4 | W4: base_issuer_in_operative_body: CIMB Aviva Takaful Berhad endorsement_issuer: Sun Life Malaysia Takaful Berhad endorsement_issuer_registration: 689263-M documentary_name_change_bridge: In-file notice effective 19 August 2013; historical and renamed entities preserved separately in metadata, not independently checked against a registry. product_name: Takaful PA SmartPro observed_dated_endorsements: 02/2019 effective 1 July 2019; 01/2018 effective 1 July 2018 version_boundary_note: Historical base wording plus later attached amendments; endorsement date is not the base edition or evidence of current use. | X4: Financial Institution / Non-financial Institution distinction is a frozen/source label not established by the sampled body anchors. Keep the two SHA-distinct files separate; do not deduplicate or infer separate products. Base edition date/code and complete intervening endorsement/language boundaries remain unverified. | Y4: Main-containing role independently established from body p16/p17/p20/p26, without relying on FI/NFI filename labels. Separate SHA records retained. No deduplication, product split, family closure or group merge. Historical CIMB Aviva Takaful body, later Sun Life Malaysia Takaful endorsements, and in-file name-change notice remain separate time-scoped evidence. | AA4: =HYPERLINK("https://chatgpt.com/api/library/files/libfile_b303d0e820e08191b7ca12b5c5e78338/download","B15私有元数据包") -> B15私有元数据包 | AB4: https://www.sunlifemalaysia.com/client-care/downloads/ | AC4: https://www.sunlifemalaysia.com/getContentAsset/a92d55a5-5d55-4167-828e-93256af6cae4/826411a5-9a44-43a6-8410-a7ad95da6d70/46.pdf | AD4: 46321.297 | AE4: 46321.304 | AF4: 46321.319 | AG4: B15-MY-003:accepted-role-only:20261026 | AH4: =IF(AND(AI4="匹配",LEN(V4)=64,J4<>"",L4<>"",K4>0,M4>0,AD4>0,AE4>0,AF4>0,AG4<>"",N4="待全文",O4=0,P4=0,Q4+R4+S4=1),"角色已验收","需检查证据") -> 角色已验收 | AI4: =IF(COUNTIF($A$2:$A$91,A4)=1,"匹配","缺范围或重复") -> 匹配
A5: B15-MY-004 | B5: B15 | C5: MY | D5: Sun Life Malaysia Assurance Berhad | E5: Group Term Life - MRTA/MLTA Complimentary GTL Campaign - Plan B (CIMB Bank) | F5: 非合同CIS | G5: noncontract_certificate_information_summary | H5: 21 | I5: 21 | J5: 1, 2, 3, 21 | K5: 4 | L5: 1, 2, 3, 21 | M5: 4 | N5: 待全文 | O5: 0 | P5: 0 | Q5: =IF(F5="主角色提议",1,0) -> 0 | R5: =IF(F5="非合同CIS",1,0) -> 1 | S5: =IF(F5="映射保留",1,0) -> 0 | T5: 0 | U5: regional-20261025-2c0bd51ab5ff5b16 | V5: 2c0bd51ab5ff5b161fa434fad7ef5b03b02b218c46d383417dab38e637bc088c | W5: issuer_in_cover_and_cis_opening: Sun Life Malaysia Assurance Berhad product_name: Group Term Life - Plan B master_reference_code: GTLCIMB1124 master_holder: CIMB Bank / CIMB Bank Berhad (address field) version_boundary_note: Code is a master reference observed in the file, not an inferred issuance date or current-version assertion. | X5: Plan/campaign labels do not make this the master policy; the master policy is referred to but not verified by this file checkpoint. | Y5: Physical p3 is explicitly an information-only noncontract CIS and points to a separate master contract/policy. This does not establish the missing master wording. No assertion that every uninspected page has been classified or read. | AA5: =HYPERLINK("https://chatgpt.com/api/library/files/libfile_b303d0e820e08191b7ca12b5c5e78338/download","B15私有元数据包") -> B15私有元数据包 | AB5: https://www.sunlifemalaysia.com/client-care/downloads/ | AC5: https://www.sunlifemalaysia.com/getContentAsset/3eddf7ec-f5ca-4417-a67f-74a07c68298c/826411a5-9a44-43a6-8410-a7ad95da6d70/GTL-Certificate-of-insurance-for-CIMB-Client-_Eng-BM_Repriced-MRTA-MLTA_PlanB_-Website_6.pdf | AD5: 46321.297 | AE5: 46321.304 | AF5: 46321.319 | AG5: B15-MY-004:accepted-role-only:20261026 | AH5: =IF(AND(AI5="匹配",LEN(V5)=64,J5<>"",L5<>"",K5>0,M5>0,AD5>0,AE5>0,AF5>0,AG5<>"",N5="待全文",O5=0,P5=0,Q5+R5+S5=1),"角色已验收","需检查证据") -> 角色已验收 | AI5: =IF(COUNTIF($A$2:$A$91,A5)=1,"匹配","缺范围或重复") -> 匹配
A6: B15-MY-005 | B6: B15 | C6: MY | D6: Sun Life Malaysia Takaful Berhad | E6: Takaful PA SmartPro Contract (Non-financial Institution) | F6: 主角色提议 | G6: historical_main_contract_with_endorsements | H6: 50 | I6: 50 | J6: 1, 2, 3, 4, 5, 9, 13, 14, 15, 16, 17, 20, 26, 50 | K6: 14 | L6: 1, 2, 3, 4, 5, 9, 13, 14, 15, 16, 17, 20, 26, 50 | M6: 14 | N6: 待全文 | O6: 0 | P6: 0 | Q6: =IF(F6="主角色提议",1,0) -> 1 | R6: =IF(F6="非合同CIS",1,0) -> 0 | S6: =IF(F6="映射保留",1,0) -> 0 | T6: 1 | U6: regional-20261025-4f3084f52e0020fb | V6: 4f3084f52e0020fbb040dfcae80cfe1c8d41fe975d88a2cc94a6309e2bd32f0e | W6: base_issuer_in_operative_body: CIMB Aviva Takaful Berhad endorsement_issuer: Sun Life Malaysia Takaful Berhad endorsement_issuer_registration: 689263-M documentary_name_change_bridge: In-file notice effective 19 August 2013; historical and renamed entities preserved separately in metadata, not independently checked against a registry. product_name: Takaful PA SmartPro observed_dated_endorsements: 02/2019 effective 1 July 2019; 01/2018 effective 1 July 2018 version_boundary_note: Historical base wording plus later attached amendments; endorsement date is not the base edition or evidence of current use. | X6: Financial Institution / Non-financial Institution distinction is a frozen/source label not established by the sampled body anchors. Keep the two SHA-distinct files separate; do not deduplicate or infer separate products. Base edition date/code and complete intervening endorsement/language boundaries remain unverified. | Y6: Main-containing role independently established from body p16/p17/p20/p26, without relying on FI/NFI filename labels. Separate SHA records retained. No deduplication, product split, family closure or group merge. Historical CIMB Aviva Takaful body, later Sun Life Malaysia Takaful endorsements, and in-file name-change notice remain separate time-scoped evidence. | AA6: =HYPERLINK("https://chatgpt.com/api/library/files/libfile_b303d0e820e08191b7ca12b5c5e78338/download","B15私有元数据包") -> B15私有元数据包 | AB6: https://www.sunlifemalaysia.com/client-care/downloads/ | AC6: https://www.sunlifemalaysia.com/getContentAsset/2d1453a4-4fe4-49df-bc08-2996ff52e9c4/826411a5-9a44-43a6-8410-a7ad95da6d70/44.pdf | AD6: 46321.297 | AE6: 46321.304 | AF6: 46321.319 | AG6: B15-MY-005:accepted-role-only:20261026 | AH6: =IF(AND(AI6="匹配",LEN(V6)=64,J6<>"",L6<>"",K6>0,M6>0,AD6>0,AE6>0,AF6>0,AG6<>"",N6="待全文",O6=0,P6=0,Q6+R6+S6=1),"角色已验收","需检查证据") -> 角色已验收 | AI6: =IF(COUNTIF($A$2:$A$91,A6)=1,"匹配","缺范围或重复") -> 匹配
A7: B15-MY-006 | B7: B15 | C7: MY | D7: Sun Life Malaysia Takaful Berhad | E7: Group Term Takaful (GTTSA0425) - Legacy and Protection Campaign | F7: 非合同CIS | G7: noncontract_certificate_information_summary | H7: 35 | I7: 35 | J7: 1, 2, 3, 35 | K7: 4 | L7: 1, 2, 3, 35 | M7: 4 | N7: 待全文 | O7: 0 | P7: 0 | Q7: =IF(F7="主角色提议",1,0) -> 0 | R7: =IF(F7="非合同CIS",1,0) -> 1 | S7: =IF(F7="映射保留",1,0) -> 0 | T7: 0 | U7: regional-20261025-7c9c448f8d174410 | V7: 7c9c448f8d1744108ca1953aab9a33f3a8d8ccc51b837eb3018365d79fc669f3 | W7: issuer_in_cover_and_cis_opening: Sun Life Malaysia Takaful Berhad product_name: Group Term Takaful (GTT SA) master_reference_code: GTTSA0425 master_holder: CIMB Islamic Bank Berhad version_boundary_note: Code is a master reference observed in the file, not an inferred issuance date or current-version assertion. | X7: Legacy and Protection Campaign is a frozen/source label, not an independently verified body title in these anchors. | Y7: Physical p3 is explicitly an information-only noncontract CIS and points to a separate master contract/policy. This does not establish the missing master wording. No assertion that every uninspected page has been classified or read. | AA7: =HYPERLINK("https://chatgpt.com/api/library/files/libfile_b303d0e820e08191b7ca12b5c5e78338/download","B15私有元数据包") -> B15私有元数据包 | AB7: https://www.sunlifemalaysia.com/client-care/downloads/ | AC7: https://www.sunlifemalaysia.com/getContentAsset/f6c43dbe-a174-43f9-b005-9c3902e5c9fa/826411a5-9a44-43a6-8410-a7ad95da6d70/GTT-Certificate-of-Takaful_EngBM-for-client-_GTT-SA_040425_CIMB-Islamic-Bank-Clean.pdf | AD7: 46321.297 | AE7: 46321.304 | AF7: 46321.319 | AG7: B15-MY-006:accepted-role-only:20261026 | AH7: =IF(AND(AI7="匹配",LEN(V7)=64,J7<>"",L7<>"",K7>0,M7>0,AD7>0,AE7>0,AF7>0,AG7<>"",N7="待全文",O7=0,P7=0,Q7+R7+S7=1),"角色已验收","需检查证据") -> 角色已验收 | AI7: =IF(COUNTIF($A$2:$A$91,A7)=1,"匹配","缺范围或重复") -> 匹配
A8: B15-MY-007 | B8: B15 | C8: MY | D8: Sun Life Malaysia Takaful Berhad | E8: Takaful Child Protector Contract | F8: 主角色提议 | G8: historical_main_contract_with_compulsory_rider_and_endorsements | H8: 55 | I8: 55 | J8: 1, 2, 3, 4, 7, 11, 12, 13, 14, 15, 31, 32, 55 | K8: 13 | L8: 1, 2, 3, 4, 7, 11, 12, 13, 14, 15, 31, 32, 55 | M8: 13 | N8: 待全文 | O8: 0 | P8: 0 | Q8: =IF(F8="主角色提议",1,0) -> 1 | R8: =IF(F8="非合同CIS",1,0) -> 0 | S8: =IF(F8="映射保留",1,0) -> 0 | T8: 1 | U8: regional-20261025-a426d72a21ab5416 | V8: a426d72a21ab5416aa0ac713c6469a057f2d9d1ffbd9a6b701f9886d69b93537 | W8: base_issuer_in_operative_body: CIMB Aviva Takaful Berhad endorsement_issuer: Sun Life Malaysia Takaful Berhad endorsement_issuer_registration: 689263-M documentary_name_change_bridge: In-file notice effective 19 August 2013; historical and renamed entities preserved separately in metadata, not independently checked against a registry. product_name: Takaful Child Protector observed_dated_endorsements: 02/2019 effective 1 July 2019; endorsement effective 1 April 2016; endorsement effective 1 January 2015 version_boundary_note: Historical base wording plus later attached amendments; endorsement date is not the base edition or evidence of current use. | X8: Base edition date/code and complete intervening endorsement/language boundaries remain unverified; compulsory rider presence does not establish package completeness. | Y8: Main-containing role independently established from body p14/p15; p31/p32 expressly identify a dependent compulsory supplementary rider. p7 endorsement replaces base constitution clauses; it must be reconciled with p15 before substantive adoption. p1/p3 endorsements use master policy language and p1 also uses master contract language; do not infer group ownership or merge from this nomenclature. | AA8: =HYPERLINK("https://chatgpt.com/api/library/files/libfile_b303d0e820e08191b7ca12b5c5e78338/download","B15私有元数据包") -> B15私有元数据包 | AB8: https://www.sunlifemalaysia.com/client-care/downloads/ | AC8: https://www.sunlifemalaysia.com/getContentAsset/b6c5f427-e104-4142-a889-0102067a2492/826411a5-9a44-43a6-8410-a7ad95da6d70/42.pdf | AD8: 46321.297 | AE8: 46321.304 | AF8: 46321.319 | AG8: B15-MY-007:accepted-role-only:20261026 | AH8: =IF(AND(AI8="匹配",LEN(V8)=64,J8<>"",L8<>"",K8>0,M8>0,AD8>0,AE8>0,AF8>0,AG8<>"",N8="待全文",O8=0,P8=0,Q8+R8+S8=1),"角色已验收","需检查证据") -> 角色已验收 | AI8: =IF(COUNTIF($A$2:$A$91,A8)=1,"匹配","缺范围或重复") -> 匹配
A9: B15-MY-008 | B9: B15 | C9: MY | D9: Sun Life Malaysia Takaful Berhad | E9: Group Term Life - MRTT Complimentary GTT Campaign - Plan B (CIMB Bank Berhad) | F9: 非合同CIS | G9: noncontract_certificate_information_summary | H9: 21 | I9: 21 | J9: 1, 2, 3, 21 | K9: 4 | L9: 1, 2, 3, 21 | M9: 4 | N9: 待全文 | O9: 0 | P9: 0 | Q9: =IF(F9="主角色提议",1,0) -> 0 | R9: =IF(F9="非合同CIS",1,0) -> 1 | S9: =IF(F9="映射保留",1,0) -> 0 | T9: 0 | U9: regional-20261025-c33bc4acb793b240 | V9: c33bc4acb793b240b66006cb6e16e52fdb3bd596261a9a1f30b25671dcc63014 | W9: issuer_in_cover_and_cis_opening: Sun Life Malaysia Takaful Berhad product_name: Group Term Takaful - Plan B master_reference_code: GTTCIMB0623 master_holder: CIMB Islamic Bank / CIMB Islamic Bank Berhad (address field) version_boundary_note: Code is a master reference observed in the file, not an inferred issuance date or current-version assertion. | X9: Frozen target incorrectly says Group Term Life and CIMB Bank Berhad; observed body identifies Group Term Takaful and CIMB Islamic Bank. No replacement master contract has been established. | Y9: Physical p3 is explicitly an information-only noncontract CIS and points to a separate master contract/policy. This does not establish the missing master wording. No assertion that every uninspected page has been classified or read. Frozen source label says Group Term Life and CIMB Bank Berhad. Actual p1/p3 say Group Term Takaful and Sun Life Malaysia Takaful Berhad; p2 says CIMB Islamic Bank (CIMB Islamic Bank Berhad in address), GTTCIMB0623. Plan A/B is a benefit-table heading at p2, not a separately proved product or master-version identity. Frozen target/source ownership retained, not silently overwritten. | AA9: =HYPERLINK("https://chatgpt.com/api/library/files/libfile_b303d0e820e08191b7ca12b5c5e78338/download","B15私有元数据包") -> B15私有元数据包 | AB9: https://www.sunlifemalaysia.com/client-care/downloads/ | AC9: https://www.sunlifemalaysia.com/getContentAsset/025fe2db-a9f7-48d8-94e8-1db37d7d6e52/826411a5-9a44-43a6-8410-a7ad95da6d70/GTT-Certificate-of-takaful-for-Client_GTTCIMB0623-_Repriced-MRTT_PlanB-Webiste_3.pdf | AD9: 46321.297 | AE9: 46321.304 | AF9: 46321.319 | AG9: B15-MY-008:accepted-role-only:20261026 | AH9: =IF(AND(AI9="匹配",LEN(V9)=64,J9<>"",L9<>"",K9>0,M9>0,AD9>0,AE9>0,AF9>0,AG9<>"",N9="待全文",O9=0,P9=0,Q9+R9+S9=1),"角色已验收","需检查证据") -> 角色已验收 | AI9: =IF(COUNTIF($A$2:$A$91,A9)=1,"匹配","缺范围或重复") -> 匹配
A10: B15-MY-009 | B10: B15 | C10: MY | D10: Sun Life Malaysia Takaful Berhad | E10: Group Term Takaful - Green Home Campaign (CIMB Islamic Bank) | F10: 非合同CIS | G10: noncontract_certificate_information_summary | H10: 21 | I10: 21 | J10: 1, 2, 3, 21 | K10: 4 | L10: 1, 2, 3, 21 | M10: 4 | N10: 待全文 | O10: 0 | P10: 0 | Q10: =IF(F10="主角色提议",1,0) -> 0 | R10: =IF(F10="非合同CIS",1,0) -> 1 | S10: =IF(F10="映射保留",1,0) -> 0 | T10: 0 | U10: regional-20261025-db5c2580a3c7e7bc | V10: db5c2580a3c7e7bc1ae64c2f4d8f9884bbaaffe0f8101054e28b6d82592c8447 | W10: issuer_in_cover_and_cis_opening: Sun Life Malaysia Takaful Berhad product_name: Group Term Takaful master_reference_code: GTTCIMB0623 master_holder: CIMB Islamic Bank / CIMB Islamic Bank Berhad (address field) version_boundary_note: Code is a master reference observed in the file, not an inferred issuance date or current-version assertion. | X10: Green Home Campaign is the frozen/source label; it is not a body title established by the inspected cover, details page, CIS opening and final anchor. Shared master code with Plan A/B is not file equivalence. | Y10: Physical p3 is explicitly an information-only noncontract CIS and points to a separate master contract/policy. This does not establish the missing master wording. No assertion that every uninspected page has been classified or read. | AA10: =HYPERLINK("https://chatgpt.com/api/library/files/libfile_b303d0e820e08191b7ca12b5c5e78338/download","B15私有元数据包") -> B15私有元数据包 | AB10: https://www.sunlifemalaysia.com/client-care/downloads/ | AC10: https://www.sunlifemalaysia.com/getContentAsset/4c7f5651-1d54-4b4e-9e8a-fbfb0f6c1ca7/826411a5-9a44-43a6-8410-a7ad95da6d70/GTT-Certificate-of-takaful-for-Client_GTTCIMB0623-_Green-Building_18032024-Final.pdf | AD10: 46321.297 | AE10: 46321.304 | AF10: 46321.319 | AG10: B15-MY-009:accepted-role-only:20261026 | AH10: =IF(AND(AI10="匹配",LEN(V10)=64,J10<>"",L10<>"",K10>0,M10>0,AD10>0,AE10>0,AF10>0,AG10<>"",N10="待全文",O10=0,P10=0,Q10+R10+S10=1),"角色已验收","需检查证据") -> 角色已验收 | AI10: =IF(COUNTIF($A$2:$A$91,A10)=1,"匹配","缺范围或重复") -> 匹配
A11: B15-MY-010 | B11: B15 | C11: MY | D11: Sun Life Malaysia Takaful Berhad | E11: Group Term Takaful - Green Home Campaign (CIMB Bank Berhad) | F11: 非合同CIS | G11: noncontract_certificate_information_summary | H11: 21 | I11: 21 | J11: 1, 2, 3, 21 | K11: 4 | L11: 1, 2, 3, 21 | M11: 4 | N11: 待全文 | O11: 0 | P11: 0 | Q11: =IF(F11="主角色提议",1,0) -> 0 | R11: =IF(F11="非合同CIS",1,0) -> 1 | S11: =IF(F11="映射保留",1,0) -> 0 | T11: 0 | U11: regional-20261025-ef41d5b18cc52660 | V11: ef41d5b18cc52660c449a261037c527339137614e285740c4734494e5eb473d1 | W11: issuer_in_cover_and_cis_opening: Sun Life Malaysia Takaful Berhad product_name: Group Term Takaful master_reference_code: GTTCIMB1024 master_holder: CIMB Bank Berhad version_boundary_note: Code is a master reference observed in the file, not an inferred issuance date or current-version assertion. | X11: Green Home Campaign is the frozen/source label; it is not a body title established by the inspected cover, details page, CIS opening and final anchor. | Y11: Physical p3 is explicitly an information-only noncontract CIS and points to a separate master contract/policy. This does not establish the missing master wording. No assertion that every uninspected page has been classified or read. | AA11: =HYPERLINK("https://chatgpt.com/api/library/files/libfile_b303d0e820e08191b7ca12b5c5e78338/download","B15私有元数据包") -> B15私有元数据包 | AB11: https://www.sunlifemalaysia.com/client-care/downloads/ | AC11: https://www.sunlifemalaysia.com/getContentAsset/82e1441f-e30f-4b77-8554-d93d04c95d8d/826411a5-9a44-43a6-8410-a7ad95da6d70/GTT-Certificate-of-takaful-for-Client_GTTCIMB1024-_Green-Building_18032024-Final.pdf | AD11: 46321.297 | AE11: 46321.304 | AF11: 46321.319 | AG11: B15-MY-010:accepted-role-only:20261026 | AH11: =IF(AND(AI11="匹配",LEN(V11)=64,J11<>"",L11<>"",K11>0,M11>0,AD11>0,AE11>0,AF11>0,AG11<>"",N11="待全文",O11=0,P11=0,Q11+R11+S11=1),"角色已验收","需检查证据") -> 角色已验收 | AI11: =IF(COUNTIF($A$2:$A$91,A11)=1,"匹配","缺范围或重复") -> 匹配
A12: B16-MY-001 | B12: B16 | C12: MY | D12: Sun Life Malaysia Assurance Berhad | E12: Biz Shield Plus (Level) Master Policy | F12: 主角色提议 | G12: main_policy_with_endorsements_and_conditional_rider | H12: 40 | I12: 40 | J12: 1, 2, 3, 10, 11, 12, 13, 14, 21, 40 | K12: 10 | L12: 1, 10, 13, 14, 21, 40 | M12: 6 | N12: 待全文 | O12: 0 | P12: 0 | Q12: =IF(F12="主角色提议",1,0) -> 1 | R12: =IF(F12="非合同CIS",1,0) -> 0 | S12: =IF(F12="映射保留",1,0) -> 0 | T12: 1 | U12: regional-20261025-d72c61d2ba3780ce | V12: d72c61d2ba3780ce2cc86e28224cf7686cbf4895fabbf3e566e004a6d6c93e33 | W12: base_issuer_in_operative_body: Sun Life Malaysia Assurance Berhad product_name: Biz Shield Plus (Level) master_reference_code: BSPL0625 master_holder: CIMB Bank Berhad (endorsement) observed_dated_endorsements: 27 February 2026; 09 December 2025 version_boundary_note: Dated endorsements and reference code do not establish base edition or current adoption. | X12: No complete schedule, language boundary or intervening endorsement reconciliation was performed. Conditional rider presence does not establish that it applies to any individual certificate. | Y12: p1 identifies Level, BSPL0625, CIMB Bank Berhad and conditional BSPL005 rider effective 27 February 2026; p10 identifies 9 December 2025 amendment. p13 explicitly defines issuer; p14 supplies operative premium/constitution clause; p21 supplies base death-payment clause. p40 is terminal Malay continuation, not proof of package completeness. | AA12: =HYPERLINK("https://chatgpt.com/api/library/files/libfile_f096861615788191b2089dd752505c74/download","B16私有元数据包") -> B16私有元数据包 | AB12: https://www.sunlifemalaysia.com/client-care/downloads/ | AC12: https://www.sunlifemalaysia.com/getContentAsset/37a754c0-2919-4f64-b3c8-105cc8e6d636/826411a5-9a44-43a6-8410-a7ad95da6d70/BSP-with-ROP-Level-_Master-Policy-Endt_Final-Website.pdf?language=en | AD12: 46321.333 | AE12: 46321.346 | AF12: 46321.367 | AG12: B16-MY-001:accepted-role-only:20261026 | AH12: =IF(AND(AI12="匹配",LEN(V12)=64,J12<>"",L12<>"",K12>0,M12>0,AD12>0,AE12>0,AF12>0,AG12<>"",N12="待全文",O12=0,P12=0,Q12+R12+S12=1),"角色已验收","需检查证据") -> 角色已验收 | AI12: =IF(COUNTIF($A$2:$A$91,A12)=1,"匹配","缺范围或重复") -> 匹配
A13: B16-MY-002 | B13: B16 | C13: MY | D13: Sun Life Malaysia Assurance Berhad | E13: Biz Shield Plus (Reducing) Master Policy | F13: 主角色提议 | G13: main_policy_with_endorsements_and_conditional_rider | H13: 42 | I13: 42 | J13: 1, 2, 3, 10, 11, 12, 13, 14, 21, 42 | K13: 10 | L13: 1, 10, 13, 14, 21, 42 | M13: 6 | N13: 待全文 | O13: 0 | P13: 0 | Q13: =IF(F13="主角色提议",1,0) -> 1 | R13: =IF(F13="非合同CIS",1,0) -> 0 | S13: =IF(F13="映射保留",1,0) -> 0 | T13: 1 | U13: regional-20261025-5f8f4352a6b56721 | V13: 5f8f4352a6b567216d01e3f6f9a88b276bf2b1cc9e28c02378aa338ae2a43a1c | W13: base_issuer_in_operative_body: Sun Life Malaysia Assurance Berhad product_name: Biz Shield Plus (Reducing) master_reference_code: BSPR0625 master_holder: CIMB Bank Berhad (endorsement) observed_dated_endorsements: 27 February 2026; 09 December 2025 version_boundary_note: Dated endorsements and reference code do not establish base edition or current adoption. | X13: No complete schedule, language boundary or intervening endorsement reconciliation was performed. Conditional rider presence does not establish that it applies to any individual certificate. | Y13: p1 identifies Reducing, BSPR0625, CIMB Bank Berhad and conditional BSPR006 rider effective 27 February 2026; p10 identifies 9 December 2025 amendment. p13 explicitly defines issuer; p14 supplies operative premium/constitution clause; p21 supplies base reducing-sum death-payment clause. p42 is terminal Malay formula, not proof of completeness. | AA13: =HYPERLINK("https://chatgpt.com/api/library/files/libfile_f096861615788191b2089dd752505c74/download","B16私有元数据包") -> B16私有元数据包 | AB13: https://www.sunlifemalaysia.com/client-care/downloads/ | AC13: https://www.sunlifemalaysia.com/getContentAsset/9397cb92-5fb6-4ea0-b936-61a0d90adfa0/826411a5-9a44-43a6-8410-a7ad95da6d70/BSP-with-ROP-Reducing-_Master-Policy-Endt_Final-Website.pdf?language=en | AD13: 46321.333 | AE13: 46321.346 | AF13: 46321.367 | AG13: B16-MY-002:accepted-role-only:20261026 | AH13: =IF(AND(AI13="匹配",LEN(V13)=64,J13<>"",L13<>"",K13>0,M13>0,AD13>0,AE13>0,AF13>0,AG13<>"",N13="待全文",O13=0,P13=0,Q13+R13+S13=1),"角色已验收","需检查证据") -> 角色已验收 | AI13: =IF(COUNTIF($A$2:$A$91,A13)=1,"匹配","缺范围或重复") -> 匹配
A14: B16-MY-003 | B14: B16 | C14: MY | D14: Sun Life Malaysia Assurance Berhad | E14: Group Amanah Saham Assurance Contract (GASA 2014) | F14: 主角色提议 | G14: main_policy_with_endorsements | H14: 44 | I14: 44 | J14: 1, 2, 3, 17, 18, 19, 20, 21, 22, 27, 44 | K14: 11 | L14: 1, 18, 21, 22, 27, 44 | M14: 6 | N14: 待全文 | O14: 0 | P14: 0 | Q14: =IF(F14="主角色提议",1,0) -> 1 | R14: =IF(F14="非合同CIS",1,0) -> 0 | S14: =IF(F14="映射保留",1,0) -> 0 | T14: 1 | U14: regional-20261025-2480171341a01b0f | V14: 2480171341a01b0f17b78305a4878bfda7d7b961f044199077ed30ff09bf8342 | W14: base_issuer_in_operative_body: Sun Life Malaysia Assurance Berhad product_name: Group Amanah Saham Assurance (GASA 2014) master_reference_code: GASA0714 (endorsements) observed_dated_endorsements: 1 June 2021; 1 January 2015 version_boundary_note: GASA 2014 is observed nomenclature; later endorsement dates are not replacement base-edition evidence. | X14: Contents physical p21 (printed p1) is immediately followed by physical p22 (printed p3); listed printed p2 schedule not present at that adjacency. No package completeness conclusion. Base wording and amendments remain unreconciled. | Y14: p1/p18 independently confirm GASA2014/GASA0714 amendments dated 2021/2015. p21 lists GASA001 schedule p2 and GASA002 conditions p3; immediate p22 is printed p3 and explicitly defines issuer and operative policy composition. p27 supplies base death-payment wording. p44 terminal formula footer identifies GASA2014. | AA14: =HYPERLINK("https://chatgpt.com/api/library/files/libfile_f096861615788191b2089dd752505c74/download","B16私有元数据包") -> B16私有元数据包 | AB14: https://www.sunlifemalaysia.com/client-care/downloads/ | AC14: https://www.sunlifemalaysia.com/getContentAsset/19b99826-cbd7-41d5-b9ec-0ac26b2b238b/826411a5-9a44-43a6-8410-a7ad95da6d70/7.pdf | AD14: 46321.333 | AE14: 46321.346 | AF14: 46321.367 | AG14: B16-MY-003:accepted-role-only:20261026 | AH14: =IF(AND(AI14="匹配",LEN(V14)=64,J14<>"",L14<>"",K14>0,M14>0,AD14>0,AE14>0,AF14>0,AG14<>"",N14="待全文",O14=0,P14=0,Q14+R14+S14=1),"角色已验收","需检查证据") -> 角色已验收 | AI14: =IF(COUNTIF($A$2:$A$91,A14)=1,"匹配","缺范围或重复") -> 匹配
A15: B16-MY-004 | B15: B16 | C15: MY | D15: Sun Life Malaysia Assurance Berhad | E15: Group Amanah Saham Assurance Contract (New GASA) | F15: 映射保留 | G15: main_policy_with_endorsements_source_label_identity_unresolved | H15: 46 | I15: 46 | J15: 1, 2, 3, 19, 20, 21, 22, 23, 24, 29, 46 | K15: 11 | L15: 1, 3, 20, 23, 24, 29, 46 | M15: 7 | N15: 待全文 | O15: 0 | P15: 0 | Q15: =IF(F15="主角色提议",1,0) -> 0 | R15: =IF(F15="非合同CIS",1,0) -> 0 | S15: =IF(F15="映射保留",1,0) -> 1 | T15: 0 | U15: regional-20261025-ff30e8c3cfb2e4cc | V15: ff30e8c3cfb2e4cca399ca8effe4d3dd63a2b033159a1e6cc8ced25116a18625 | W15: base_issuer_in_operative_body: Sun Life Malaysia Assurance Berhad product_name: Group Amanah Saham Assurance (GASA 2014) master_reference_code: GASA0714 (endorsements) observed_dated_endorsements: 1 July 2025; 1 June 2021; 1 January 2015 version_boundary_note: GASA 2014 is observed nomenclature; later endorsement dates are not replacement base-edition evidence. | X15: Contents physical p23 (printed p1) is immediately followed by physical p24 (printed p3); listed printed p2 schedule not present at that adjacency. No package completeness conclusion. Base wording and amendments remain unreconciled. Frozen New GASA label is not established as the observed body title: sampled base and endorsements say GASA 2014 / GASA0714. Primary matching proposal withheld; no cross-file merge or product identity conclusion. 2025 amendment calls GASA001 general conditions, whereas sampled base contents/body use GASA002; retain annexure-reference discrepancy pending full reconciliation. | Y15: p1 and p3/p20 identify GASA2014/GASA0714, not New GASA; p1 2025 amendment calls GASA001 general conditions. p23 table/p24 body instead locate general conditions at GASA002 and p24 supplies issuer and operative constitution. p29 supplies death promise. p23 printed p1 goes directly to p24 printed p3; p46 terminal footer identifies GASA2014. Source-label discrepancy and annexure mismatch unresolved; primary proposal withheld. | Z15: Contents physical p23 (printed p1) is immediately followed by physical p24 (printed p3); listed printed p2 schedule not present at that adjacency. No package completeness conclusion. Base wording and amendments remain unreconciled. Frozen New GASA label is not established as the observed body title: sampled base and endorsements say GASA 2014 / GASA0714. Primary matching proposal withheld; no cross-file merge or product identity conclusion. 2025 amendment calls GASA001 general conditions, whereas sampled base contents/body use GASA002; retain annexure-reference discrepancy pending full reconciliation. | AA15: =HYPERLINK("https://chatgpt.com/api/library/files/libfile_f096861615788191b2089dd752505c74/download","B16私有元数据包") -> B16私有元数据包 | AB15: https://www.sunlifemalaysia.com/client-care/downloads/ | AC15: https://www.sunlifemalaysia.com/getContentAsset/78bc26a6-2dd9-4378-8743-c32f013d561d/826411a5-9a44-43a6-8410-a7ad95da6d70/5-Master-Policy-GASA-from-website-_0725.pdf?language=en | AD15: 46321.333 | AE15: 46321.346 | AF15: 46321.367 | AG15: B16-MY-004:accepted-role-only:20261026 | AH15: =IF(AND(AI15="匹配",LEN(V15)=64,J15<>"",L15<>"",K15>0,M15>0,AD15>0,AE15>0,AF15>0,AG15<>"",N15="待全文",O15=0,P15=0,Q15+R15+S15=1),"角色已验收","需检查证据") -> 角色已验收 | AI15: =IF(COUNTIF($A$2:$A$91,A15)=1,"匹配","缺范围或重复") -> 匹配
A16: B16-MY-005 | B16: B16 | C16: MY | D16: Sun Life Malaysia Assurance Berhad | E16: Group Mortgage Level Term Assurance Master Policy (MLTA 2015) | F16: 主角色提议 | G16: main_policy_with_endorsements | H16: 38 | I16: 38 | J16: 1, 2, 3, 12, 13, 14, 15, 21, 38 | K16: 9 | L16: 1, 3, 13, 14, 15, 21, 38 | M16: 7 | N16: 待全文 | O16: 0 | P16: 0 | Q16: =IF(F16="主角色提议",1,0) -> 1 | R16: =IF(F16="非合同CIS",1,0) -> 0 | S16: =IF(F16="映射保留",1,0) -> 0 | T16: 1 | U16: regional-20261025-d6f1b31f6a2f4a27 | V16: d6f1b31f6a2f4a27b5af4973a8e2888b28716fa5a6d4bc40f914b9376e4ad95a | W16: base_issuer_in_operative_body: Sun Life Malaysia Assurance Berhad product_name: Group Mortgage Level Term Assurance (MLTA 2015) master_reference_code: MLTA0615 master_holder: CIMB Bank Berhad (endorsement) observed_dated_endorsements: 06 December 2025; 19 May 2023 version_boundary_note: 2015 is observed base nomenclature; master code and later amendment dates do not establish current edition. | X16: Contents printed p1 immediately precedes general conditions printed p3; listed schedule p2 not present at that adjacency. Uninspected endorsements and all substantive/version relationships remain pending full review. | Y16: p1/p3 establish MLTA2015/MLTA0615 amendments dated 6 December 2025 and 19 May 2023, and CIMB Bank holder on p3. p13 table printed p1 leads immediately to p14 printed p3, leaving listed schedule p2 unestablished. p14 issuer definition, p15 operative constitution, p21 death promise establish main role; p38 terminal Malay continuation. | AA16: =HYPERLINK("https://chatgpt.com/api/library/files/libfile_f096861615788191b2089dd752505c74/download","B16私有元数据包") -> B16私有元数据包 | AB16: https://www.sunlifemalaysia.com/client-care/downloads/ | AC16: https://www.sunlifemalaysia.com/getContentAsset/a52a296b-7bf7-46a9-8e90-9b4bacd7cd55/826411a5-9a44-43a6-8410-a7ad95da6d70/6-Group-Mortgage-Level-Term-Assurance-Master-Policy-MLTA-2015-_1225.pdf?language=en | AD16: 46321.333 | AE16: 46321.346 | AF16: 46321.367 | AG16: B16-MY-005:accepted-role-only:20261026 | AH16: =IF(AND(AI16="匹配",LEN(V16)=64,J16<>"",L16<>"",K16>0,M16>0,AD16>0,AE16>0,AF16>0,AG16<>"",N16="待全文",O16=0,P16=0,Q16+R16+S16=1),"角色已验收","需检查证据") -> 角色已验收 | AI16: =IF(COUNTIF($A$2:$A$91,A16)=1,"匹配","缺范围或重复") -> 匹配
A17: B16-MY-006 | B17: B16 | C17: MY | D17: Sun Life Malaysia Assurance Berhad | E17: Group Mortgage Reducing Term Assurance Master Policy (MRTA 2015) | F17: 主角色提议 | G17: main_policy_with_endorsements | H17: 42 | I17: 42 | J17: 1, 2, 3, 12, 13, 14, 15, 16, 17, 21, 22, 42 | K17: 12 | L17: 1, 3, 14, 15, 16, 22, 42 | M17: 7 | N17: 待全文 | O17: 0 | P17: 0 | Q17: =IF(F17="主角色提议",1,0) -> 1 | R17: =IF(F17="非合同CIS",1,0) -> 0 | S17: =IF(F17="映射保留",1,0) -> 0 | T17: 1 | U17: regional-20261025-3777f3abd7942111 | V17: 3777f3abd79421110c324faf6534bed20939ec2e9c4186c587cf89120a9fae62 | W17: base_issuer_in_operative_body: Sun Life Malaysia Assurance Berhad product_name: Group Mortgage Reducing Term Assurance (MRTA 2015) master_reference_code: MRTA0615 master_holder: CIMB Bank Berhad (endorsement) observed_dated_endorsements: 06 December 2025; 27 June 2022 version_boundary_note: 2015 is observed base nomenclature; master code and later amendment dates do not establish current edition. | X17: Contents printed p1 immediately precedes general conditions printed p3; listed schedule p2 not present at that adjacency. Uninspected endorsements and all substantive/version relationships remain pending full review. | Y17: p1/p3 establish MRTA2015/MRTA0615 amendments dated 6 December 2025 and 27 June 2022, CIMB Bank holder on p3. p14 table printed p1 leads immediately to p15 printed p3; listed schedule p2 unestablished. p15 issuer definition, p16 operative constitution, p22 reducing-sum death promise establish main role; p42 terminal formula. | AA17: =HYPERLINK("https://chatgpt.com/api/library/files/libfile_f096861615788191b2089dd752505c74/download","B16私有元数据包") -> B16私有元数据包 | AB17: https://www.sunlifemalaysia.com/client-care/downloads/ | AC17: https://www.sunlifemalaysia.com/getContentAsset/42a1819d-8953-453b-86c1-388deb5ae85a/826411a5-9a44-43a6-8410-a7ad95da6d70/7-Group-Mortgage-Reducing-Term-Assurance-Master-Policy-MRTA-2015-_1225.pdf?language=en | AD17: 46321.333 | AE17: 46321.346 | AF17: 46321.367 | AG17: B16-MY-006:accepted-role-only:20261026 | AH17: =IF(AND(AI17="匹配",LEN(V17)=64,J17<>"",L17<>"",K17>0,M17>0,AD17>0,AE17>0,AF17>0,AG17<>"",N17="待全文",O17=0,P17=0,Q17+R17+S17=1),"角色已验收","需检查证据") -> 角色已验收 | AI17: =IF(COUNTIF($A$2:$A$91,A17)=1,"匹配","缺范围或重复") -> 匹配
A18: B16-MY-007 | B18: B16 | C18: MY | D18: Sun Life Malaysia Assurance Berhad | E18: Group Mortgage Reducing Term Assurance Master Policy (MRTA 2015 - Business Loan) | F18: 主角色提议 | G18: main_policy_with_endorsements_and_conditional_rider | H18: 58 | I18: 58 | J18: 1, 2, 3, 13, 14, 15, 16, 23, 24, 25, 26, 27, 28, 29, 30, 33, 37, 57, 58 | K18: 19 | L18: 1, 3, 13, 25, 26, 27, 33, 57, 58 | M18: 9 | N18: 待全文 | O18: 0 | P18: 0 | Q18: =IF(F18="主角色提议",1,0) -> 1 | R18: =IF(F18="非合同CIS",1,0) -> 0 | S18: =IF(F18="映射保留",1,0) -> 0 | T18: 1 | U18: regional-20261025-764a37e7b69ee85e | V18: 764a37e7b69ee85e5ff36b41e31235abbe7c4eb89bf4e99db8a196e6a62e53d4 | W18: base_issuer_in_operative_body: Sun Life Malaysia Assurance Berhad product_name: Group Mortgage Reducing Term Assurance (MRTA 2015) - Business Loan master_reference_code: GBLI0615 master_holder: CIMB Bank Berhad master_policy_commencement_date: 23 May 2016 (schedule) observed_dated_endorsements: 06 December 2025; 27 June 2022 version_boundary_note: Schedule commencement is not a base-edition date; 2015 title and 2016 commencement retained separately. | X18: Uninspected intervening endorsements, rider applicability and language boundaries remain unreconciled. Schedule and base eligibility mention property-loan applicants despite Business Loan title; no eligibility reconciliation or product inference performed. | Y18: p1/p3 confirm Business Loan/GBLI0615 and 2025/2022 amendments; p13 confirms conditional MRTA006 refund rider, not independent base policy. p25 schedule shows CIMB Bank, GBLI0615, 23 May 2016 commencement; this is not edition date. p26 issuer and p27 operative constitution plus p33 death promise establish main role. p25/p27 say property-loan applicants despite Business Loan title. p57 terminal Malay formula/p58 visually blank; no completeness conclusion. | AA18: =HYPERLINK("https://chatgpt.com/api/library/files/libfile_f096861615788191b2089dd752505c74/download","B16私有元数据包") -> B16私有元数据包 | AB18: https://www.sunlifemalaysia.com/client-care/downloads/ | AC18: https://www.sunlifemalaysia.com/getContentAsset/3163bef3-5c68-4a79-9ad6-f28095b1518c/826411a5-9a44-43a6-8410-a7ad95da6d70/8-Group-Mortgage-Reducing-Term-Assurance-Master-Policy-MRTA-2015-BL-_1225.pdf?language=en | AD18: 46321.333 | AE18: 46321.346 | AF18: 46321.367 | AG18: B16-MY-007:accepted-role-only:20261026 | AH18: =IF(AND(AI18="匹配",LEN(V18)=64,J18<>"",L18<>"",K18>0,M18>0,AD18>0,AE18>0,AF18>0,AG18<>"",N18="待全文",O18=0,P18=0,Q18+R18+S18=1),"角色已验收","需检查证据") -> 角色已验收 | AI18: =IF(COUNTIF($A$2:$A$91,A18)=1,"匹配","缺范围或重复") -> 匹配
A19: B16-MY-008 | B19: B16 | C19: MY | D19: Sun Life Malaysia Assurance Berhad | E19: Mortgage Reducing Term Assurance Master Policy - for certificate issued after 5th Aug 2013 | F19: 主角色提议 | G19: historical_main_policy_with_endorsements | H19: 32 | I19: 32 | J19: 1, 2, 3, 7, 8, 9, 10, 15, 32 | K19: 9 | L19: 1, 3, 7, 9, 10, 15, 32 | M19: 7 | N19: 待全文 | O19: 0 | P19: 0 | Q19: =IF(F19="主角色提议",1,0) -> 1 | R19: =IF(F19="非合同CIS",1,0) -> 0 | S19: =IF(F19="映射保留",1,0) -> 0 | T19: 1 | U19: regional-20261025-0c4a8cc94b3d7f74 | V19: 0c4a8cc94b3d7f74f861c884002c38959085fd2a6543dd43926874c7a509c640 | W19: base_issuer_in_operative_body: CIMB Aviva Assurance Berhad endorsement_issuer: Sun Life Malaysia Assurance Berhad documentary_name_change_bridge: In-file p7 notice effective 19 August 2013; not externally registry-verified. product_name: Group Mortgage Reducing Term Assurance master_reference_code: MRTA0813 (endorsements) observed_dated_endorsements: 1 July 2020; 1 January 2015 version_boundary_note: Code is observed reference; does not independently prove the frozen certificate-issued-after-5-August-2013 cutoff. | X19: Frozen certificate-issued-after-5-August-2013 applicability is a source label not independently established by sampled anchors. Listed schedule printed p2 is absent from physical p9→p10 adjacency (printed p1→p3). Historical base and later amendments are not reconciled or adopted as current. | Y19: p1/p3 identify MRTA0813 amendments dated 2020/2015 from Sun Life. p7 in-file name-change notice is effective 19 August 2013; p10 explicitly defines CIMB Aviva Assurance as issuer and contains operative constitution, p15 death promise. p9 printed p1 leads to p10 printed p3; listed schedule p2 unestablished. p32 terminal historical-issuer Malay formula. Source certificate cutoff remains unverified; no registry/current-version inference. | AA19: =HYPERLINK("https://chatgpt.com/api/library/files/libfile_f096861615788191b2089dd752505c74/download","B16私有元数据包") -> B16私有元数据包 | AB19: https://www.sunlifemalaysia.com/client-care/downloads/ | AC19: https://www.sunlifemalaysia.com/getContentAsset/59ad5224-2340-45da-849f-cc1ff15228aa/826411a5-9a44-43a6-8410-a7ad95da6d70/12.pdf | AD19: 46321.333 | AE19: 46321.346 | AF19: 46321.367 | AG19: B16-MY-008:accepted-role-only:20261026 | AH19: =IF(AND(AI19="匹配",LEN(V19)=64,J19<>"",L19<>"",K19>0,M19>0,AD19>0,AE19>0,AF19>0,AG19<>"",N19="待全文",O19=0,P19=0,Q19+R19+S19=1),"角色已验收","需检查证据") -> 角色已验收 | AI19: =IF(COUNTIF($A$2:$A$91,A19)=1,"匹配","缺范围或重复") -> 匹配
A20: B16-MY-009 | B20: B16 | C20: MY | D20: Sun Life Malaysia Assurance Berhad | E20: Mortgage Reducing Term Assurance Master Policy - for certificate issued prior to 2013 | F20: 主角色提议 | G20: historical_main_policy_with_endorsements | H20: 22 | I20: 22 | J20: 1, 2, 3, 4, 5, 6, 7, 8, 11, 21, 22 | K20: 11 | L20: 1, 2, 4, 5, 6, 8, 11, 21, 22 | M20: 9 | N20: 待全文 | O20: 0 | P20: 0 | Q20: =IF(F20="主角色提议",1,0) -> 1 | R20: =IF(F20="非合同CIS",1,0) -> 0 | S20: =IF(F20="映射保留",1,0) -> 0 | T20: 1 | U20: regional-20261025-68b4ba22a06ebd69 | V20: 68b4ba22a06ebd69a6624173131c5f1302b1f0caf0bf6850878fd9ba1708c511 | W20: base_issuer_in_operative_body: CIMB Aviva Assurance Berhad endorsement_issuer: Sun Life Malaysia Assurance Berhad documentary_name_change_bridge: In-file p4 notice effective 19 August 2013; not externally registry-verified. product_name: Mortgage Reducing Term Assurance (MRTA) master_reference_code: GCL00001 (endorsement) observed_dated_endorsements: 1 July 2020 version_boundary_note: Frozen prior-to-2013 certificate cutoff is not established by the sampled body; historical issuer retained. cover_bank_label: CIMB Bank Berhad; capacity not expressly labelled on sampled cover | X20: Frozen prior-to-2013 certificate applicability remains unverified. Base cover uses Master Contract while operative clauses and endorsement use policy; nomenclature preserved without ownership inference. First Schedule not established by sampled cover→Second Schedule adjacency; full package remains pending. Malay endorsement GTL002 versus English Second Schedule reference requires later reconciliation. CIMB Bank appears on base cover; its master-holder capacity is not independently established from a schedule by this QA. Original executor cover attribution retained without silently promoting it. | Y20: p1 identifies GCL00001/2020 endorsement using Second Schedule; p2 Malay counterpart uses GTL002, retained discrepancy. p4 name-change notice and p6 CIMB Aviva issuer definition provide documentary bridge; p8 policy constitution and p11 death/TPD promises establish historical main role. p5 cover says Master Contract and names CIMB Bank but does not expressly label its capacity. p21 Malay terminal formula/p22 visually blank; First Schedule not established and prior-2013 source cutoff remains unproved. | AA20: =HYPERLINK("https://chatgpt.com/api/library/files/libfile_f096861615788191b2089dd752505c74/download","B16私有元数据包") -> B16私有元数据包 | AB20: https://www.sunlifemalaysia.com/client-care/downloads/ | AC20: https://www.sunlifemalaysia.com/getContentAsset/151d07b5-6ade-4464-951a-c9be59c94838/826411a5-9a44-43a6-8410-a7ad95da6d70/13.pdf | AD20: 46321.333 | AE20: 46321.346 | AF20: 46321.367 | AG20: B16-MY-009:accepted-role-only:20261026 | AH20: =IF(AND(AI20="匹配",LEN(V20)=64,J20<>"",L20<>"",K20>0,M20>0,AD20>0,AE20>0,AF20>0,AG20<>"",N20="待全文",O20=0,P20=0,Q20+R20+S20=1),"角色已验收","需检查证据") -> 角色已验收 | AI20: =IF(COUNTIF($A$2:$A$91,A20)=1,"匹配","缺范围或重复") -> 匹配
A21: B16-MY-010 | B21: B16 | C21: MY | D21: Sun Life Malaysia Assurance Berhad | E21: Mortgage Reducing Term Assurance Master Policy (Business Loan)- for certificate issued prior to 2015 | F21: 主角色提议 | G21: main_policy_with_endorsements | H21: 32 | I21: 32 | J21: 1, 2, 3, 7, 8, 9, 10, 15, 32 | K21: 9 | L21: 1, 3, 8, 9, 10, 15, 32 | M21: 7 | N21: 待全文 | O21: 0 | P21: 0 | Q21: =IF(F21="主角色提议",1,0) -> 1 | R21: =IF(F21="非合同CIS",1,0) -> 0 | S21: =IF(F21="映射保留",1,0) -> 0 | T21: 1 | U21: regional-20261025-88f32c7d739ec36f | V21: 88f32c7d739ec36f58172a41d6781fd812df2a5ca9f35666395805ff2c07f82b | W21: base_issuer_in_operative_body: Sun Life Malaysia Assurance Berhad product_name: Group Mortgage Reducing Term Assurance - Business Loan master_reference_code: GBLI0714 (endorsements) observed_dated_endorsements: 1 July 2020; 1 January 2015 version_boundary_note: GBLI0714 is an observed master reference; frozen prior-to-2015 certificate cutoff not independently established. | X21: Frozen certificate-issued-prior-to-2015 applicability is not independently established by sampled anchors. Contents p1 immediately precedes general conditions p3; listed schedule p2 not present at that adjacency. All uninspected endorsement relationships, language boundaries and substantive adoption remain pending. | Y21: p1/p3 identify Business Loan/GBLI0714 and 2020/2015 amendments; p8 table printed p1 goes immediately to p9 printed p3, listed schedule p2 unestablished. p9 issuer and policy-composition clause, p10 explicit business-loan eligibility/operative cover, p15 death promise establish main role. p32 terminal Malay formula. Prior-2015 source cutoff remains unproved. | AA21: =HYPERLINK("https://chatgpt.com/api/library/files/libfile_f096861615788191b2089dd752505c74/download","B16私有元数据包") -> B16私有元数据包 | AB21: https://www.sunlifemalaysia.com/client-care/downloads/ | AC21: https://www.sunlifemalaysia.com/getContentAsset/ab31d08a-f132-46c5-b2f4-8e8ebbb19810/826411a5-9a44-43a6-8410-a7ad95da6d70/14.pdf | AD21: 46321.333 | AE21: 46321.346 | AF21: 46321.367 | AG21: B16-MY-010:accepted-role-only:20261026 | AH21: =IF(AND(AI21="匹配",LEN(V21)=64,J21<>"",L21<>"",K21>0,M21>0,AD21>0,AE21>0,AF21>0,AG21<>"",N21="待全文",O21=0,P21=0,Q21+R21+S21=1),"角色已验收","需检查证据") -> 角色已验收 | AI21: =IF(COUNTIF($A$2:$A$91,A21)=1,"匹配","缺范围或重复") -> 匹配
A22: B16-MY-011 | B22: B16 | C22: MY | D22: Sun Life Malaysia Assurance Berhad | E22: SmartLife (Group Term Life) Master Policy | F22: 主角色提议 | G22: historical_main_policy_with_endorsements | H22: 89 | I22: 89 | J22: 1, 2, 3, 25, 26, 27, 28, 29, 30, 31, 32, 33, 34, 35, 39, 89 | K22: 16 | L22: 1, 3, 26, 30, 32, 33, 39 | M22: 7 | N22: 待全文 | O22: 0 | P22: 0 | Q22: =IF(F22="主角色提议",1,0) -> 1 | R22: =IF(F22="非合同CIS",1,0) -> 0 | S22: =IF(F22="映射保留",1,0) -> 0 | T22: 1 | U22: regional-20261025-adb4d99226d29ac5 | V22: adb4d99226d29ac54b45df1c6866fd6117388654147a376bb771f76ef1ac02ba | W22: base_issuer_in_operative_body: CIMB Aviva Assurance Berhad product_name: SmartLife (Group Term Life) master_reference_code: GTL0313 version_boundary_note: Codes/title years, endorsement dates and attached-notice dates are not inferred editions or current-adoption evidence. later_issuer_in_attachment: Sun Life Malaysia Assurance Berhad documentary_name_change_bridge: p30 name-change notice effective 19 August 2013; documentary bridge only. | X22: Named holder and schedule remain unestablished; physical p32/p33 jump printed p1 to p3 across scheduled p2. Keep amended p26 and historical p33 policy constitution separate pending full reconciliation. Named master holder and actual schedule were not established. TOC references schedule p2 but adjacent physical p33 begins printed p3; package completeness remains unresolved. | Y22: Body-based operative main wording and issuer identity inspected; not filename-only. Only named anchors were inspected; not every selected page or file fully read. No independent adoption of uninspected terminal/attachment details. Main-containing role label is not an exhaustive attachment inventory or exact version/product/package adoption. | AA22: =HYPERLINK("https://chatgpt.com/api/library/files/libfile_f096861615788191b2089dd752505c74/download","B16私有元数据包") -> B16私有元数据包 | AB22: https://www.sunlifemalaysia.com/client-care/downloads/ | AC22: https://www.sunlifemalaysia.com/getContentAsset/4c1b0051-340d-4ddb-a349-e778c18d5051/826411a5-9a44-43a6-8410-a7ad95da6d70/15.pdf | AD22: 46321.333 | AE22: 46321.346 | AF22: 46321.367 | AG22: B16-MY-011:accepted-role-only:20261026 | AH22: =IF(AND(AI22="匹配",LEN(V22)=64,J22<>"",L22<>"",K22>0,M22>0,AD22>0,AE22>0,AF22>0,AG22<>"",N22="待全文",O22=0,P22=0,Q22+R22+S22=1),"角色已验收","需检查证据") -> 角色已验收 | AI22: =IF(COUNTIF($A$2:$A$91,A22)=1,"匹配","缺范围或重复") -> 匹配
A23: B16-MY-012 | B23: B16 | C23: MY | D23: Sun Life Malaysia Assurance Berhad | E23: Sun ProtectMax Master Policy | F23: 主角色提议 | G23: main_policy_with_endorsements | H23: 158 | I23: 158 | J23: 1, 2, 3, 19, 20, 21, 22, 89, 90, 91, 92, 93, 94, 102, 158 | K23: 15 | L23: 1, 3, 19, 89, 94, 102 | M23: 6 | N23: 待全文 | O23: 0 | P23: 0 | Q23: =IF(F23="主角色提议",1,0) -> 1 | R23: =IF(F23="非合同CIS",1,0) -> 0 | S23: =IF(F23="映射保留",1,0) -> 0 | T23: 1 | U23: regional-20261025-245d20c5931ef4a3 | V23: 245d20c5931ef4a383f179dbf7e229d9210117697c17c6f4baa8233523a14f8a | W23: base_issuer_in_operative_body: Sun Life Malaysia Assurance Berhad product_name: Sun ProtectMax master_reference_code: SPM0918 master_holder: CIMB Bank Berhad version_boundary_note: Codes/title years, endorsement dates and attached-notice dates are not inferred editions or current-adoption evidence. | X23: English endorsement and Malay base anchors only; English base boundaries, all amendments and language reconciliation pending. Benefit-table campaign codes do not establish independent products. Only selected English endorsement and Malay base anchors inspected; English base start and all attachment boundaries are not established. Campaign/table codes are not independent products. | Y23: Body-based operative main wording and issuer identity inspected; not filename-only. Only named anchors were inspected; not every selected page or file fully read. No independent adoption of uninspected terminal/attachment details. Main-containing role label is not an exhaustive attachment inventory or exact version/product/package adoption. | AA23: =HYPERLINK("https://chatgpt.com/api/library/files/libfile_f096861615788191b2089dd752505c74/download","B16私有元数据包") -> B16私有元数据包 | AB23: https://www.sunlifemalaysia.com/client-care/downloads/ | AC23: https://www.sunlifemalaysia.com/getContentAsset/e5f46b34-6f2e-4877-8a4b-eccfc8046979/826411a5-9a44-43a6-8410-a7ad95da6d70/11-Sun-ProtectMax_Master-Policy-Website-_0725.pdf?language=en | AD23: 46321.333 | AE23: 46321.346 | AF23: 46321.367 | AG23: B16-MY-012:accepted-role-only:20261026 | AH23: =IF(AND(AI23="匹配",LEN(V23)=64,J23<>"",L23<>"",K23>0,M23>0,AD23>0,AE23>0,AF23>0,AG23<>"",N23="待全文",O23=0,P23=0,Q23+R23+S23=1),"角色已验收","需检查证据") -> 角色已验收 | AI23: =IF(COUNTIF($A$2:$A$91,A23)=1,"匹配","缺范围或重复") -> 匹配
A24: B16-MY-013 | B24: B16 | C24: MY | D24: Sun Life Malaysia Assurance Berhad | E24: Sun Guard Master Policy | F24: 主角色提议 | G24: main_policy_with_endorsements | H24: 82 | I24: 82 | J24: 1, 2, 3, 7, 8, 9, 10, 12, 19, 82 | K24: 10 | L24: 1, 3, 12, 19 | M24: 4 | N24: 待全文 | O24: 0 | P24: 0 | Q24: =IF(F24="主角色提议",1,0) -> 1 | R24: =IF(F24="非合同CIS",1,0) -> 0 | S24: =IF(F24="映射保留",1,0) -> 0 | T24: 1 | U24: regional-20261025-d06bfb474ad633bf | V24: d06bfb474ad633bf270af828d2ef5783fad8262a5da54c4d12d70eacbcc3540d | W24: base_issuer_in_operative_body: Sun Life Malaysia Assurance Berhad product_name: Sun Guard master_reference_code: SDG1019 master_holder: U Mobile Sdn Bhd version_boundary_note: Codes/title years, endorsement dates and attached-notice dates are not inferred editions or current-adoption evidence. | X24: Holder is a master holder, not insurer; distribution subtype, base edition, complete attachment inventory and current adoption unproved. Holder U Mobile is established in operative definitions; this does not establish distribution subtype, current adoption or package completeness. | Y24: Body-based operative main wording and issuer identity inspected; not filename-only. Only named anchors were inspected; not every selected page or file fully read. No independent adoption of uninspected terminal/attachment details. Main-containing role label is not an exhaustive attachment inventory or exact version/product/package adoption. | AA24: =HYPERLINK("https://chatgpt.com/api/library/files/libfile_f096861615788191b2089dd752505c74/download","B16私有元数据包") -> B16私有元数据包 | AB24: https://www.sunlifemalaysia.com/client-care/downloads/ | AC24: https://www.sunlifemalaysia.com/getContentAsset/8f6b5644-133e-4865-a511-d1f3c751b65e/826411a5-9a44-43a6-8410-a7ad95da6d70/19.pdf | AD24: 46321.333 | AE24: 46321.346 | AF24: 46321.367 | AG24: B16-MY-013:accepted-role-only:20261026 | AH24: =IF(AND(AI24="匹配",LEN(V24)=64,J24<>"",L24<>"",K24>0,M24>0,AD24>0,AE24>0,AF24>0,AG24<>"",N24="待全文",O24=0,P24=0,Q24+R24+S24=1),"角色已验收","需检查证据") -> 角色已验收 | AI24: =IF(COUNTIF($A$2:$A$91,A24)=1,"匹配","缺范围或重复") -> 匹配
A25: B16-MY-014 | B25: B16 | C25: MY | D25: Sun Life Malaysia Assurance Berhad | E25: Sun Flexi Master Policy | F25: 主角色提议 | G25: main_policy_with_endorsements | H25: 67 | I25: 67 | J25: 1, 2, 3, 9, 10, 11, 12, 14, 15, 24, 67 | K25: 11 | L25: 1, 3, 10, 11, 15, 24 | M25: 6 | N25: 待全文 | O25: 0 | P25: 0 | Q25: =IF(F25="主角色提议",1,0) -> 1 | R25: =IF(F25="非合同CIS",1,0) -> 0 | S25: =IF(F25="映射保留",1,0) -> 0 | T25: 1 | U25: regional-20261025-e8b5883b02da0933 | V25: e8b5883b02da093391920e0fccf3b39b414a919ad0a5a486e8530510eb511c93 | W25: base_issuer_in_operative_body: Sun Life Malaysia Assurance Berhad product_name: Sun Flexi master_reference_code: SDG1018 master_holder: CIMB Bank Berhad version_boundary_note: Codes/title years, endorsement dates and attached-notice dates are not inferred editions or current-adoption evidence. | X25: Pagination conflict p2 of48 followed by p4 of29 confirmed; missing extent and schedule completeness not inferred. Executor-reported terminal Malay pagination retained as a pending observation, not independently revisited here. Printed pagination is internally nonuniform: physical p10 says p2 of48, p11 says p4 of29, p12 says p5 of29, terminal p67 says Malay p32 of32. Do not infer missing-page extent or completeness from this checkpoint. | Y25: Body-based operative main wording and issuer identity inspected; not filename-only. Only named anchors were inspected; not every selected page or file fully read. No independent adoption of uninspected terminal/attachment details. Main-containing role label is not an exhaustive attachment inventory or exact version/product/package adoption. | AA25: =HYPERLINK("https://chatgpt.com/api/library/files/libfile_f096861615788191b2089dd752505c74/download","B16私有元数据包") -> B16私有元数据包 | AB25: https://www.sunlifemalaysia.com/client-care/downloads/ | AC25: https://www.sunlifemalaysia.com/getContentAsset/5dfb960d-fe6f-4d98-bc4c-84f16becd244/826411a5-9a44-43a6-8410-a7ad95da6d70/12-Sun-Flexi-Master-Policy-Website-_0725.pdf?language=en | AD25: 46321.333 | AE25: 46321.346 | AF25: 46321.367 | AG25: B16-MY-014:accepted-role-only:20261026 | AH25: =IF(AND(AI25="匹配",LEN(V25)=64,J25<>"",L25<>"",K25>0,M25>0,AD25>0,AE25>0,AF25>0,AG25<>"",N25="待全文",O25=0,P25=0,Q25+R25+S25=1),"角色已验收","需检查证据") -> 角色已验收 | AI25: =IF(COUNTIF($A$2:$A$91,A25)=1,"匹配","缺范围或重复") -> 匹配
A26: B16-MY-015 | B26: B16 | C26: MY | D26: Sun Life Malaysia Assurance Berhad | E26: Mortgage Reducing Term Assurance with Funeral Benefit 2024 (MRTA) | F26: 主角色提议 | G26: main_policy_with_endorsements | H26: 20 | I26: 20 | J26: 1, 2, 3, 4, 12, 18, 20 | K26: 7 | L26: 1, 2, 3, 4, 12, 18 | M26: 6 | N26: 待全文 | O26: 0 | P26: 0 | Q26: =IF(F26="主角色提议",1,0) -> 1 | R26: =IF(F26="非合同CIS",1,0) -> 0 | S26: =IF(F26="映射保留",1,0) -> 0 | T26: 1 | U26: regional-20261025-0b44500849ab0519 | V26: 0b44500849ab0519f6f4de2119ae14016be7a86dbf9561bcf4cbfc5cf12212ff | W26: base_issuer_in_operative_body: Sun Life Malaysia Assurance Berhad product_name: Insurans Pengurangan Tempoh Gadai Janji dengan Manfaat Khairat Kematian 2024 master_reference_code: MRTAFB24 version_boundary_note: Codes/title years, endorsement dates and attached-notice dates are not inferred editions or current-adoption evidence. | X26: Inspected source wording is Malay; frozen en/ms language label does not prove bilingual content. 2024 is part of the observed title, not independently established edition/current status. Named holder and schedule unestablished; adjacency skips printed p4. Actual anchors are Malay. Frozen language label en/ms is not accepted as proof of bilingual content. Schedule/holder not established; physical p3 printed p3 is followed by physical p4 printed p5. | Y26: Body-based operative main wording and issuer identity inspected; not filename-only. Only named anchors were inspected; not every selected page or file fully read. No independent adoption of uninspected terminal/attachment details. Main-containing role label is not an exhaustive attachment inventory or exact version/product/package adoption. | AA26: =HYPERLINK("https://chatgpt.com/api/library/files/libfile_f096861615788191b2089dd752505c74/download","B16私有元数据包") -> B16私有元数据包 | AB26: https://www.sunlifemalaysia.com/client-care/downloads/ | AC26: https://www.sunlifemalaysia.com/getContentAsset/95bbeb9b-5a64-4b91-b3a9-a537a6d476ca/826411a5-9a44-43a6-8410-a7ad95da6d70/9-MRTA-LPPSA_Master-Policy-Website-_0725.pdf?language=en | AD26: 46321.333 | AE26: 46321.346 | AF26: 46321.367 | AG26: B16-MY-015:accepted-role-only:20261026 | AH26: =IF(AND(AI26="匹配",LEN(V26)=64,J26<>"",L26<>"",K26>0,M26>0,AD26>0,AE26>0,AF26>0,AG26<>"",N26="待全文",O26=0,P26=0,Q26+R26+S26=1),"角色已验收","需检查证据") -> 角色已验收 | AI26: =IF(COUNTIF($A$2:$A$91,A26)=1,"匹配","缺范围或重复") -> 匹配
A27: B16-MY-016 | B27: B16 | C27: MY | D27: Sun Life Malaysia Takaful Berhad | E27: Credit Protector Plus-i Master Contract | F27: 主角色提议 | G27: main_contract | H27: 53 | I27: 53 | J27: 1, 2, 3, 4, 5, 14, 53 | K27: 7 | L27: 1, 2, 3, 5, 14 | M27: 5 | N27: 待全文 | O27: 0 | P27: 0 | Q27: =IF(F27="主角色提议",1,0) -> 1 | R27: =IF(F27="非合同CIS",1,0) -> 0 | S27: =IF(F27="映射保留",1,0) -> 0 | T27: 1 | U27: regional-20261025-d6a9cc0757273b57 | V27: d6a9cc0757273b57079338e32012107b3767cb2239485145e81b10df9965e368 | W27: base_issuer_in_operative_body: Sun Life Malaysia Takaful Berhad product_name: Credit Protector Plus-i (CPP-i) version_boundary_note: Codes/title years, endorsement dates and attached-notice dates are not inferred editions or current-adoption evidence. | X27: CPPI001/003/007 are observed annexure labels, not master reference or edition. Named holder and schedule unestablished; printed p2 to p4 adjacency retained. No named master holder or master reference established. Physical p2 printed p2 is followed by physical p3 printed p4; schedule completeness unresolved. | Y27: Body-based operative main wording and issuer identity inspected; not filename-only. Only named anchors were inspected; not every selected page or file fully read. No independent adoption of uninspected terminal/attachment details. Main-containing role label is not an exhaustive attachment inventory or exact version/product/package adoption. | AA27: =HYPERLINK("https://chatgpt.com/api/library/files/libfile_f096861615788191b2089dd752505c74/download","B16私有元数据包") -> B16私有元数据包 | AB27: https://www.sunlifemalaysia.com/client-care/downloads/ | AC27: https://www.sunlifemalaysia.com/getContentAsset/6e5d72e9-c864-4744-b649-8a153bac7fa7/826411a5-9a44-43a6-8410-a7ad95da6d70/Master-Contract_CPP-i_v1-0_15042026-Final-_Website.pdf | AD27: 46321.333 | AE27: 46321.346 | AF27: 46321.367 | AG27: B16-MY-016:accepted-role-only:20261026 | AH27: =IF(AND(AI27="匹配",LEN(V27)=64,J27<>"",L27<>"",K27>0,M27>0,AD27>0,AE27>0,AF27>0,AG27<>"",N27="待全文",O27=0,P27=0,Q27+R27+S27=1),"角色已验收","需检查证据") -> 角色已验收 | AI27: =IF(COUNTIF($A$2:$A$91,A27)=1,"匹配","缺范围或重复") -> 匹配
... A31: B16-MY-020 | B31: B16 | C31: MY | D31: Sun Life Malaysia Takaful Berhad | E31: Cash Plus-i Protector Plan Contract | F31: 主角色提议 | G31: historical_main_contract_with_attached_notices | H31: 32 | I31: 32 | J31: 1, 2, 3, 4, 5, 6, 7, 8, 32 | K31: 9 | L31: 1, 2, 3, 5, 6, 7 | M31: 6 | N31: 待全文 | O31: 0 | P31: 0 | Q31: =IF(F31="主角色提议",1,0) -> 1 | R31: =IF(F31="非合同CIS",1,0) -> 0 | S31: =IF(F31="映射保留",1,0) -> 0 | T31: 1 | U31: regional-20261025-2cefe456e8676d68 | V31: 2cefe456e8676d683ef3d6e53e00485bc85a563996113afc24a12f8fb1060c54 | W31: base_issuer_in_operative_body: CIMB Aviva Takaful Berhad product_name: Cash Plus-i Protector Plan version_boundary_note: Codes/title years, endorsement dates and attached-notice dates are not inferred editions or current-adoption evidence. later_issuer_in_attachment: Sun Life Malaysia Takaful Berhad documentary_name_change_bridge: p1 name-change notice effective 19 August 2013; p3 expressly says formerly CIMB Aviva Takaful. Documentary only. | X31: Generic surplus-management notice applicability to Cash Plus-i remains unreconciled. No master reference, named holder, base edition or current adoption established. Master reference and named holder were not established. Generic surplus-management notice names other products; applicability not reconciled. | Y31: Body-based operative main wording and issuer identity inspected; not filename-only. Only named anchors were inspected; not every selected page or file fully read. No independent adoption of uninspected terminal/attachment details. Main-containing role label is not an exhaustive attachment inventory or exact version/product/package adoption. | AA31: =HYPERLINK("https://chatgpt.com/api/library/files/libfile_f096861615788191b2089dd752505c74/download","B16私有元数据包") -> B16私有元数据包 | AB31: https://www.sunlifemalaysia.com/client-care/downloads/ | AC31: https://www.sunlifemalaysia.com/getContentAsset/b03d622c-b898-4ba6-9b4d-c9a123a33a6d/826411a5-9a44-43a6-8410-a7ad95da6d70/3a.pdf | AD31: 46321.333 | AE31: 46321.346 | AF31: 46321.367 | AG31: B16-MY-020:accepted-role-only:20261026 | AH31: =IF(AND(AI31="匹配",LEN(V31)=64,J31<>"",L31<>"",K31>0,M31>0,AD31>0,AE31>0,AF31>0,AG31<>"",N31="待全文",O31=0,P31=0,Q31+R31+S31=1),"角色已验收","需检查证据") -> 角色已验收 | AI31: =IF(COUNTIF($A$2:$A$91,A31)=1,"匹配","缺范围或重复") -> 匹配
A32: B16-MY-021 | B32: B16 | C32: MY | D32: Sun Life Malaysia Takaful Berhad | E32: CuepacsCare Contract | F32: 主角色提议 | G32: main_contract_with_endorsements | H32: 46 | I32: 46 | J32: 1, 2, 5, 6, 7, 8, 9, 15, 46 | K32: 9 | L32: 1, 5, 7, 8, 9, 46 | M32: 6 | N32: 待全文 | O32: 0 | P32: 0 | Q32: =IF(F32="主角色提议",1,0) -> 1 | R32: =IF(F32="非合同CIS",1,0) -> 0 | S32: =IF(F32="映射保留",1,0) -> 0 | T32: 1 | U32: regional-20261025-b4aac8e0c7e022d1 | V32: b4aac8e0c7e022d1ecec67df7ee401b504ce8a8060cd2ca4d3992b82d4f8f423 | W32: base_issuer_in_operative_body: Sun Life Malaysia Takaful Berhad endorsement_issuer: Sun Life Malaysia Takaful Berhad product_name: CuepacsCare master_reference_codes_in_endorsements: CPC0814 observed_dated_endorsements: 1 January 2015 version_boundary_note: Attachment dates and reference-code digits are not a base-edition date, complete amendment inventory, or evidence of current use. | X32: Observed page numbering skips schedule printed p3 between physical p7 and p8; file ends at printed Malay 22 of 25. Schedule presence and completeness are not established; no missing-content reconstruction. Base edition, complete intervening amendment/language boundaries and schedules remain unverified. | AA32: =HYPERLINK("https://chatgpt.com/api/library/files/libfile_f096861615788191b2089dd752505c74/download","B16私有元数据包") -> B16私有元数据包 | AB32: https://www.sunlifemalaysia.com/client-care/downloads/ | AC32: https://www.sunlifemalaysia.com/getContentAsset/d0f707c9-eee8-4148-8684-654bb153556c/826411a5-9a44-43a6-8410-a7ad95da6d70/4a.pdf | AD32: 46321.333 | AE32: 46321.346 | AF32: 46321.367 | AG32: B16-MY-021:accepted-role-only:20261026 | AH32: =IF(AND(AI32="匹配",LEN(V32)=64,J32<>"",L32<>"",K32>0,M32>0,AD32>0,AE32>0,AF32>0,AG32<>"",N32="待全文",O32=0,P32=0,Q32+R32+S32=1),"角色已验收","需检查证据") -> 角色已验收 | AI32: =IF(COUNTIF($A$2:$A$91,A32)=1,"匹配","缺范围或重复") -> 匹配
A33: B16-MY-022 | B33: B16 | C33: MY | D33: Sun Life Malaysia Takaful Berhad | E33: Decreasing Term Takaful (DTT) with Optional CI Waiver Benefit Master Contract | F33: 映射保留 | G33: historical_main_contract_with_endorsements_identity_unresolved | H33: 100 | I33: 100 | J33: 1, 2, 40, 44, 45, 46, 47, 48, 49, 50, 55, 100 | K33: 12 | L33: 1, 2, 45, 47, 48, 49, 50, 55 | M33: 8 | N33: 待全文 | O33: 0 | P33: 0 | Q33: =IF(F33="主角色提议",1,0) -> 0 | R33: =IF(F33="非合同CIS",1,0) -> 0 | S33: =IF(F33="映射保留",1,0) -> 1 | T33: 0 | U33: regional-20261025-553d1edd0b57d5c8 | V33: 553d1edd0b57d5c86eacd45ff45f566d81fe7f89ca046cf3fb20d2e03f2b7620 | W33: base_issuer_in_operative_body: CIMB Aviva Takaful Berhad endorsement_issuer: Sun Life Malaysia Takaful Berhad product_name: Decreasing Term Takaful (DTT) with Optional CI Waiver Benefit master_reference_codes_in_endorsements: DTT00001; DTT00002 observed_dated_endorsements: 1 July 2025; 1 January 2015 version_boundary_note: Attachment dates and reference-code digits are not a base-edition date, complete amendment inventory, or evidence of current use. documentary_name_change_bridge: In-file notice says name changed to Sun Life Malaysia Takaful Berhad effective 19 August 2013; historical and renamed issuer observations remain separate. | X33: English 2025 endorsement p1 is DTT00001 while Malay p2 is DTT00002; p45 earlier endorsement covers both. Multi-reference/language correspondence remains unresolved; do not force a single identity. Historical issuer is supported by in-file name-change bridge only, not independent registry verification. Base edition, complete intervening amendment/language boundaries and schedules remain unverified. Adjacent physical p49/p50 jump from printed 2 to 4 of 27. The intervening schedule is not established; do not infer package completeness. | Z33: English 2025 endorsement p1 is DTT00001 while Malay p2 is DTT00002; p45 earlier endorsement covers both. Multi-reference/language correspondence remains unresolved; do not force a single identity. Historical issuer is supported by in-file name-change bridge only, not independent registry verification. Base edition, complete intervening amendment/language boundaries and schedules remain unverified. Adjacent physical p49/p50 jump from printed 2 to 4 of 27. The intervening schedule is not established; do not infer package completeness. | AA33: =HYPERLINK("https://chatgpt.com/api/library/files/libfile_f096861615788191b2089dd752505c74/download","B16私有元数据包") -> B16私有元数据包 | AB33: https://www.sunlifemalaysia.com/client-care/downloads/ | AC33: https://www.sunlifemalaysia.com/getContentAsset/44122011-f383-4910-8b82-bb755b3ca4b2/826411a5-9a44-43a6-8410-a7ad95da6d70/3-Decreasing-Term-Takaful_Master-Contract-Website-_0725.pdf?language=en | AD33: 46321.333 | AE33: 46321.346 | AF33: 46321.367 | AG33: B16-MY-022:accepted-role-only:20261026 | AH33: =IF(AND(AI33="匹配",LEN(V33)=64,J33<>"",L33<>"",K33>0,M33>0,AD33>0,AE33>0,AF33>0,AG33<>"",N33="待全文",O33=0,P33=0,Q33+R33+S33=1),"角色已验收","需检查证据") -> 角色已验收 | AI33: =IF(COUNTIF($A$2:$A$91,A33)=1,"匹配","缺范围或重复") -> 匹配
A34: B16-MY-023 | B34: B16 | C34: MY | D34: Sun Life Malaysia Takaful Berhad | E34: Group Term Financing Takaful Master Contract (GTFT 2015) - for certificate issued after 2015 | F34: 主角色提议 | G34: main_contract_with_endorsements | H34: 57 | I34: 57 | J34: 1, 2, 10, 11, 12, 13, 18, 19, 20, 21, 22, 25, 57 | K34: 13 | L34: 1, 10, 13, 19, 20, 21, 22, 25 | M34: 8 | N34: 待全文 | O34: 0 | P34: 0 | Q34: =IF(F34="主角色提议",1,0) -> 1 | R34: =IF(F34="非合同CIS",1,0) -> 0 | S34: =IF(F34="映射保留",1,0) -> 0 | T34: 1 | U34: regional-20261025-ca4facc39d0f8c18 | V34: ca4facc39d0f8c1884e396fa01033ccc4af5c9cc3ee5748ca1f3fc1c185aad02 | W34: base_issuer_in_operative_body: Sun Life Malaysia Takaful Berhad endorsement_issuer: Sun Life Malaysia Takaful Berhad product_name: Group Term Financing Takaful (GTFT 2015) master_reference_codes_in_endorsements: GTFT0315 observed_dated_endorsements: 1 July 2025; 1 July 2020; 1 July 2019 version_boundary_note: Attachment dates and reference-code digits are not a base-edition date, complete amendment inventory, or evidence of current use. | X34: Source label for certificate issued after 2015 is not independently established by these anchors; GTFT2015 is an observed title, not a current-adoption statement. Base edition, complete intervening amendment/language boundaries and schedules remain unverified. Adjacent physical p20/p21 jump from printed 2 to 4 of 22. Schedule presence/completeness remains unproved. | AA34: =HYPERLINK("https://chatgpt.com/api/library/files/libfile_f096861615788191b2089dd752505c74/download","B16私有元数据包") -> B16私有元数据包 | AB34: https://www.sunlifemalaysia.com/client-care/downloads/ | AC34: https://www.sunlifemalaysia.com/getContentAsset/2a56e4bb-5085-43d3-99c3-f12bf7d9b5f9/826411a5-9a44-43a6-8410-a7ad95da6d70/4-Master-Contract_GTFT-2015-From-website-_0725.pdf?language=en | AD34: 46321.333 | AE34: 46321.346 | AF34: 46321.367 | AG34: B16-MY-023:accepted-role-only:20261026 | AH34: =IF(AND(AI34="匹配",LEN(V34)=64,J34<>"",L34<>"",K34>0,M34>0,AD34>0,AE34>0,AF34>0,AG34<>"",N34="待全文",O34=0,P34=0,Q34+R34+S34=1),"角色已验收","需检查证据") -> 角色已验收 | AI34: =IF(COUNTIF($A$2:$A$91,A34)=1,"匹配","缺范围或重复") -> 匹配
A35: B16-MY-024 | B35: B16 | C35: MY | D35: Sun Life Malaysia Takaful Berhad | E35: Group Mortgage Reducing Term Takaful Master Contract (MRTT 2015) | F35: 主角色提议 | G35: main_contract_with_endorsements | H35: 69 | I35: 69 | J35: 1, 2, 6, 7, 8, 9, 25, 27, 28, 30, 69 | K35: 11 | L35: 1, 2, 7, 25, 27, 28, 30 | M35: 7 | N35: 待全文 | O35: 0 | P35: 0 | Q35: =IF(F35="主角色提议",1,0) -> 1 | R35: =IF(F35="非合同CIS",1,0) -> 0 | S35: =IF(F35="映射保留",1,0) -> 0 | T35: 1 | U35: regional-20261025-0de2a08b0aedd8a5 | V35: 0de2a08b0aedd8a57e4d5d582d0c977ba84957cbedaf9c6c72572e8ee954191c | W35: base_issuer_in_operative_body: Sun Life Malaysia Takaful Berhad endorsement_issuer: Sun Life Malaysia Takaful Berhad product_name: Group Mortgage Reducing Term Takaful (MRTT 2015) master_reference_codes_in_endorsements: MTTC0615; MTTI0615; MTTV0615 observed_dated_endorsements: 6 December 2025; 1 June 2021 version_boundary_note: Attachment dates and reference-code digits are not a base-edition date, complete amendment inventory, or evidence of current use. | X35: English p1 points to MRTT003 general conditions, Malay p2 points to MRTT002 benefit provisions; reconcile amendment correspondence before substantive use. p25 includes additional reference MTTV0615; no split into independently established products. Base edition, complete intervening amendment/language boundaries and schedules remain unverified. | AA35: =HYPERLINK("https://chatgpt.com/api/library/files/libfile_f096861615788191b2089dd752505c74/download","B16私有元数据包") -> B16私有元数据包 | AB35: https://www.sunlifemalaysia.com/client-care/downloads/ | AC35: https://www.sunlifemalaysia.com/getContentAsset/3d58d3d4-afe9-46a8-ae96-923de127a2ce/826411a5-9a44-43a6-8410-a7ad95da6d70/5-Group-Mortgage-Reducing-Term-Takaful-Master-Contract-MRTT-2015-_1225.pdf?language=en | AD35: 46321.333 | AE35: 46321.346 | AF35: 46321.367 | AG35: B16-MY-024:accepted-role-only:20261026 | AH35: =IF(AND(AI35="匹配",LEN(V35)=64,J35<>"",L35<>"",K35>0,M35>0,AD35>0,AE35>0,AF35>0,AG35<>"",N35="待全文",O35=0,P35=0,Q35+R35+S35=1),"角色已验收","需检查证据") -> 角色已验收 | AI35: =IF(COUNTIF($A$2:$A$91,A35)=1,"匹配","缺范围或重复") -> 匹配
A36: B16-MY-025 | B36: B16 | C36: MY | D36: Sun Life Malaysia Takaful Berhad | E36: Group Mortgage Reducing Term Takaful Master Contract (MRTT 2015) - Business Financing | F36: 主角色提议 | G36: main_contract_with_endorsements | H36: 67 | I36: 67 | J36: 1, 2, 4, 5, 6, 7, 25, 27, 28, 30, 67 | K36: 11 | L36: 1, 2, 4, 5, 25, 27, 28, 30 | M36: 8 | N36: 待全文 | O36: 0 | P36: 0 | Q36: =IF(F36="主角色提议",1,0) -> 1 | R36: =IF(F36="非合同CIS",1,0) -> 0 | S36: =IF(F36="映射保留",1,0) -> 0 | T36: 1 | U36: regional-20261025-704b1f110c6e6a8a | V36: 704b1f110c6e6a8a3ceba387a92952c671746f922ad51697ea899ace9ace8197 | W36: base_issuer_in_operative_body: Sun Life Malaysia Takaful Berhad endorsement_issuer: Sun Life Malaysia Takaful Berhad product_name: Group Mortgage Reducing Term Takaful (MRTT 2015) - Business Financing master_reference_codes_in_endorsements: GBTC0615; GBTI0615 master_holder: CIMB Bank Berhad and CIMB Islamic Bank Berhad (p4 endorsement) observed_dated_endorsements: 6 December 2025; 27 June 2022; 1 June 2021; 1 June 2018 version_boundary_note: Attachment dates and reference-code digits are not a base-edition date, complete amendment inventory, or evidence of current use. | X36: English p1 points to MRTT003 general conditions, Malay p2 points to MRTT002 benefit provisions; reconcile amendment correspondence before substantive use. Master-holder pair is observed in p4 endorsement, not a complete individual schedule; no split into independent products. Base edition, complete intervening amendment/language boundaries and schedules remain unverified. | AA36: =HYPERLINK("https://chatgpt.com/api/library/files/libfile_f096861615788191b2089dd752505c74/download","B16私有元数据包") -> B16私有元数据包 | AB36: https://www.sunlifemalaysia.com/client-care/downloads/ | AC36: https://www.sunlifemalaysia.com/getContentAsset/d2f03a81-48f0-4601-973d-78a2c9cd5500/826411a5-9a44-43a6-8410-a7ad95da6d70/6-Group-Mortgage-Reducing-Term-Takaful-Master-Contract-MRTT-2015-BF-_1225.pdf?language=en | AD36: 46321.333 | AE36: 46321.346 | AF36: 46321.367 | AG36: B16-MY-025:accepted-role-only:20261026 | AH36: =IF(AND(AI36="匹配",LEN(V36)=64,J36<>"",L36<>"",K36>0,M36>0,AD36>0,AE36>0,AF36>0,AG36<>"",N36="待全文",O36=0,P36=0,Q36+R36+S36=1),"角色已验收","需检查证据") -> 角色已验收 | AI36: =IF(COUNTIF($A$2:$A$91,A36)=1,"匹配","缺范围或重复") -> 匹配
A37: B16-MY-026 | B37: B16 | C37: MY | D37: Sun Life Malaysia Takaful Berhad | E37: Mortgage Reducing Term Takaful Master Contract - Bank Rakyat (Cert. after 2015) | F37: 主角色提议 | G37: main_contract_with_endorsements | H37: 48 | I37: 48 | J37: 1, 2, 7, 8, 9, 10, 12, 14, 15, 20, 48 | K37: 11 | L37: 1, 9, 12, 14, 15, 20 | M37: 6 | N37: 待全文 | O37: 0 | P37: 0 | Q37: =IF(F37="主角色提议",1,0) -> 1 | R37: =IF(F37="非合同CIS",1,0) -> 0 | S37: =IF(F37="映射保留",1,0) -> 0 | T37: 1 | U37: regional-20261025-9e859a0e754b82f0 | V37: 9e859a0e754b82f00f4439f52fa27a905585fa3caf49229112f59fab3698f2cf | W37: base_issuer_in_operative_body: Sun Life Malaysia Takaful Berhad endorsement_issuer: Sun Life Malaysia Takaful Berhad product_name: Group Mortgage Reducing Term Takaful (MRTT) master_reference_codes_in_endorsements: MTTR0315 observed_dated_endorsements: 1 July 2020; 1 July 2019 version_boundary_note: Attachment dates and reference-code digits are not a base-edition date, complete amendment inventory, or evidence of current use. | X37: Bank Rakyat and certificate-after-2015 are frozen/source labels; sampled base refers holder to an unverified schedule and does not independently establish that bank/date boundary. Base edition, complete intervening amendment/language boundaries and schedules remain unverified. | AA37: =HYPERLINK("https://chatgpt.com/api/library/files/libfile_f096861615788191b2089dd752505c74/download","B16私有元数据包") -> B16私有元数据包 | AB37: https://www.sunlifemalaysia.com/client-care/downloads/ | AC37: https://www.sunlifemalaysia.com/getContentAsset/1a01ca6b-7e09-4701-85bc-73feb4fbaf8e/826411a5-9a44-43a6-8410-a7ad95da6d70/10a.pdf | AD37: 46321.333 | AE37: 46321.346 | AF37: 46321.367 | AG37: B16-MY-026:accepted-role-only:20261026 | AH37: =IF(AND(AI37="匹配",LEN(V37)=64,J37<>"",L37<>"",K37>0,M37>0,AD37>0,AE37>0,AF37>0,AG37<>"",N37="待全文",O37=0,P37=0,Q37+R37+S37=1),"角色已验收","需检查证据") -> 角色已验收 | AI37: =IF(COUNTIF($A$2:$A$91,A37)=1,"匹配","缺范围或重复") -> 匹配
